Workbook

Sheet Pendentes
A1: Data | B1: Ticket | C1: Vendedor | D1: Cliente | E1: Produto | F1: TipoReceita | G1: Qtde | H1: VlrUnitário | I1: VlrTotal | J1: Vlr Meta | K1: %Comissão | L1: %ComissãoSupervisor | M1: Base | N1: ComissãoVendedor | O1: ComissãoSupervisor | P1: Clicksign | Q1: Contrato_Termo Aditivo | R1: Obs | S1: Parcelas | T1: Data Contrato | U1: Contrato | V1: SDR_RESPONSÁVEL
A2: 46147 | B2: 141516 | C2: Rayssa Karapeticov | D2: Zein | E2: loja B2B | F2: Mensalidade | G2: 1 | H2: 3001.35 | I2: =vendas2026[[#This Row],[Qtde]]*vendas2026[[#This Row],[VlrUnitário]] -> 21060 | J2: =(vendas2026[[#This Row],[VlrTotal]]*0.2)+vendas2026[[#This Row],[VlrTotal]] -> 21404.52 | K2: 1 | L2: =vendas2026[[#This Row],[%Comissão]]*0.25 -> 0.0175 | M2: Sim | N2: =vendas2026[[#This Row],[VlrTotal]]*vendas2026[[#This Row],[%Comissão]] -> 1248.597 | O2: =vendas2026[[#This Row],[VlrTotal]]*vendas2026[[#This Row],[%ComissãoSupervisor]] -> 0 | P2: Feito | Q2: Feito | S2: 1 | T2: 46156 | U2: Pendente | V2: Rayssa Karapeticov
A3: 46154 | B3: 142403 | C3: Rayssa Karapeticov | D3: Maquimp | E3: ERP | F3: Treinamentos e Implantações | G3: 280 | H3: 210 | I3: =vendas2026[[#This Row],[Qtde]]*vendas2026[[#This Row],[VlrUnitário]] -> 840 | J3: =vendas2026[[#This Row],[VlrTotal]] -> 840 | K3: 0.07 | L3: =vendas2026[[#This Row],[%Comissão]]*0.25 -> 0.25 | M3: Não | N3: =vendas2026[[#This Row],[VlrTotal]]*vendas2026[[#This Row],[%Comissão]] -> 840 | O3: =vendas2026[[#This Row],[VlrTotal]]*vendas2026[[#This Row],[%ComissãoSupervisor]] -> 0 | P3: Feito | Q3: Feito | S3: 10 | U3: Pendente | V3: Rayssa Karapeticov
A4: 46154 | B4: 142403 | C4: Rayssa Karapeticov | D4: Maquimp | E4: ERP | F4: Mensalidade | G4: 14 | H4: 275.82 | I4: =vendas2026[[#This Row],[Qtde]]*vendas2026[[#This Row],[VlrUnitário]] -> 7999.8 | J4: =vendas2026[[#This Row],[VlrTotal]] -> 7999.8 | K4: 1 | L4: =vendas2026[[#This Row],[%Comissão]]*0.25 -> 0.016675 | M4: Não | N4: =vendas2026[[#This Row],[VlrTotal]]*vendas2026[[#This Row],[%Comissão]] -> 533.58666 | O4: =vendas2026[[#This Row],[VlrTotal]]*vendas2026[[#This Row],[%ComissãoSupervisor]] -> 133.39667 | P4: Feito | Q4: Feito | S4: 1 | U4: Pendente | V4: Rayssa Karapeticov
A5: 46154 | B5: 142403 | C5: Rayssa Karapeticov | D5: Maquimp | E5: Telemarketing | F5: Mensalidade | G5: 1 | H5: 320.76 | I5: =vendas2026[[#This Row],[Qtde]]*vendas2026[[#This Row],[VlrUnitário]] -> 986.7 | J5: =vendas2026[[#This Row],[VlrTotal]] -> 986.7 | K5: 1 | L5: =vendas2026[[#This Row],[%Comissão]]*0.25 -> 0.25 | M5: Não | N5: =vendas2026[[#This Row],[VlrTotal]]*vendas2026[[#This Row],[%Comissão]] -> 986.7 | O5: =vendas2026[[#This Row],[VlrTotal]]*vendas2026[[#This Row],[%ComissãoSupervisor]] -> 246.675 | P5: Feito | Q5: Feito | S5: 1 | U5: Pendente | V5: Rayssa Karapeticov

Sheet 2026
A1: Data | B1: Ticket | C1: Vendedor | D1: Cliente | E1: Produto | F1: TipoReceita | G1: Qtde | H1: VlrUnitário | I1: VlrTotal | J1: Vlr Meta | K1: %Comissão | L1: %ComissãoSupervisor | M1: Base | N1: ComissãoVendedor | O1: ComissãoSupervisor | P1: Clicksign | Q1: Contrato_Termo Aditivo | R1: Obs | S1: Parcelas | T1: Data Contrato | U1: Contrato | V1: SDR_RESPONSÁVEL
A2: 46027 | B2: 133837 | C2: Paulo Souza | D2: PlastCap | E2: Treinamento | F2: Treinamentos e Implantações | G2: 180 | H2: 117 | I2: 17837.1 | K2: 0.07 | L2: 0 | M2: Sim | N2: 1248.597 | O2: 0 | P2: Feito | Q2: Feito | S2: 12 | U2: Assinado | V2: Paulo Souza
A3: 46027 | B3: 133837 | C3: Paulo Souza | D3: PlastCap | E3: ERP-PDV | F3: Mensalidade | G3: 3 | H3: 280 | I3: 840 | K3: 1 | L3: 0 | M3: Sim | N3: 840 | O3: 0 | P3: Feito | Q3: Feito | S3: 1 | U3: Assinado | V3: Paulo Souza
A4: 46027 | B4: 135649 | C4: Rayssa Karapeticov | D4: MB Plasticos | E4: Treinamento | F4: Treinamentos e Implantações | G4: 60 | H4: 133.33 | I4: =vendas2026[[#This Row],[Qtde]]*vendas2026[[#This Row],[VlrUnitário]] -> 7999.8 | K4: 0.0667 | L4: =vendas2026[[#This Row],[%Comissão]]*0.25 -> 0.016675 | M4: Sim | N4: =vendas2026[[#This Row],[VlrTotal]]*vendas2026[[#This Row],[%Comissão]] -> 533.58666 | O4: =vendas2026[[#This Row],[VlrTotal]]*vendas2026[[#This Row],[%ComissãoSupervisor]] -> 133.39667 | P4: Feito | Q4: Feito | S4: 3 | U4: Assinado | V4: Rayssa Karapeticov
A5: 46027 | B5: 135649 | C5: Rayssa Karapeticov | D5: MB Plasticos | E5: AFV Proposta WEB | F5: Mensalidade | G5: 78 | H5: 12.65 | I5: =vendas2026[[#This Row],[VlrUnitário]]*vendas2026[[#This Row],[Qtde]] -> 986.7 | K5: 1 | L5: =vendas2026[[#This Row],[%Comissão]]*0.25 -> 0.25 | M5: Sim | N5: =vendas2026[[#This Row],[VlrTotal]]*vendas2026[[#This Row],[%Comissão]] -> 986.7 | O5: =vendas2026[[#This Row],[VlrTotal]]*vendas2026[[#This Row],[%ComissãoSupervisor]] -> 246.675 | P5: Feito | Q5: Feito | S5: 1 | U5: Assinado | V5: Rayssa Karapeticov
A6: 46034 | B6: 134739 | C6: Rayssa Karapeticov | D6: Dolce Home | E6: Melhoria | F6: Melhoria | G6: 6 | H6: 158.401 | I6: =vendas2026[[#This Row],[VlrUnitário]]*vendas2026[[#This Row],[Qtde]] -> 950.406 | K6: 0.007 | L6: =vendas2026[[#This Row],[%Comissão]]*0.25 -> 0.00175 | M6: Sim | N6: =vendas2026[[#This Row],[VlrTotal]]*vendas2026[[#This Row],[%Comissão]] -> 6.652842 | O6: =vendas2026[[#This Row],[VlrTotal]]*vendas2026[[#This Row],[%ComissãoSupervisor]] -> 1.6632105 | P6: Não tem | Q6: não tem | S6: 1 | U6: não tem | V6: Rayssa Karapeticov
A7: 46034 | B7: 136315 | C7: Paulo Souza | D7: Akitem | E7: CNPJ | F7: CDU | G7: 1 | H7: 15053.87 | I7: =vendas2026[[#This Row],[VlrUnitário]]*vendas2026[[#This Row],[Qtde]] -> 15053.87 | K7: 0.07 | L7: 0 | M7: Sim | N7: =vendas2026[[#This Row],[VlrTotal]]*vendas2026[[#This Row],[%Comissão]] -> 1053.7709 | O7: =vendas2026[[#This Row],[VlrTotal]]*vendas2026[[#This Row],[%ComissãoSupervisor]] -> 0 | P7: Feito | Q7: Feito | S7: 6 | U7: Assinado | V7: Paulo Souza
A8: 46034 | B8: 136315 | C8: Paulo Souza | D8: Akitem | E8: ERP | F8: Mensalidade | G8: 1 | H8: 275.62 | I8: =vendas2026[[#This Row],[VlrUnitário]]*vendas2026[[#This Row],[Qtde]] -> 275.62 | K8: 1 | L8: 0 | M8: Sim | N8: =vendas2026[[#This Row],[VlrTotal]]*vendas2026[[#This Row],[%Comissão]] -> 275.62 | O8: =vendas2026[[#This Row],[VlrTotal]]*vendas2026[[#This Row],[%ComissãoSupervisor]] -> 0 | P8: Feito | Q8: Feito | S8: 1 | U8: Assinado | V8: Paulo Souza
A9: 46043 | B9: 132374 | C9: Rayssa Karapeticov | D9: Keita | E9: Treinamento | F9: Treinamentos e Implantações | G9: 94 | H9: 178.5 | I9: =vendas2026[[#This Row],[VlrUnitário]]*vendas2026[[#This Row],[Qtde]] -> 16779 | K9: 0.0667 | L9: =vendas2026[[#This Row],[%Comissão]]*0.25 -> 0.016675 | M9: Sim | N9: =vendas2026[[#This Row],[VlrTotal]]*vendas2026[[#This Row],[%Comissão]] -> 1119.1593 | O9: =vendas2026[[#This Row],[VlrTotal]]*vendas2026[[#This Row],[%ComissãoSupervisor]] -> 279.78983 | P9: Não tem | Q9: não tem | S9: 10 | U9: Assinado | V9: Rayssa Karapeticov
A10: 46043 | B10: 132678 | C10: Junior Lopes | D10: Amilplast | E10: Treinamento | F10: Treinamentos e Implantações | G10: 270 | H10: 190 | I10: =G10*H10 -> 51300 | K10: 0.07 | L10: =K10*0.25 -> 0.0175 | M10: Não | N10: =(K10*I10) -> 3591 | O10: =I10*L10 -> 897.75 | P10: Feito | Q10: Feito | S10: 10 | U10: Assinado | V10: Junior Lopes
A11: 46043 | B11: 132678 | C11: Junior Lopes | D11: Amilplast | E11: ERP | F11: Mensalidade | G11: 5 | H11: 275.62 | I11: =G11*H11 -> 1378.1 | K11: 1 | L11: =K11*0.25 -> 0.25 | M11: Não | N11: =(K11*I11) -> 1378.1 | O11: =I11*L11 -> 344.525 | P11: Feito | Q11: Feito | S11: 1 | U11: Assinado | V11: Junior Lopes
A12: 46043 | B12: 132678 | C12: Junior Lopes | D12: Amilplast | E12: MDE | F12: Mensalidade | G12: 1 | H12: 356.4 | I12: =G12*H12 -> 356.4 | K12: 1 | L12: =K12*0.25 -> 0.25 | M12: Não | N12: =(K12*I12) -> 356.4 | O12: =I12*L12 -> 89.1 | P12: Feito | Q12: Feito | S12: 1 | U12: Assinado | V12: Junior Lopes
A13: 46043 | B13: 136662 | C13: Rayssa Karapeticov | D13: Nixhouse | E13: Treinamento | F13: Treinamentos e Implantações | G13: 10 | H13: 210 | I13: =G13*H13 -> 2100 | K13: 0.07 | L13: =K13*0.25 -> 0.0175 | M13: Sim | N13: =(K13*I13) -> 147 | O13: =I13*L13 -> 36.75 | P13: Não tem | Q13: não tem | S13: 4 | U13: não tem | V13: Rayssa Karapeticov
A14: 46043 | B14: 136717,136720,136721 | C14: Paulo Souza | D14: NVT Importadora | E14: ERP | F14: Treinamentos e Implantações | G14: 240 | H14: 200 | I14: =G14*H14 -> 48000 | K14: 0.07 | L14: 0 | M14: Não | N14: =(K14*I14) -> 3360 | O14: =I14*L14 -> 0 | P14: Feito | Q14: Feito | S14: 6 | U14: Assinado | V14: Paulo Souza
A15: 46043 | B15: 136717,136720,136721 | C15: Paulo Souza | D15: NVT Importadora | E15: BI | F15: CDU | G15: 1 | H15: 8100 | I15: =G15*H15 -> 8100 | K15: 0.07 | L15: 0 | M15: Não | N15: =(K15*I15) -> 567 | O15: =I15*L15 -> 0 | P15: Feito | Q15: Feito | S15: 6 | U15: Assinado | V15: Paulo Souza
A16: 46043 | B16: 136717,136720,136721 | C16: Paulo Souza | D16: NVT Importadora | E16: CLOUD | F16: CDU | G16: 1 | H16: 1600 | I16: =G16*H16 -> 1600 | K16: 0.07 | L16: 0 | M16: Não | N16: =(K16*I16) -> 112 | O16: =I16*L16 -> 0 | P16: Feito | Q16: Feito | S16: 6 | U16: Assinado | V16: Paulo Souza
A17: 46043 | B17: 136717,136720,136721 | C17: Paulo Souza | D17: NVT Importadora | E17: ERP | F17: Mensalidade | G17: 8 | H17: 250 | I17: =G17*H17 -> 2000 | K17: 1 | L17: 0 | M17: Não | N17: =(K17*I17) -> 2000 | O17: =I17*L17 -> 0 | P17: Feito | Q17: Feito | S17: 1 | U17: Assinado | V17: Paulo Souza
A18: 46043 | B18: 136717,136720,136721 | C18: Paulo Souza | D18: NVT Importadora | E18: WMS | F18: Mensalidade | G18: 4 | H18: 100 | I18: =G18*H18 -> 400 | K18: 1 | L18: 0 | M18: Não | N18: =(K18*I18) -> 400 | O18: =I18*L18 -> 0 | P18: Feito | Q18: Feito | S18: 1 | U18: Assinado | V18: Paulo Souza
A19: 46043 | B19: 136717,136720,136721 | C19: Paulo Souza | D19: NVT Importadora | E19: BI | F19: Mensalidade | G19: 1 | H19: 1080 | I19: =G19*H19 -> 1080 | K19: 1 | L19: 0 | M19: Não | N19: =(K19*I19) -> 1080 | O19: =I19*L19 -> 0 | P19: Feito | Q19: Feito | S19: 1 | U19: Assinado | V19: Paulo Souza
A20: 46043 | B20: 136717,136720,136721 | C20: Paulo Souza | D20: NVT Importadora | E20: AFV | F20: Mensalidade | G20: 30 | H20: 90 | I20: =G20*H20 -> 2700 | K20: 1 | L20: 0 | M20: Não | N20: =(K20*I20) -> 2700 | O20: =I20*L20 -> 0 | P20: Feito | Q20: Feito | S20: 1 | U20: Assinado | V20: Paulo Souza
A21: 46043 | B21: 136717,136720,136721 | C21: Paulo Souza | D21: NVT Importadora | E21: MDE | F21: Mensalidade | G21: 1 | H21: 356.4 | I21: =G21*H21 -> 356.4 | K21: 1 | L21: 0 | M21: Não | N21: =(K21*I21) -> 356.4 | O21: =I21*L21 -> 0 | P21: Feito | Q21: Feito | S21: 1 | U21: Assinado | V21: Paulo Souza
A22: 46043 | B22: 136717,136720,136721 | C22: Paulo Souza | D22: NVT Importadora | E22: Envio Boleto Whatsapp | F22: Mensalidade | G22: 1 | H22: 197 | I22: =G22*H22 -> 197 | K22: 1 | L22: 0 | M22: Não | N22: =(K22*I22) -> 197 | O22: =I22*L22 -> 0 | P22: Feito | Q22: Feito | S22: 1 | U22: Assinado | V22: Paulo Souza
A23: 46043 | B23: 136717,136720,136721 | C23: Paulo Souza | D23: NVT Importadora | E23: CLOUD | F23: Mensalidade | G23: 1 | H23: 2524.72 | I23: =G23*H23 -> 2524.72 | K23: 1 | L23: 0 | M23: Não | N23: =(K23*I23) -> 2524.72 | O23: =I23*L23 -> 0 | P23: Feito | Q23: Feito | S23: 1 | U23: Assinado | V23: Paulo Souza
A24: 46043 | B24: 114426 | C24: Rayssa Karapeticov | D24: Culturama | E24: Treinamento | F24: Treinamentos e Implantações | G24: 11 | H24: 210 | I24: =G24*H24 -> 2310 | K24: 0.07 | L24: =K24*0.25 -> 0.0175 | M24: Sim | N24: =(K24*I24) -> 161.7 | O24: =I24*L24 -> 40.425 | P24: Não tem | Q24: não tem | S24: 6 | U24: não tem | V24: Rayssa Karapeticov
A25: 46043 | B25: 136856 | C25: Rayssa Karapeticov | D25: Rischiotto | E25: Adicional Intelipost | F25: Treinamentos e Implantações | G25: 16 | H25: 178.5 | I25: =G25*H25 -> 2856 | K25: 0.0667 | L25: =K25*0.25 -> 0.016675 | M25: Sim | N25: =(K25*I25) -> 190.4952 | O25: =I25*L25 -> 47.6238 | P25: Feito | Q25: Feito | S25: 6 | U25: Assinado | V25: Rayssa Karapeticov
A26: 46043 | B26: 136856 | C26: Rayssa Karapeticov | D26: Rischiotto | E26: Adicional Intelipost | F26: Mensalidade | G26: 1 | H26: 641.52 | I26: =G26*H26 -> 641.52 | K26: 1 | L26: =K26*0.25 -> 0.25 | M26: Sim | N26: =(K26*I26) -> 641.52 | O26: =I26*L26 -> 160.38 | P26: Feito | Q26: Feito | S26: 1 | U26: Assinado | V26: Rayssa Karapeticov
A27: 46044 | B27: 134776 | C27: Rayssa Karapeticov | D27: Qualyplast | E27: Melhoria | F27: Melhoria | G27: 8 | H27: 176 | I27: =G27*H27 -> 1408 | K27: 0.01 | L27: =K27*0.25 -> 0.0025 | M27: Sim | N27: =(K27*I27) -> 14.08 | O27: =I27*L27 -> 3.52 | P27: Não tem | Q27: não tem | S27: 3 | U27: não tem | V27: Rayssa Karapeticov
A28: 46044 | B28: 136981 | C28: Rayssa Karapeticov | D28: Dolce Home | E28: CNPJ | F28: CDU | G28: 1 | H28: 2419.18 | I28: =G28*H28 -> 2419.18 | K28: 0.06667 | L28: =K28*0.25 -> 0.0166675 | M28: Sim | N28: =(K28*I28) -> 161.28673 | O28: =I28*L28 -> 40.321683 | P28: Feito | Q28: Feito | S28: 6 | U28: Assinado | V28: Rayssa Karapeticov
A29: 46044 | B29: 136981 | C29: Rayssa Karapeticov | D29: Dolce Home | E29: CNPJ | F29: Treinamentos e Implantações | G29: 16 | H29: 178.68 | I29: =G29*H29 -> 2858.88 | K29: 0.0667 | L29: =K29*0.25 -> 0.016675 | M29: Sim | N29: =(K29*I29) -> 190.6873 | O29: =I29*L29 -> 47.671824 | P29: Feito | Q29: Feito | S29: 6 | U29: Assinado | V29: Rayssa Karapeticov
A30: 46048 | B30: 137055 | C30: Rayssa Karapeticov | D30: GP Inox | E30: BI | F30: CDU | G30: 1 | H30: 8100 | I30: =G30*H30 -> 8100 | K30: 0.07 | L30: =K30*0.25 -> 0.0175 | M30: Sim | N30: =(K30*I30) -> 567 | O30: =I30*L30 -> 141.75 | P30: Feito | Q30: Feito | S30: 6 | U30: Assinado | V30: Rayssa Karapeticov
A31: 46048 | B31: 137055 | C31: Rayssa Karapeticov | D31: GP Inox | E31: BI | F31: Mensalidade | G31: 1 | H31: 1070 | I31: =G31*H31 -> 1070 | K31: 1 | L31: =K31*0.25 -> 0.25 | M31: Sim | N31: =(K31*I31) -> 1070 | O31: =I31*L31 -> 267.5 | P31: Feito | Q31: Feito | S31: 1 | U31: Assinado | V31: Rayssa Karapeticov
A32: 46052 | B32: 137171 | C32: Junior Lopes | D32: RN Porcelanas | E32: ERP | F32: Treinamentos e Implantações | G32: 300 | H32: 166.67 | I32: =G32*H32 -> 50001 | K32: 0.05 | L32: =K32*0.25 -> 0.0125 | M32: Não | N32: =(K32*I32) -> 2500.05 | O32: =I32*L32 -> 625.0125 | P32: Feito | Q32: Feito | S32: 10 | U32: Assinado | V32: Junior Lopes
A33: 46052 | B33: 137171 | C33: Junior Lopes | D33: RN Porcelanas | E33: ERP | F33: Mensalidade | G33: 7 | H33: 240 | I33: =G33*H33 -> 1680 | K33: 1 | L33: =K33*0.25 -> 0.25 | M33: Não | N33: =(K33*I33) -> 1680 | O33: =I33*L33 -> 420 | P33: Feito | Q33: Feito | S33: 1 | U33: Assinado | V33: Junior Lopes
A34: 46052 | B34: 137171 | C34: Junior Lopes | D34: RN Porcelanas | E34: WMS | F34: Mensalidade | G34: 1 | H34: 140 | I34: =G34*H34 -> 140 | K34: 1 | L34: =K34*0.25 -> 0.25 | M34: Não | N34: =(K34*I34) -> 140 | O34: =I34*L34 -> 35 | P34: Feito | Q34: Feito | S34: 1 | U34: Assinado | V34: Junior Lopes
A35: 46052 | B35: 137171 | C35: Junior Lopes | D35: RN Porcelanas | E35: AFV | F35: Mensalidade | G35: 10 | H35: 88 | I35: =G35*H35 -> 880 | K35: 1 | L35: =K35*0.25 -> 0.25 | M35: Não | N35: =(K35*I35) -> 880 | O35: =I35*L35 -> 220 | P35: Feito | Q35: Feito | S35: 1 | U35: Assinado | V35: Junior Lopes
... A38: 46052 | B38: 137309 | C38: Rayssa Karapeticov | D38: ArcaPlast | E38: Melhoria | F38: Melhoria | G38: 5 | H38: 176 | I38: =G38*H38 -> 880 | K38: 0.01 | L38: =K38*0.25 -> 0.0025 | M38: Sim | N38: =(K38*I38) -> 8.8 | O38: =I38*L38 -> 2.2 | P38: Não tem | Q38: não tem | S38: 3 | U38: não tem | V38: Rayssa Karapeticov
A39: 46052 | B39: 125596 | C39: Paulo Souza | D39: Agua Sana | E39: Treinamento | F39: Treinamentos e Implantações | G39: 40 | H39: 180 | I39: =G39*H39 -> 7200 | K39: 0.07 | L39: 0 | M39: Sim | N39: =(K39*I39) -> 504 | O39: =I39*L39 -> 0 | P39: Não tem | Q39: não tem | S39: 6 | U39: não tem | V39: Paulo Souza
A40: 46055 | B40: 130904 | C40: Junior Lopes | D40: Tiago eletronicos | E40: B2B | F40: CDU | G40: 1 | H40: 22270 | I40: =vendas2026[[#This Row],[VlrUnitário]]*vendas2026[[#This Row],[Qtde]] -> 22270 | J40: =vendas2026[[#This Row],[VlrTotal]] -> 22270 | K40: 0.07 | L40: =vendas2026[[#This Row],[%Comissão]]*0.25 -> 0.0175 | M40: Não | N40: =vendas2026[[#This Row],[VlrTotal]]*vendas2026[[#This Row],[%Comissão]] -> 1558.9 | O40: =vendas2026[[#This Row],[VlrTotal]]*vendas2026[[#This Row],[%ComissãoSupervisor]] -> 389.725 | P40: Feito | Q40: Feito | S40: 10 | U40: Assinado | V40: Junior Lopes
A41: 46055 | B41: 130904 | C41: Junior Lopes | D41: Tiago eletronicos | E41: B2B | F41: Mensalidade | G41: 1 | H41: 3000 | I41: =vendas2026[[#This Row],[VlrUnitário]]*vendas2026[[#This Row],[Qtde]] -> 3000 | J41: =(vendas2026[[#This Row],[VlrTotal]]*0.2)+vendas2026[[#This Row],[VlrTotal]] -> 3600 | K41: 1 | L41: =vendas2026[[#This Row],[%Comissão]]*0.25 -> 0.25 | M41: Não | N41: =vendas2026[[#This Row],[VlrTotal]]*vendas2026[[#This Row],[%Comissão]] -> 3000 | O41: =vendas2026[[#This Row],[VlrTotal]]*vendas2026[[#This Row],[%ComissãoSupervisor]] -> 750 | P41: Feito | Q41: Feito | S41: 1 | U41: Assinado | V41: Junior Lopes
A42: 46055 | B42: 128860 | C42: Paulo Souza | D42: Sagol | E42: Treinamento | F42: Treinamentos e Implantações | G42: 110 | H42: 185 | I42: =vendas2026[[#This Row],[Qtde]]*vendas2026[[#This Row],[VlrUnitário]] -> 20350 | J42: 20350 | K42: 0.07 | L42: 0 | M42: Não | N42: =vendas2026[[#This Row],[VlrTotal]]*vendas2026[[#This Row],[%Comissão]] -> 1424.5 | O42: 0 | P42: Não tem | Q42: não tem | S42: 6 | U42: não tem | V42: Paulo Souza
A43: 46055 | B43: 128860 | C43: Paulo Souza | D43: Sagol | E43: AFV | F43: Mensalidade | G43: 15 | H43: 87 | I43: =vendas2026[[#This Row],[Qtde]]*vendas2026[[#This Row],[VlrUnitário]] -> 1305 | J43: 1305 | K43: 1 | L43: 0 | M43: Não | N43: =vendas2026[[#This Row],[VlrTotal]]*vendas2026[[#This Row],[%Comissão]] -> 1305 | O43: 0 | P43: Não tem | Q43: não tem | S43: 1 | U43: não tem | V43: Paulo Souza
A44: 46055 | B44: 128860 | C44: Paulo Souza | D44: Sagol | E44: AFV Preposto | F44: Mensalidade | G44: 10 | H44: 43.5 | I44: =vendas2026[[#This Row],[Qtde]]*vendas2026[[#This Row],[VlrUnitário]] -> 435 | J44: 435 | K44: 1 | L44: 0 | M44: Não | N44: =vendas2026[[#This Row],[VlrTotal]]*vendas2026[[#This Row],[%Comissão]] -> 435 | O44: 0 | P44: Não tem | Q44: não tem | S44: 1 | U44: não tem | V44: Paulo Souza
A45: 46059 | B45: 137190 | C45: Junior Lopes | D45: Conthey | E45: ERP | F45: Treinamentos e Implantações | G45: 290 | H45: 200 | I45: =vendas2026[[#This Row],[Qtde]]*vendas2026[[#This Row],[VlrUnitário]] -> 58000 | J45: 58000 | K45: 0.05 | L45: =vendas2026[[#This Row],[%Comissão]]*0.25 -> 0.0125 | M45: Não | N45: =vendas2026[[#This Row],[VlrTotal]]*vendas2026[[#This Row],[%Comissão]] -> 2900 | O45: =vendas2026[[#This Row],[VlrTotal]]*vendas2026[[#This Row],[%ComissãoSupervisor]] -> 725 | P45: Feito | Q45: Feito | S45: 12 | U45: Assinado | V45: Junior Lopes
A46: 46059 | B46: 137370 | C46: Junior Lopes | D46: Conthey | E46: ERP | F46: Mensalidade | G46: 20 | H46: 255 | I46: =vendas2026[[#This Row],[Qtde]]*vendas2026[[#This Row],[VlrUnitário]] -> 5100 | J46: 5100 | K46: 1 | L46: =vendas2026[[#This Row],[%Comissão]]*0.25 -> 0.25 | M46: Não | N46: =vendas2026[[#This Row],[VlrTotal]]*vendas2026[[#This Row],[%Comissão]] -> 5100 | O46: =vendas2026[[#This Row],[VlrTotal]]*vendas2026[[#This Row],[%ComissãoSupervisor]] -> 1275 | P46: Feito | Q46: Feito | S46: 1 | U46: Assinado | V46: Junior Lopes
A47: 46059 | B47: 137370 | C47: Junior Lopes | D47: Conthey | E47: AFV | F47: Mensalidade | G47: 20 | H47: 90 | I47: =vendas2026[[#This Row],[Qtde]]*vendas2026[[#This Row],[VlrUnitário]] -> 1800 | J47: 1800 | K47: 1 | L47: =vendas2026[[#This Row],[%Comissão]]*0.25 -> 0.25 | M47: Não | N47: =vendas2026[[#This Row],[VlrTotal]]*vendas2026[[#This Row],[%Comissão]] -> 1800 | O47: =vendas2026[[#This Row],[VlrTotal]]*vendas2026[[#This Row],[%ComissãoSupervisor]] -> 450 | P47: Feito | Q47: Feito | S47: 1 | U47: Assinado | V47: Junior Lopes
A48: 46059 | B48: 137370 | C48: Junior Lopes | D48: Conthey | E48: MDE | F48: Mensalidade | G48: 1 | H48: 330 | I48: =vendas2026[[#This Row],[Qtde]]*vendas2026[[#This Row],[VlrUnitário]] -> 330 | J48: 330 | K48: 1 | L48: =vendas2026[[#This Row],[%Comissão]]*0.25 -> 0.25 | M48: Não | N48: =vendas2026[[#This Row],[VlrTotal]]*vendas2026[[#This Row],[%Comissão]] -> 330 | O48: =vendas2026[[#This Row],[VlrTotal]]*vendas2026[[#This Row],[%ComissãoSupervisor]] -> 82.5 | P48: Feito | Q48: Feito | S48: 1 | U48: Assinado | V48: Junior Lopes
A49: 46059 | B49: 137739 | C49: Rayssa Karapeticov | D49: Textil Regimara | E49: BI | F49: CDU | G49: 1 | H49: 8100 | I49: =vendas2026[[#This Row],[Qtde]]*vendas2026[[#This Row],[VlrUnitário]] -> 8100 | J49: =(vendas2026[[#This Row],[VlrTotal]]*0.2)+vendas2026[[#This Row],[VlrTotal]] -> 9720 | K49: 0.25 | L49: =vendas2026[[#This Row],[%Comissão]]*0.25 -> 0.0625 | M49: Sim | N49: =vendas2026[[#This Row],[VlrTotal]]*vendas2026[[#This Row],[%Comissão]] -> 2025 | O49: =vendas2026[[#This Row],[VlrTotal]]*vendas2026[[#This Row],[%ComissãoSupervisor]] -> 506.25 | P49: Feito | Q49: Feito | S49: 6 | U49: Assinado | V49: Rayssa Karapeticov
A50: 46059 | B50: 137739 | C50: Rayssa Karapeticov | D50: Textil Regimara | E50: BI | F50: Mensalidade | G50: 1 | H50: 1080 | I50: =vendas2026[[#This Row],[Qtde]]*vendas2026[[#This Row],[VlrUnitário]] -> 1080 | J50: =(vendas2026[[#This Row],[VlrTotal]]*0.2)+vendas2026[[#This Row],[VlrTotal]] -> 1296 | K50: 1 | L50: =vendas2026[[#This Row],[%Comissão]]*0.25 -> 0.25 | M50: Sim | N50: =vendas2026[[#This Row],[VlrTotal]]*vendas2026[[#This Row],[%Comissão]] -> 1080 | O50: =vendas2026[[#This Row],[VlrTotal]]*vendas2026[[#This Row],[%ComissãoSupervisor]] -> 270 | P50: Feito | Q50: Feito | S50: 1 | U50: Assinado | V50: Rayssa Karapeticov
A51: 46059 | B51: 137720 | C51: Rayssa Karapeticov | D51: Shock Import | E51: AFV | F51: Mensalidade | G51: 5 | H51: 115 | I51: =vendas2026[[#This Row],[Qtde]]*vendas2026[[#This Row],[VlrUnitário]] -> 575 | J51: =(vendas2026[[#This Row],[VlrTotal]]*0.2)+vendas2026[[#This Row],[VlrTotal]] -> 690 | K51: 1 | L51: =vendas2026[[#This Row],[%Comissão]]*0.25 -> 0.25 | M51: Sim | N51: =vendas2026[[#This Row],[VlrTotal]]*vendas2026[[#This Row],[%Comissão]] -> 575 | O51: =vendas2026[[#This Row],[VlrTotal]]*vendas2026[[#This Row],[%ComissãoSupervisor]] -> 143.75 | P51: Feito | Q51: Feito | S51: 1 | U51: Assinado | V51: Rayssa Karapeticov
A52: 46059 | B52: 137481 | C52: Rayssa Karapeticov | D52: Kascao | E52: Treinamento | F52: Treinamentos e Implantações | G52: 8 | H52: 189 | I52: =vendas2026[[#This Row],[Qtde]]*vendas2026[[#This Row],[VlrUnitário]] -> 1512 | J52: =(vendas2026[[#This Row],[VlrTotal]]*0.2)+vendas2026[[#This Row],[VlrTotal]] -> 1814.4 | K52: 0.07 | L52: =vendas2026[[#This Row],[%Comissão]]*0.25 -> 0.0175 | M52: Sim | N52: =vendas2026[[#This Row],[VlrTotal]]*vendas2026[[#This Row],[%Comissão]] -> 105.84 | O52: =vendas2026[[#This Row],[VlrTotal]]*vendas2026[[#This Row],[%ComissãoSupervisor]] -> 26.46 | P52: Não tem | Q52: não tem | S52: 4 | U52: não tem | V52: Rayssa Karapeticov
A53: 46065 | B53: 138938 | C53: Junior Lopes | D53: Orbhes Colchoes | E53: AFV | F53: Treinamentos e Implantações | G53: 80 | H53: 212 | I53: =vendas2026[[#This Row],[Qtde]]*vendas2026[[#This Row],[VlrUnitário]] -> 16960 | J53: 16960 | K53: 0.07 | L53: =vendas2026[[#This Row],[%Comissão]]*0.25 -> 0.0175 | M53: Não | N53: =vendas2026[[#This Row],[VlrTotal]]*vendas2026[[#This Row],[%Comissão]] -> 1187.2 | O53: =vendas2026[[#This Row],[VlrTotal]]*vendas2026[[#This Row],[%ComissãoSupervisor]] -> 296.8 | P53: Feito | Q53: Feito | S53: 4 | U53: Assinado | V53: Junior Lopes
A54: 46065 | B54: 138938 | C54: Junior Lopes | D54: Orbhes Colchoes | E54: AFV | F54: Mensalidade | G54: 30 | H54: 109.25 | I54: =vendas2026[[#This Row],[Qtde]]*vendas2026[[#This Row],[VlrUnitário]] -> 3277.5 | J54: 3277.5 | K54: 1 | L54: =vendas2026[[#This Row],[%Comissão]]*0.25 -> 0.25 | M54: Não | N54: =vendas2026[[#This Row],[VlrTotal]]*vendas2026[[#This Row],[%Comissão]] -> 3277.5 | O54: =vendas2026[[#This Row],[VlrTotal]]*vendas2026[[#This Row],[%ComissãoSupervisor]] -> 819.375 | P54: Feito | Q54: Feito | S54: 1 | U54: Assinado | V54: Junior Lopes
A55: 46065 | B55: 128860 | C55: Paulo Souza | D55: Sagol | E55: Envio Boleto Whatsapp | F55: Mensalidade | G55: 1 | H55: 356.4 | I55: =vendas2026[[#This Row],[Qtde]]*vendas2026[[#This Row],[VlrUnitário]] -> 356.4 | J55: =(vendas2026[[#This Row],[VlrTotal]]*0.2)+vendas2026[[#This Row],[VlrTotal]] -> 427.68 | K55: 1 | L55: 0 | M55: Sim | N55: =vendas2026[[#This Row],[VlrTotal]]*vendas2026[[#This Row],[%Comissão]] -> 356.4 | O55: =vendas2026[[#This Row],[VlrTotal]]*vendas2026[[#This Row],[%ComissãoSupervisor]] -> 0 | P55: Feito | Q55: Feito | S55: 1 | U55: Assinado | V55: Paulo Souza
A56: 46066 | B56: 138101 | C56: Rayssa Karapeticov | D56: Univendas | E56: Treinamento | F56: Treinamentos e Implantações | G56: 24 | H56: 125 | I56: =vendas2026[[#This Row],[Qtde]]*vendas2026[[#This Row],[VlrUnitário]] -> 3000 | J56: =(vendas2026[[#This Row],[VlrTotal]]*0.2)+vendas2026[[#This Row],[VlrTotal]] -> 3600 | K56: 0.21 | L56: =vendas2026[[#This Row],[%Comissão]]*0.25 -> 0.0525 | M56: Sim | N56: =vendas2026[[#This Row],[VlrTotal]]*vendas2026[[#This Row],[%Comissão]] -> 630 | O56: =vendas2026[[#This Row],[VlrTotal]]*vendas2026[[#This Row],[%ComissãoSupervisor]] -> 157.5 | P56: Não tem | Q56: não tem | S56: 5 | U56: não tem | V56: Rayssa Karapeticov
A57: 46070 | B57: 135881...65 | C57: Rayssa Karapeticov | D57: Inga | E57: Melhoria | F57: Melhoria | G57: 236 | H57: 176 | I57: =vendas2026[[#This Row],[Qtde]]*vendas2026[[#This Row],[VlrUnitário]] -> 41536 | J57: =vendas2026[[#This Row],[VlrTotal]] -> 41536 | K57: 0.01 | L57: =vendas2026[[#This Row],[%Comissão]]*0.25 -> 0.0025 | M57: Sim | N57: =vendas2026[[#This Row],[VlrTotal]]*vendas2026[[#This Row],[%Comissão]] -> 415.36 | O57: =vendas2026[[#This Row],[VlrTotal]]*vendas2026[[#This Row],[%ComissãoSupervisor]] -> 103.84 | P57: Não tem | Q57: não tem | S57: 4 | U57: não tem | V57: Rayssa Karapeticov
A58: 46072 | B58: 135372 | C58: Rayssa Karapeticov | D58: Sagol | E58: Melhoria | F58: Melhoria | G58: 24 | H58: 176 | I58: =vendas2026[[#This Row],[Qtde]]*vendas2026[[#This Row],[VlrUnitário]] -> 4224 | J58: =vendas2026[[#This Row],[VlrTotal]] -> 4224 | K58: 0.01 | L58: =vendas2026[[#This Row],[%Comissão]]*0.25 -> 0.0025 | M58: Sim | N58: =vendas2026[[#This Row],[VlrTotal]]*vendas2026[[#This Row],[%Comissão]] -> 42.24 | O58: =vendas2026[[#This Row],[VlrTotal]]*vendas2026[[#This Row],[%ComissãoSupervisor]] -> 10.56 | P58: Não tem | Q58: não tem | S58: 3 | U58: não tem | V58: Rayssa Karapeticov
A59: 46076 | B59: 138313 | C59: Rayssa Karapeticov | D59: Universal Quimica | E59: CNPJ | F59: CDU | G59: 1 | H59: 3150.4 | I59: =vendas2026[[#This Row],[Qtde]]*vendas2026[[#This Row],[VlrUnitário]] -> 3150.4 | J59: =(vendas2026[[#This Row],[VlrTotal]]*0.2)+vendas2026[[#This Row],[VlrTotal]] -> 3780.48 | K59: 0.25 | L59: =vendas2026[[#This Row],[%Comissão]]*0.25 -> 0.0625 | M59: Sim | N59: =vendas2026[[#This Row],[VlrTotal]]*vendas2026[[#This Row],[%Comissão]] -> 787.6 | O59: =vendas2026[[#This Row],[VlrTotal]]*vendas2026[[#This Row],[%ComissãoSupervisor]] -> 196.9 | P59: Não tem | Q59: não tem | S59: 6 | U59: não tem | V59: Rayssa Karapeticov
A60: 46076 | B60: 138313 | C60: Rayssa Karapeticov | D60: Universal Quimica | E60: Treinamento | F60: Treinamentos e Implantações | G60: 40 | H60: 146.24 | I60: =vendas2026[[#This Row],[Qtde]]*vendas2026[[#This Row],[VlrUnitário]] -> 5849.6 | J60: =(vendas2026[[#This Row],[VlrTotal]]*0.2)+vendas2026[[#This Row],[VlrTotal]] -> 7019.52 | K60: 0.25 | L60: =vendas2026[[#This Row],[%Comissão]]*0.25 -> 0.0625 | M60: Sim | N60: =vendas2026[[#This Row],[VlrTotal]]*vendas2026[[#This Row],[%Comissão]] -> 1462.4 | O60: =vendas2026[[#This Row],[VlrTotal]]*vendas2026[[#This Row],[%ComissãoSupervisor]] -> 365.6 | P60: Não tem | Q60: não tem | S60: 6 | U60: não tem | V60: Rayssa Karapeticov
A61: 46078 | B61: 138540 ..138541 | C61: Paulo Souza | D61: Iracema | E61: ERP | F61: Treinamentos e Implantações | G61: 316 | H61: 200 | I61: =vendas2026[[#This Row],[Qtde]]*vendas2026[[#This Row],[VlrUnitário]] -> 63200 | J61: =vendas2026[[#This Row],[VlrTotal]] -> 63200 | K61: 0.07 | L61: 0 | M61: Não | N61: =vendas2026[[#This Row],[VlrTotal]]*vendas2026[[#This Row],[%Comissão]] -> 4424 | O61: =vendas2026[[#This Row],[VlrTotal]]*vendas2026[[#This Row],[%ComissãoSupervisor]] -> 0 | P61: Feito | Q61: Feito | S61: 6 | U61: Assinado | V61: Paulo Souza
A62: 46078 | B62: 138540 ..138541 | C62: Paulo Souza | D62: Iracema | E62: ERP | F62: CDU | G62: 1 | H62: 35502.9 | I62: =vendas2026[[#This Row],[Qtde]]*vendas2026[[#This Row],[VlrUnitário]] -> 35502.9 | J62: =vendas2026[[#This Row],[VlrTotal]] -> 35502.9 | K62: 0.25 | L62: 0 | M62: Não | N62: =vendas2026[[#This Row],[VlrTotal]]*vendas2026[[#This Row],[%Comissão]] -> 8875.725 | O62: =vendas2026[[#This Row],[VlrTotal]]*vendas2026[[#This Row],[%ComissãoSupervisor]] -> 0 | P62: Feito | Q62: Feito | S62: 6 | U62: Assinado | V62: Paulo Souza
A63: 46078 | B63: 138540 ..138541 | C63: Paulo Souza | D63: Iracema | E63: ERP | F63: Mensalidade | G63: 15 | H63: 275.62 | I63: =vendas2026[[#This Row],[Qtde]]*vendas2026[[#This Row],[VlrUnitário]] -> 4134.3 | J63: =vendas2026[[#This Row],[VlrTotal]] -> 4134.3 | K63: 1 | L63: 0 | M63: Não | N63: =vendas2026[[#This Row],[VlrTotal]]*vendas2026[[#This Row],[%Comissão]] -> 4134.3 | O63: =vendas2026[[#This Row],[VlrTotal]]*vendas2026[[#This Row],[%ComissãoSupervisor]] -> 0 | P63: Feito | Q63: Feito | S63: 1 | U63: Assinado | V63: Paulo Souza
A64: 46078 | B64: 138540 ..138541 | C64: Paulo Souza | D64: Iracema | E64: AFV | F64: Mensalidade | G64: 40 | H64: 115 | I64: =vendas2026[[#This Row],[Qtde]]*vendas2026[[#This Row],[VlrUnitário]] -> 4600 | J64: =vendas2026[[#This Row],[VlrTotal]] -> 4600 | K64: 1 | L64: 0 | M64: Não | N64: =vendas2026[[#This Row],[VlrTotal]]*vendas2026[[#This Row],[%Comissão]] -> 4600 | O64: =vendas2026[[#This Row],[VlrTotal]]*vendas2026[[#This Row],[%ComissãoSupervisor]] -> 0 | P64: Feito | Q64: Feito | S64: 1 | U64: Assinado | V64: Paulo Souza
A65: 46078 | B65: 138540 ..138541 | C65: Paulo Souza | D65: Iracema | E65: MDE | F65: Mensalidade | G65: 1 | H65: 356.4 | I65: =vendas2026[[#This Row],[Qtde]]*vendas2026[[#This Row],[VlrUnitário]] -> 356.4 | J65: =vendas2026[[#This Row],[VlrTotal]] -> 356.4 | K65: 1 | L65: 0 | M65: Não | N65: =vendas2026[[#This Row],[VlrTotal]]*vendas2026[[#This Row],[%Comissão]] -> 356.4 | O65: =vendas2026[[#This Row],[VlrTotal]]*vendas2026[[#This Row],[%ComissãoSupervisor]] -> 0 | P65: Feito | Q65: Feito | S65: 1 | U65: Assinado | V65: Paulo Souza
A66: 46078 | B66: 138540 ..138541 | C66: Paulo Souza | D66: Iracema | E66: BI | F66: Mensalidade | G66: 1 | H66: 1080 | I66: =vendas2026[[#This Row],[Qtde]]*vendas2026[[#This Row],[VlrUnitário]] -> 1080 | J66: =vendas2026[[#This Row],[VlrTotal]] -> 1080 | K66: 1 | L66: 0 | M66: Não | N66: =vendas2026[[#This Row],[VlrTotal]]*vendas2026[[#This Row],[%Comissão]] -> 1080 | O66: =vendas2026[[#This Row],[VlrTotal]]*vendas2026[[#This Row],[%ComissãoSupervisor]] -> 0 | P66: Feito | Q66: Feito | S66: 1 | U66: Assinado | V66: Paulo Souza
A67: 46078 | B67: 138540 ..138541 | C67: Paulo Souza | D67: Iracema | E67: WMS | F67: Mensalidade | G67: 5 | H67: 142.53 | I67: =vendas2026[[#This Row],[Qtde]]*vendas2026[[#This Row],[VlrUnitário]] -> 712.65 | J67: =vendas2026[[#This Row],[VlrTotal]] -> 712.65 | K67: 1 | L67: 0 | M67: Não | N67: =vendas2026[[#This Row],[VlrTotal]]*vendas2026[[#This Row],[%Comissão]] -> 712.65 | O67: =vendas2026[[#This Row],[VlrTotal]]*vendas2026[[#This Row],[%ComissãoSupervisor]] -> 0 | P67: Feito | Q67: Feito | S67: 1 | U67: Assinado | V67: Paulo Souza
A68: 46078 | B68: 138540 ..138541 | C68: Paulo Souza | D68: Iracema | E68: Contabil | F68: Mensalidade | G68: 1 | H68: 689 | I68: =vendas2026[[#This Row],[Qtde]]*vendas2026[[#This Row],[VlrUnitário]] -> 689 | J68: =vendas2026[[#This Row],[VlrTotal]] -> 689 | K68: 1 | L68: 0 | M68: Não | N68: =vendas2026[[#This Row],[VlrTotal]]*vendas2026[[#This Row],[%Comissão]] -> 689 | O68: =vendas2026[[#This Row],[VlrTotal]]*vendas2026[[#This Row],[%ComissãoSupervisor]] -> 0 | P68: Feito | Q68: Feito | S68: 1 | U68: Assinado | V68: Paulo Souza
A69: 46078 | B69: 138540 ..138541 | C69: Paulo Souza | D69: Iracema | E69: Rd Station | F69: Mensalidade | G69: 1 | H69: 712 | I69: =vendas2026[[#This Row],[Qtde]]*vendas2026[[#This Row],[VlrUnitário]] -> 712 | J69: =vendas2026[[#This Row],[VlrTotal]] -> 712 | K69: 1 | L69: 0 | M69: Não | N69: =vendas2026[[#This Row],[VlrTotal]]*vendas2026[[#This Row],[%Comissão]] -> 712 | O69: =vendas2026[[#This Row],[VlrTotal]]*vendas2026[[#This Row],[%ComissãoSupervisor]] -> 0 | P69: Feito | Q69: Feito | S69: 1 | U69: Assinado | V69: Paulo Souza
A70: 46078 | B70: 138575..138580 | C70: Paulo Souza | D70: Casart | E70: ERP | F70: Treinamentos e Implantações | G70: 196 | H70: 200 | I70: =vendas2026[[#This Row],[Qtde]]*vendas2026[[#This Row],[VlrUnitário]] -> 39200 | J70: =vendas2026[[#This Row],[VlrTotal]] -> 39200 | K70: 0.07 | L70: 0 | M70: Não | N70: =vendas2026[[#This Row],[VlrTotal]]*vendas2026[[#This Row],[%Comissão]] -> 2744 | O70: =vendas2026[[#This Row],[VlrTotal]]*vendas2026[[#This Row],[%ComissãoSupervisor]] -> 0 | P70: Feito | Q70: Feito | S70: 6 | U70: Assinado | V70: Paulo Souza
A71: 46078 | B71: 138575..138580 | C71: Paulo Souza | D71: Casart | E71: ERP | F71: CDU | G71: 1 | H71: 35502.9 | I71: =vendas2026[[#This Row],[Qtde]]*vendas2026[[#This Row],[VlrUnitário]] -> 35502.9 | J71: =vendas2026[[#This Row],[VlrTotal]] -> 35502.9 | K71: 0.25 | L71: 0 | M71: Não | N71: =vendas2026[[#This Row],[VlrTotal]]*vendas2026[[#This Row],[%Comissão]] -> 8875.725 | O71: =vendas2026[[#This Row],[VlrTotal]]*vendas2026[[#This Row],[%ComissãoSupervisor]] -> 0 | P71: Feito | Q71: Feito | S71: 6 | U71: Assinado | V71: Paulo Souza
A72: 46078 | B72: 138575..138580 | C72: Paulo Souza | D72: Casart | E72: ERP | F72: Mensalidade | G72: 12 | H72: 275.62 | I72: =vendas2026[[#This Row],[Qtde]]*vendas2026[[#This Row],[VlrUnitário]] -> 3307.44 | J72: =vendas2026[[#This Row],[VlrTotal]] -> 3307.44 | K72: 1 | L72: 0 | M72: Não | N72: =vendas2026[[#This Row],[VlrTotal]]*vendas2026[[#This Row],[%Comissão]] -> 3307.44 | O72: =vendas2026[[#This Row],[VlrTotal]]*vendas2026[[#This Row],[%ComissãoSupervisor]] -> 0 | P72: Feito | Q72: Feito | S72: 1 | U72: Assinado | V72: Paulo Souza
... A76: 46078 | B76: 138575..138580 | C76: Paulo Souza | D76: Casart | E76: Rd Station | F76: Mensalidade | G76: 1 | H76: 712 | I76: =vendas2026[[#This Row],[Qtde]]*vendas2026[[#This Row],[VlrUnitário]] -> 712 | J76: =vendas2026[[#This Row],[VlrTotal]] -> 712 | K76: 1 | L76: 0 | M76: Não | N76: =vendas2026[[#This Row],[VlrTotal]]*vendas2026[[#This Row],[%Comissão]] -> 712 | O76: =vendas2026[[#This Row],[VlrTotal]]*vendas2026[[#This Row],[%ComissãoSupervisor]] -> 0 | P76: Feito | Q76: Feito | S76: 1 | U76: Assinado | V76: Paulo Souza
A77: 46078 | B77: 138641 | C77: Paulo Souza | D77: Dinatale | E77: ERP | F77: Treinamentos e Implantações | G77: 316 | H77: 200 | I77: =vendas2026[[#This Row],[Qtde]]*vendas2026[[#This Row],[VlrUnitário]] -> 63200 | J77: =vendas2026[[#This Row],[VlrTotal]] -> 63200 | K77: 0.07 | L77: 0 | M77: Não | N77: =vendas2026[[#This Row],[VlrTotal]]*vendas2026[[#This Row],[%Comissão]] -> 4424 | O77: =vendas2026[[#This Row],[VlrTotal]]*vendas2026[[#This Row],[%ComissãoSupervisor]] -> 0 | P77: Feito | Q77: Feito | S77: 6 | U77: Assinado | V77: Paulo Souza
A78: 46078 | B78: 138641 | C78: Paulo Souza | D78: Dinatale | E78: ERP | F78: CDU | G78: 1 | H78: 35502.9 | I78: =vendas2026[[#This Row],[Qtde]]*vendas2026[[#This Row],[VlrUnitário]] -> 35502.9 | J78: =vendas2026[[#This Row],[VlrTotal]] -> 35502.9 | K78: 0.25 | L78: 0 | M78: Não | N78: =vendas2026[[#This Row],[VlrTotal]]*vendas2026[[#This Row],[%Comissão]] -> 8875.725 | O78: =vendas2026[[#This Row],[VlrTotal]]*vendas2026[[#This Row],[%ComissãoSupervisor]] -> 0 | P78: Feito | Q78: Feito | S78: 6 | U78: Assinado | V78: Paulo Souza
A79: 46078 | B79: 138641 | C79: Paulo Souza | D79: Dinatale | E79: ERP | F79: Mensalidade | G79: 30 | H79: 275.62 | I79: =vendas2026[[#This Row],[Qtde]]*vendas2026[[#This Row],[VlrUnitário]] -> 8268.6 | J79: =vendas2026[[#This Row],[VlrTotal]] -> 8268.6 | K79: 1 | L79: 0 | M79: Não | N79: =vendas2026[[#This Row],[VlrTotal]]*vendas2026[[#This Row],[%Comissão]] -> 8268.6 | O79: =vendas2026[[#This Row],[VlrTotal]]*vendas2026[[#This Row],[%ComissãoSupervisor]] -> 0 | P79: Feito | Q79: Feito | S79: 1 | U79: Assinado | V79: Paulo Souza
A80: 46078 | B80: 138641 | C80: Paulo Souza | D80: Dinatale | E80: AFV | F80: Mensalidade | G80: 60 | H80: 105 | I80: =vendas2026[[#This Row],[Qtde]]*vendas2026[[#This Row],[VlrUnitário]] -> 6300 | J80: =vendas2026[[#This Row],[VlrTotal]] -> 6300 | K80: 1 | L80: 0 | M80: Não | N80: =vendas2026[[#This Row],[VlrTotal]]*vendas2026[[#This Row],[%Comissão]] -> 6300 | O80: =vendas2026[[#This Row],[VlrTotal]]*vendas2026[[#This Row],[%ComissãoSupervisor]] -> 0 | P80: Feito | Q80: Feito | S80: 1 | U80: Assinado | V80: Paulo Souza
A81: 46078 | B81: 138641 | C81: Paulo Souza | D81: Dinatale | E81: MDE | F81: Mensalidade | G81: 1 | H81: 356.4 | I81: =vendas2026[[#This Row],[Qtde]]*vendas2026[[#This Row],[VlrUnitário]] -> 356.4 | J81: =vendas2026[[#This Row],[VlrTotal]] -> 356.4 | K81: 1 | L81: 0 | M81: Não | N81: =vendas2026[[#This Row],[VlrTotal]]*vendas2026[[#This Row],[%Comissão]] -> 356.4 | O81: =vendas2026[[#This Row],[VlrTotal]]*vendas2026[[#This Row],[%ComissãoSupervisor]] -> 0 | P81: Feito | Q81: Feito | S81: 1 | U81: Assinado | V81: Paulo Souza
A82: 46078 | B82: 138641 | C82: Paulo Souza | D82: Dinatale | E82: BI | F82: Mensalidade | G82: 1 | H82: 1080 | I82: =vendas2026[[#This Row],[Qtde]]*vendas2026[[#This Row],[VlrUnitário]] -> 1080 | J82: =vendas2026[[#This Row],[VlrTotal]] -> 1080 | K82: 1 | L82: 0 | M82: Não | N82: =vendas2026[[#This Row],[VlrTotal]]*vendas2026[[#This Row],[%Comissão]] -> 1080 | O82: =vendas2026[[#This Row],[VlrTotal]]*vendas2026[[#This Row],[%ComissãoSupervisor]] -> 0 | P82: Feito | Q82: Feito | S82: 1 | U82: Assinado | V82: Paulo Souza
A83: 46078 | B83: 138641 | C83: Paulo Souza | D83: Dinatale | E83: WMS | F83: Mensalidade | G83: 5 | H83: 142.56 | I83: =vendas2026[[#This Row],[Qtde]]*vendas2026[[#This Row],[VlrUnitário]] -> 712.8 | J83: =vendas2026[[#This Row],[VlrTotal]] -> 712.8 | K83: 1 | L83: 0 | M83: Não | N83: =vendas2026[[#This Row],[VlrTotal]]*vendas2026[[#This Row],[%Comissão]] -> 712.8 | O83: =vendas2026[[#This Row],[VlrTotal]]*vendas2026[[#This Row],[%ComissãoSupervisor]] -> 0 | P83: Feito | Q83: Feito | S83: 1 | U83: Assinado | V83: Paulo Souza
A84: 46078 | B84: 138641 | C84: Paulo Souza | D84: Dinatale | E84: Contabil | F84: Mensalidade | G84: 1 | H84: 689 | I84: =vendas2026[[#This Row],[Qtde]]*vendas2026[[#This Row],[VlrUnitário]] -> 689 | J84: =vendas2026[[#This Row],[VlrTotal]] -> 689 | K84: 1 | L84: 0 | M84: Não | N84: =vendas2026[[#This Row],[VlrTotal]]*vendas2026[[#This Row],[%Comissão]] -> 689 | O84: =vendas2026[[#This Row],[VlrTotal]]*vendas2026[[#This Row],[%ComissãoSupervisor]] -> 0 | P84: Feito | Q84: Feito | S84: 1 | U84: Assinado | V84: Paulo Souza
A85: 46078 | B85: 138641 | C85: Paulo Souza | D85: Dinatale | E85: Rd Station | F85: Mensalidade | G85: 1 | H85: 712 | I85: =vendas2026[[#This Row],[Qtde]]*vendas2026[[#This Row],[VlrUnitário]] -> 712 | J85: =vendas2026[[#This Row],[VlrTotal]] -> 712 | K85: 1 | L85: 0 | M85: Não | N85: =vendas2026[[#This Row],[VlrTotal]]*vendas2026[[#This Row],[%Comissão]] -> 712 | O85: =vendas2026[[#This Row],[VlrTotal]]*vendas2026[[#This Row],[%ComissãoSupervisor]] -> 0 | P85: Feito | Q85: Feito | S85: 1 | U85: Assinado | V85: Paulo Souza
A86: 46078 | B86: 138643 | C86: Paulo Souza | D86: MC Flore | E86: ERP | F86: Treinamentos e Implantações | G86: 196 | H86: 200 | I86: =vendas2026[[#This Row],[Qtde]]*vendas2026[[#This Row],[VlrUnitário]] -> 39200 | J86: =vendas2026[[#This Row],[VlrTotal]] -> 39200 | K86: 0.07 | L86: 0 | M86: Não | N86: =vendas2026[[#This Row],[VlrTotal]]*vendas2026[[#This Row],[%Comissão]] -> 2744 | O86: =vendas2026[[#This Row],[VlrTotal]]*vendas2026[[#This Row],[%ComissãoSupervisor]] -> 0 | P86: Feito | Q86: Feito | S86: 6 | U86: Assinado | V86: Paulo Souza
A87: 46078 | B87: 138643 | C87: Paulo Souza | D87: MC Flore | E87: ERP | F87: CDU | G87: 1 | H87: 35502.9 | I87: =vendas2026[[#This Row],[Qtde]]*vendas2026[[#This Row],[VlrUnitário]] -> 35502.9 | J87: =vendas2026[[#This Row],[VlrTotal]] -> 35502.9 | K87: 0.25 | L87: 0 | M87: Não | N87: =vendas2026[[#This Row],[VlrTotal]]*vendas2026[[#This Row],[%Comissão]] -> 8875.725 | O87: =vendas2026[[#This Row],[VlrTotal]]*vendas2026[[#This Row],[%ComissãoSupervisor]] -> 0 | P87: Feito | Q87: Feito | S87: 6 | U87: Assinado | V87: Paulo Souza
A88: 46078 | B88: 138643 | C88: Paulo Souza | D88: MC Flore | E88: ERP | F88: Mensalidade | G88: 14 | H88: 275.62 | I88: =vendas2026[[#This Row],[Qtde]]*vendas2026[[#This Row],[VlrUnitário]] -> 3858.68 | J88: =vendas2026[[#This Row],[VlrTotal]] -> 3858.68 | K88: 1 | L88: 0 | M88: Não | N88: =vendas2026[[#This Row],[VlrTotal]]*vendas2026[[#This Row],[%Comissão]] -> 3858.68 | O88: =vendas2026[[#This Row],[VlrTotal]]*vendas2026[[#This Row],[%ComissãoSupervisor]] -> 0 | P88: Feito | Q88: Feito | S88: 1 | U88: Assinado | V88: Paulo Souza
... A94: 46078 | B94: 136629 | C94: Rayssa Karapeticov | D94: Fu Xing | E94: Melhoria | F94: Melhoria | G94: 80 | H94: 150 | I94: =vendas2026[[#This Row],[Qtde]]*vendas2026[[#This Row],[VlrUnitário]] -> 12000 | J94: =vendas2026[[#This Row],[VlrTotal]] -> 12000 | K94: 0.0069 | L94: 0 | M94: Sim | N94: =vendas2026[[#This Row],[VlrTotal]]*vendas2026[[#This Row],[%Comissão]] -> 82.8 | O94: =vendas2026[[#This Row],[VlrTotal]]*vendas2026[[#This Row],[%ComissãoSupervisor]] -> 0 | P94: Não tem | Q94: não tem | S94: 1 | U94: não tem | V94: Rayssa Karapeticov
A95: 46078 | B95: 138487 | C95: Rayssa Karapeticov | D95: AD & AD | E95: Envio Boleto Whatsapp | F95: Treinamentos e Implantações | G95: 2 | H95: 210 | I95: =vendas2026[[#This Row],[Qtde]]*vendas2026[[#This Row],[VlrUnitário]] -> 420 | J95: =(vendas2026[[#This Row],[VlrTotal]]*0.2)+vendas2026[[#This Row],[VlrTotal]] -> 504 | K95: 0.07 | L95: =vendas2026[[#This Row],[%Comissão]]*0.25 -> 0.0175 | M95: Sim | N95: =vendas2026[[#This Row],[VlrTotal]]*vendas2026[[#This Row],[%Comissão]] -> 29.4 | O95: =vendas2026[[#This Row],[VlrTotal]]*vendas2026[[#This Row],[%ComissãoSupervisor]] -> 7.35 | P95: Feito | Q95: Feito | S95: 1 | U95: Assinado | V95: Rayssa Karapeticov
A96: 46078 | B96: 138487 | C96: Rayssa Karapeticov | D96: AD & AD | E96: Envio Boleto Whatsapp | F96: Mensalidade | G96: 1 | H96: 356.4 | I96: =vendas2026[[#This Row],[Qtde]]*vendas2026[[#This Row],[VlrUnitário]] -> 356.4 | J96: =(vendas2026[[#This Row],[VlrTotal]]*0.2)+vendas2026[[#This Row],[VlrTotal]] -> 427.68 | K96: 1 | L96: =vendas2026[[#This Row],[%Comissão]]*0.25 -> 0.25 | M96: Sim | N96: =vendas2026[[#This Row],[VlrTotal]]*vendas2026[[#This Row],[%Comissão]] -> 356.4 | O96: =vendas2026[[#This Row],[VlrTotal]]*vendas2026[[#This Row],[%ComissãoSupervisor]] -> 89.1 | P96: Feito | Q96: Feito | S96: 1 | U96: Assinado | V96: Rayssa Karapeticov
A97: 46078 | B97: 138723 | C97: Rayssa Karapeticov | D97: Inga | E97: Treinamento | F97: Treinamentos e Implantações | G97: 40 | H97: 210 | I97: =vendas2026[[#This Row],[Qtde]]*vendas2026[[#This Row],[VlrUnitário]] -> 8400 | J97: =(vendas2026[[#This Row],[VlrTotal]]*0.2)+vendas2026[[#This Row],[VlrTotal]] -> 10080 | K97: 0.25 | L97: =vendas2026[[#This Row],[%Comissão]]*0.25 -> 0.0625 | M97: Sim | N97: =vendas2026[[#This Row],[VlrTotal]]*vendas2026[[#This Row],[%Comissão]] -> 2100 | O97: =vendas2026[[#This Row],[VlrTotal]]*vendas2026[[#This Row],[%ComissãoSupervisor]] -> 525 | P97: Não tem | Q97: não tem | S97: 6 | U97: não tem | V97: Rayssa Karapeticov
A98: 46078 | B98: 134770 | C98: Rayssa Karapeticov | D98: Dcarte | E98: Melhoria | F98: Melhoria | G98: 4 | H98: 176 | I98: =vendas2026[[#This Row],[Qtde]]*vendas2026[[#This Row],[VlrUnitário]] -> 704 | J98: =vendas2026[[#This Row],[VlrTotal]] -> 704 | K98: 0.01 | L98: =vendas2026[[#This Row],[%Comissão]]*0.25 -> 0.0025 | M98: Sim | N98: =vendas2026[[#This Row],[VlrTotal]]*vendas2026[[#This Row],[%Comissão]] -> 7.04 | O98: =vendas2026[[#This Row],[VlrTotal]]*vendas2026[[#This Row],[%ComissãoSupervisor]] -> 1.76 | P98: Não tem | Q98: não tem | S98: 1 | U98: não tem | V98: Rayssa Karapeticov
A99: 46078 | B99: 138211 | C99: Rayssa Karapeticov | D99: Millenium | E99: Treinamento | F99: Treinamentos e Implantações | G99: 8 | H99: 189 | I99: =vendas2026[[#This Row],[Qtde]]*vendas2026[[#This Row],[VlrUnitário]] -> 1512 | J99: =(vendas2026[[#This Row],[VlrTotal]]*0.2)+vendas2026[[#This Row],[VlrTotal]] -> 1814.4 | K99: 0.25 | L99: =vendas2026[[#This Row],[%Comissão]]*0.25 -> 0.0625 | M99: Sim | N99: =vendas2026[[#This Row],[VlrTotal]]*vendas2026[[#This Row],[%Comissão]] -> 378 | O99: =vendas2026[[#This Row],[VlrTotal]]*vendas2026[[#This Row],[%ComissãoSupervisor]] -> 94.5 | P99: Não tem | Q99: não tem | S99: 1 | U99: não tem | V99: Rayssa Karapeticov
A100: 46083 | B100: 137844 | C100: Rayssa Karapeticov | D100: FWB | E100: Melhoria | F100: Melhoria | G100: 3 | H100: 176 | I100: =vendas2026[[#This Row],[Qtde]]*vendas2026[[#This Row],[VlrUnitário]] -> 528 | J100: =vendas2026[[#This Row],[VlrTotal]] -> 528 | K100: 0.01 | L100: =vendas2026[[#This Row],[%Comissão]]*0.25 -> 0.0025 | M100: Sim | N100: =vendas2026[[#This Row],[VlrTotal]]*vendas2026[[#This Row],[%Comissão]] -> 5.28 | O100: =vendas2026[[#This Row],[VlrTotal]]*vendas2026[[#This Row],[%ComissãoSupervisor]] -> 1.32 | P100: Não tem | Q100: não tem | S100: 1 | U100: não tem | V100: Rayssa Karapeticov
A101: 46083 | B101: 138891 | C101: Rayssa Karapeticov | D101: Dasplast | E101: MDe | F101: Treinamentos e Implantações | G101: 8 | H101: 210 | I101: =vendas2026[[#This Row],[Qtde]]*vendas2026[[#This Row],[VlrUnitário]] -> 1680 | J101: =(vendas2026[[#This Row],[VlrTotal]]*0.2)+vendas2026[[#This Row],[VlrTotal]] -> 2016 | K101: 0.07 | L101: =vendas2026[[#This Row],[%Comissão]]*0.25 -> 0.0175 | M101: Sim | N101: =vendas2026[[#This Row],[VlrTotal]]*vendas2026[[#This Row],[%Comissão]] -> 117.6 | O101: =vendas2026[[#This Row],[VlrTotal]]*vendas2026[[#This Row],[%ComissãoSupervisor]] -> 29.4 | P101: Feito | Q101: Feito | S101: 4 | U101: Assinado | V101: Rayssa Karapeticov
A102: 46083 | B102: 138891 | C102: Rayssa Karapeticov | D102: Dasplast | E102: MDe | F102: Mensalidade | G102: 1 | H102: 356.4 | I102: =vendas2026[[#This Row],[Qtde]]*vendas2026[[#This Row],[VlrUnitário]] -> 356.4 | J102: =(vendas2026[[#This Row],[VlrTotal]]*0.2)+vendas2026[[#This Row],[VlrTotal]] -> 427.68 | K102: 1 | L102: =vendas2026[[#This Row],[%Comissão]]*0.25 -> 0.25 | M102: Sim | N102: =vendas2026[[#This Row],[VlrTotal]]*vendas2026[[#This Row],[%Comissão]] -> 356.4 | O102: =vendas2026[[#This Row],[VlrTotal]]*vendas2026[[#This Row],[%ComissãoSupervisor]] -> 89.1 | P102: Feito | Q102: Feito | S102: 1 | U102: Assinado | V102: Rayssa Karapeticov
A103: 46092 | B103: 134510 | C103: Rayssa Karapeticov | D103: Gyn | E103: Treinamento | F103: Treinamentos e Implantações | G103: 14 | H103: 178.5 | I103: =vendas2026[[#This Row],[Qtde]]*vendas2026[[#This Row],[VlrUnitário]] -> 2499 | J103: =(vendas2026[[#This Row],[VlrTotal]]*0.2)+vendas2026[[#This Row],[VlrTotal]] -> 2998.8 | K103: 0.0669 | L103: =vendas2026[[#This Row],[%Comissão]]*0.25 -> 0.016725 | M103: Sim | N103: =vendas2026[[#This Row],[VlrTotal]]*vendas2026[[#This Row],[%Comissão]] -> 167.1831 | O103: =vendas2026[[#This Row],[VlrTotal]]*vendas2026[[#This Row],[%ComissãoSupervisor]] -> 41.795775 | P103: Não tem | Q103: não tem | S103: 3 | U103: não tem | V103: Rayssa Karapeticov
A104: 46092 | B104: 139165 | C104: Rayssa Karapeticov | D104: Millenium | E104: CNPJ | F104: CDU | G104: 1 | H104: 7472.2 | I104: =vendas2026[[#This Row],[Qtde]]*vendas2026[[#This Row],[VlrUnitário]] -> 7472.2 | J104: =(vendas2026[[#This Row],[VlrTotal]]*0.2)+vendas2026[[#This Row],[VlrTotal]] -> 8966.64 | K104: 0.07 | L104: =vendas2026[[#This Row],[%Comissão]]*0.25 -> 0.0175 | M104: Sim | N104: =vendas2026[[#This Row],[VlrTotal]]*vendas2026[[#This Row],[%Comissão]] -> 523.054 | O104: =vendas2026[[#This Row],[VlrTotal]]*vendas2026[[#This Row],[%ComissãoSupervisor]] -> 130.7635 | P104: Feito | Q104: Feito | S104: 6 | U104: Assinado | V104: Rayssa Karapeticov
A105: 46092 | B105: 138115 | C105: Rayssa Karapeticov | D105: Brl Alimentos | E105: Melhoria | F105: Melhoria | G105: 6 | H105: 176 | I105: =vendas2026[[#This Row],[Qtde]]*vendas2026[[#This Row],[VlrUnitário]] -> 1056 | J105: 1056 | K105: 0.01 | L105: =vendas2026[[#This Row],[%Comissão]]*0.25 -> 0.0025 | M105: Sim | N105: =vendas2026[[#This Row],[VlrTotal]]*vendas2026[[#This Row],[%Comissão]] -> 10.56 | O105: =vendas2026[[#This Row],[VlrTotal]]*vendas2026[[#This Row],[%ComissãoSupervisor]] -> 2.64 | P105: Não tem | Q105: não tem | S105: 1 | U105: não tem | V105: Rayssa Karapeticov
A106: 46092 | B106: 137749 | C106: Rayssa Karapeticov | D106: Flora nectar | E106: Melhoria | F106: Melhoria | G106: 20 | H106: 176 | I106: =vendas2026[[#This Row],[Qtde]]*vendas2026[[#This Row],[VlrUnitário]] -> 3520 | J106: 3520 | K106: 0.01 | L106: =vendas2026[[#This Row],[%Comissão]]*0.25 -> 0.0025 | M106: Sim | N106: =vendas2026[[#This Row],[VlrTotal]]*vendas2026[[#This Row],[%Comissão]] -> 35.2 | O106: =vendas2026[[#This Row],[VlrTotal]]*vendas2026[[#This Row],[%ComissãoSupervisor]] -> 8.8 | P106: Não tem | Q106: não tem | S106: 1 | U106: não tem | V106: Rayssa Karapeticov
A107: 46092 | B107: 137612...137592 | C107: Rayssa Karapeticov | D107: Inga | E107: Melhoria | F107: Melhoria | G107: 56 | H107: 176 | I107: =vendas2026[[#This Row],[Qtde]]*vendas2026[[#This Row],[VlrUnitário]] -> 9856 | J107: 9856 | K107: 0.01 | L107: =vendas2026[[#This Row],[%Comissão]]*0.25 -> 0.0025 | M107: Sim | N107: =vendas2026[[#This Row],[VlrTotal]]*vendas2026[[#This Row],[%Comissão]] -> 98.56 | O107: =vendas2026[[#This Row],[VlrTotal]]*vendas2026[[#This Row],[%ComissãoSupervisor]] -> 24.64 | P107: Não tem | Q107: não tem | S107: 4 | U107: não tem | V107: Rayssa Karapeticov
A108: 46092 | B108: 137391 | C108: Rayssa Karapeticov | D108: MTA | E108: Melhoria | F108: Melhoria | G108: 2 | H108: 176 | I108: =vendas2026[[#This Row],[Qtde]]*vendas2026[[#This Row],[VlrUnitário]] -> 352 | J108: 352 | K108: 0.01 | L108: =vendas2026[[#This Row],[%Comissão]]*0.25 -> 0.0025 | M108: Sim | N108: =vendas2026[[#This Row],[VlrTotal]]*vendas2026[[#This Row],[%Comissão]] -> 3.52 | O108: =vendas2026[[#This Row],[VlrTotal]]*vendas2026[[#This Row],[%ComissãoSupervisor]] -> 0.88 | P108: Não tem | Q108: não tem | S108: 1 | U108: não tem | V108: Rayssa Karapeticov
A109: 46092 | B109: 139463 | C109: Junior Lopes | D109: Clean Tech | E109: ERP | F109: Treinamentos e Implantações | G109: 340 | H109: 171 | I109: =vendas2026[[#This Row],[Qtde]]*vendas2026[[#This Row],[VlrUnitário]] -> 58140 | J109: =vendas2026[[#This Row],[VlrTotal]] -> 58140 | K109: 0.05 | L109: =vendas2026[[#This Row],[%Comissão]]*0.25 -> 0.0125 | M109: Não | N109: =vendas2026[[#This Row],[VlrTotal]]*vendas2026[[#This Row],[%Comissão]] -> 2907 | O109: =vendas2026[[#This Row],[VlrTotal]]*vendas2026[[#This Row],[%ComissãoSupervisor]] -> 726.75 | P109: Feito | Q109: Feito | S109: 6 | U109: Assinado | V109: Junior Lopes
A110: 46092 | B110: 139463 | C110: Junior Lopes | D110: Clean Tech | E110: AFV | F110: Treinamentos e Implantações | G110: 60 | H110: 171 | I110: =vendas2026[[#This Row],[Qtde]]*vendas2026[[#This Row],[VlrUnitário]] -> 10260 | J110: =vendas2026[[#This Row],[VlrTotal]] -> 10260 | K110: 0.05 | L110: =vendas2026[[#This Row],[%Comissão]]*0.25 -> 0.0125 | M110: Não | N110: =vendas2026[[#This Row],[VlrTotal]]*vendas2026[[#This Row],[%Comissão]] -> 513 | O110: =vendas2026[[#This Row],[VlrTotal]]*vendas2026[[#This Row],[%ComissãoSupervisor]] -> 128.25 | P110: Feito | Q110: Feito | S110: 6 | U110: Assinado | V110: Junior Lopes
...

Sheet Metas Quadro
A1: TABELA 1.1
A3: Juca | B3: Meta | C3: Alvo | D3: Cobertura
A4: Projeto | B4: 90000 | C4: 86455.76 | D4: =C4/B4 -> 0.96061956
A5: Recorrente | B5: 10000 | C5: 448 | D5: =C5/B5 -> 0.0448
A7: Rayssa
A8: Projeto | B8: 90000 | C8: 16300 | D8: =C8/B8 -> 0.18111111
A9: Recorrente | B9: 9500 | C9: 10463.76 | D9: =C9/B9 -> 1.1014484
A12: Paulo | B12: Meta | C12: Alvo | D12: Cobertura
A13: Projeto | B13: 90000 | C13: 0 | D13: =C13/B13 -> 0
A14: Recorrente | B14: 10000 | C14: 0 | D14: =C14/B14 -> 0
A16: Ronaldo Nascimento | B16: Meta | C16: Alvo | D16: Cobertura
A17: Projeto | B17: 54000 | C17: 0 | D17: =C17/B17 -> 0
A18: Recorrente | B18: 7500 | C18: 0 | D18: =C18/B18 -> 0
A20: Fábio | B20: Meta | C20: Alvo | D20: Cobertura
A21: Projeto | B21: 90000 | C21: 0 | D21: =C21/B21 -> 0
A22: Recorrente | B22: 10000 | C22: 0 | D22: =C22/B22 -> 0
A24: Total Projeto Equipe | B24: =90000*4 -> 360000 | C24: =C4+C8+C13+C21+C17 -> 102755.76 | D24: =C24/B24 -> 0.28543267
A25: Total RecorrenteEquipe | B25: =B9+B14+B18+B5 -> 37000 | C25: =C5+C9+C14+C18 -> 10911.76 | D25: =C25/B25 -> 0.29491243
A27: Meta Equipe | B27: Meta | C27: Alvo | D27: Cobertura
A28: Projeto | B28: =90000*4 -> 360000 | C28: =C4+C8+C13+C17 -> 102755.76 | D28: =C28/B28 -> 0.28543267
A29: Recorrente | B29: =B25 -> 37000 | C29: =C9+C14+C18+C5 -> 10911.76 | D29: =C29/B29 -> 0.29491243

Sheet QtdeMetas
A1: FECHAMENTO DE: 01/01/2025 até 31/01/2025 | M1: Ano | N1: Mês | O1: Vendedor | P1: Lead | Q1: Propsota | R1: Apresentação | S1: Meta Individual | T1: Meta Equipe | U1: Meta Projetos | V1: OBLead | W1: OB Proposta | X1: OB Apresentação | Y1: OB Individual | Z1: OBEquipe | AA1: OB Projetos | AB1: OBI | AC1: OBE
A2: COBERTURA DE METAS | M2: 2025 | N2: 45658 | O2: Rayssa Karapeticov | Q2: =C5 -> 33 | R2: =C6 -> 18 | S2: =C7 -> 926.64 | T2: =C8 -> 32622.62 | U2: =C9 -> 62289.8 | V2: 150 | W2: 15 | X2: 12 | Y2: 10 | Z2: 30 | AA2: 90000 | AB2: =metas[[#This Row],[Meta Individual]]/10000 -> 0.092664 | AC2: =metas[[#This Row],[Meta Equipe]]/30000/3 -> 0.36247356
A3: RAYSSA | E3: JUNIOR | I3: PAULO | M3: 2025 | N3: 45658 | O3: Junior Lopes | Q3: =G5 -> 14 | R3: =G6 -> 12 | S3: =G7 -> 31339.58 | T3: =G8 -> 32622.62 | U3: =G9 -> 315102.82 | V3: 150 | W3: 15 | X3: 12 | Y3: 10 | Z3: 30 | AA3: 90000 | AB3: =metas[[#This Row],[Meta Individual]]/10000 -> 3.133958 | AC3: =metas[[#This Row],[Meta Equipe]]/30000/3 -> 0.36247356
B4: Meta | C4: Realizado | D4: Cobertura | F4: Meta | G4: Realizado | H4: Cobertura | J4: Meta | K4: Realizado | L4: Cobertura | M4: 2025 | N4: 45658 | O4: Paulo Souza | Q4: =K5 -> 15 | R4: =K6 -> 16 | S4: =K7 -> 356.4 | T4: =K8 -> 32622.62 | U4: =K9 -> 14022.08 | V4: 150 | W4: 15 | X4: 12 | Y4: 10 | Z4: 30 | AA4: 90000 | AB4: =metas[[#This Row],[Meta Individual]]/10000 -> 0.03564 | AC4: =metas[[#This Row],[Meta Equipe]]/30000/3 -> 0.36247356
A5: Proposta | B5: 15 | C5: 33 | D5: 2.2 | E5: Proposta | F5: 15 | G5: 14 | H5: 0.93333333 | I5: Proposta | J5: 15 | K5: 15 | L5: 1 | M5: 2025 | N5: 45689 | O5: Rayssa Karapeticov | Q5: =C15 -> 23 | R5: =C16 -> 22 | S5: =C17 -> 1288.03 | T5: =C18 -> 14565.4 | U5: =C19 -> 85015.22 | V5: 150 | W5: 15 | X5: 12 | Y5: 10 | Z5: 30 | AA5: 90000 | AB5: =metas[[#This Row],[Meta Individual]]/10000 -> 0.128803 | AC5: =metas[[#This Row],[Meta Equipe]]/30000/3 -> 0.16183778
A6: Apresentações | B6: 12 | C6: 18 | D6: 1.5 | E6: Apresentações | F6: 12 | G6: 12 | H6: 1 | I6: Apresentações | J6: 12 | K6: 16 | L6: 1.3333333 | M6: 2025 | N6: 45689 | O6: Junior Lopes | Q6: =G15 -> 16 | R6: =G16 -> 16 | S6: =G17 -> 11189.93 | T6: =G18 -> 14565.4 | U6: =G19 -> 121887.86 | V6: 150 | W6: 15 | X6: 12 | Y6: 10 | Z6: 30 | AA6: 90000 | AB6: =metas[[#This Row],[Meta Individual]]/10000 -> 1.118993 | AC6: =metas[[#This Row],[Meta Equipe]]/30000/3 -> 0.16183778
A7: Meta Individual | B7: 10000 | C7: 926.64 | D7: 0.092664 | E7: Meta Individual | F7: 10000 | G7: 31339.58 | H7: 3.133958 | I7: Meta Individual | J7: 10000 | K7: 356.4 | L7: 0.03564 | M7: 2025 | N7: 45689 | O7: Paulo Souza | Q7: =K15 -> 9 | R7: =K16 -> 21 | S7: =K17 -> 2087.44 | T7: =K18 -> 14565.4 | U7: =K19 -> 19104 | V7: 150 | W7: 15 | X7: 12 | Y7: 10 | Z7: 30 | AA7: 90000 | AB7: =metas[[#This Row],[Meta Individual]]/10000 -> 0.208744 | AC7: =metas[[#This Row],[Meta Equipe]]/30000/3 -> 0.16183778
A8: Meta Equipe | B8: 30000 | C8: 32622.62 | D8: 1.0874207 | E8: Meta Equipe | F8: 30000 | G8: 32622.62 | H8: 1.0874207 | I8: Meta Equipe | J8: 30000 | K8: 32622.62 | L8: 1.0874207 | M8: 2025 | N8: 45717 | O8: Rayssa Karapeticov | Q8: =C25 -> 17 | R8: =C26 -> 7 | S8: =C27 -> 6712.41 | T8: =C28 -> 14901.7 | U8: =C29 -> 111207.36 | V8: 150 | W8: 15 | X8: 12 | Y8: 10 | Z8: 30 | AA8: 90000 | AB8: =metas[[#This Row],[Meta Individual]]/10000 -> 0.671241 | AC8: =metas[[#This Row],[Meta Equipe]]/30000/3 -> 0.16557444
A9: Meta Projetos | B9: 90000 | C9: 62289.8 | D9: 0.69210889 | E9: Meta Projetos | F9: 90000 | G9: 315102.82 | H9: 3.5011424 | I9: Meta Projetos | J9: 90000 | K9: 14022.08 | L9: 0.15580089 | M9: 2025 | N9: 45717 | O9: Junior Lopes | Q9: =G25 -> 17 | R9: =G26 -> 12 | S9: =G27 -> 3064.57 | T9: =G28 -> 14901.7 | U9: =G29 -> 70833.33 | V9: 150 | W9: 15 | X9: 12 | Y9: 10 | Z9: 30 | AA9: 90000 | AB9: =metas[[#This Row],[Meta Individual]]/10000 -> 0.306457 | AC9: =metas[[#This Row],[Meta Equipe]]/30000/3 -> 0.16557444
M10: 2025 | N10: 45717 | O10: Paulo Souza | Q10: =K25 -> 4 | R10: =K26 -> 4 | S10: =K27 -> 5124.72 | T10: =K28 -> 14901.7 | U10: =K29 -> 73632 | V10: 150 | W10: 15 | X10: 12 | Y10: 10 | Z10: 30 | AA10: 90000 | AB10: =metas[[#This Row],[Meta Individual]]/10000 -> 0.512472 | AC10: =metas[[#This Row],[Meta Equipe]]/30000/3 -> 0.16557444
A11: FECHAMENTO DE: 01/02/2025 até 28/02/2025 | M11: 2025 | N11: 45748 | O11: Rayssa Karapeticov | Q11: =C35 -> 29 | R11: =C36 -> 15 | S11: =C37 -> 193 | T11: =C38 -> 13345.68 | U11: =C39 -> 29258.82 | V11: 150 | W11: 15 | X11: 12 | Y11: 10 | Z11: 30 | AA11: 90000 | AB11: =metas[[#This Row],[Meta Individual]]/10000 -> 0.0193 | AC11: =metas[[#This Row],[Meta Equipe]]/30000/3 -> 0.14828533
A12: COBERTURA DE METAS | M12: 2025 | N12: 45748 | O12: Junior Lopes | Q12: =G35 -> 15 | R12: =G36 -> 13 | S12: =G37 -> 11064.68 | T12: =G38 -> 13345.68 | U12: =G39 -> 124112.08 | V12: 150 | W12: 15 | X12: 12 | Y12: 10 | Z12: 30 | AA12: 90000 | AB12: =metas[[#This Row],[Meta Individual]]/10000 -> 1.106468 | AC12: =metas[[#This Row],[Meta Equipe]]/30000/3 -> 0.14828533
A13: RAYSSA | E13: JUNIOR | I13: PAULO | M13: 2025 | N13: 45748 | O13: Paulo Souza | Q13: =K35 -> 5 | R13: =K36 -> 6 | S13: =K37 -> 2088 | T13: =K38 -> 13345.68 | U13: =K39 -> 32058 | V13: 150 | W13: 15 | X13: 12 | Y13: 10 | Z13: 30 | AA13: 90000 | AB13: =metas[[#This Row],[Meta Individual]]/10000 -> 0.2088 | AC13: =metas[[#This Row],[Meta Equipe]]/30000/3 -> 0.14828533
B14: Meta | C14: Realizado | D14: Cobertura | F14: Meta | G14: Realizado | H14: Cobertura | J14: Meta | K14: Realizado | L14: Cobertura | M14: 2025 | N14: 45778 | O14: Rayssa Karapeticov | Q14: =C45 -> 23 | R14: =C46 -> 20 | S14: =C47 -> Realizado | T14: =C48 -> 23 | U14: =C49 -> 20 | V14: 150 | W14: 15 | X14: 12 | Y14: 10 | Z14: 30 | AA14: 90000 | AB14: =metas[[#This Row],[Meta Individual]]/10000 -> #VALUE! | AC14: =metas[[#This Row],[Meta Equipe]]/30000/3 -> 0.00025555556
A15: Proposta | B15: 15 | C15: 23 | D15: 1.5333333 | E15: Proposta | F15: 15 | G15: 16 | H15: 1.0666667 | I15: Proposta | J15: 15 | K15: 9 | L15: 0.6 | M15: 2025 | N15: 45778 | O15: Junior Lopes | Q15: =G45 -> 17 | R15: =G46 -> 14 | S15: =G47 -> Realizado | T15: =G48 -> 17 | U15: =G49 -> 14 | V15: 150 | W15: 15 | X15: 12 | Y15: 10 | Z15: 30 | AA15: 90000 | AB15: =metas[[#This Row],[Meta Individual]]/10000 -> #VALUE! | AC15: =metas[[#This Row],[Meta Equipe]]/30000/3 -> 0.00018888889
A16: Apresentações | B16: 12 | C16: 22 | D16: 1.8333333 | E16: Apresentações | F16: 12 | G16: 16 | H16: 1.3333333 | I16: Apresentações | J16: 12 | K16: 21 | L16: 1.75 | M16: 2025 | N16: 45778 | O16: Paulo Souza | Q16: =K45 -> 2 | R16: =K46 -> 1 | S16: =K47 -> Realizado | T16: =K48 -> 2 | U16: =K49 -> 1 | V16: 150 | W16: 15 | X16: 12 | Y16: 10 | Z16: 30 | AA16: 90000 | AB16: =metas[[#This Row],[Meta Individual]]/10000 -> #VALUE! | AC16: =metas[[#This Row],[Meta Equipe]]/30000/3 -> 2.2222222e-05
A17: Meta Individual | B17: 10000 | C17: 1288.03 | D17: 0.128803 | E17: Meta Individual | F17: 10000 | G17: 11189.93 | H17: 1.118993 | I17: Meta Individual | J17: 10000 | K17: 2087.44 | L17: 0.208744 | M17: 2025 | N17: 45809 | O17: Rayssa Karapeticov | Q17: =C55 -> 25 | R17: =C56 -> 19 | S17: =C57 -> 4260.96 | T17: =C58 -> 30275.77 | U17: =C59 -> 85918.58 | V17: 150 | W17: 15 | X17: 12 | Y17: 10 | Z17: 30 | AA17: 90000 | AB17: =metas[[#This Row],[Meta Individual]]/10000 -> 0.426096 | AC17: =metas[[#This Row],[Meta Equipe]]/30000/3 -> 0.33639744
A18: Meta Equipe | B18: 30000 | C18: 14565.4 | D18: 0.48551333 | E18: Meta Equipe | F18: 30000 | G18: 14565.4 | H18: 0.48551333 | I18: Meta Equipe | J18: 30000 | K18: 14565.4 | L18: 0.48551333 | M18: 2025 | N18: 45809 | O18: Junior Lopes | Q18: =G55 -> 18 | R18: =G56 -> 13 | S18: =G57 -> 4579.8 | T18: =G58 -> 30275.77 | U18: =G59 -> 33826.34 | V18: 150 | W18: 15 | X18: 12 | Y18: 10 | Z18: 30 | AA18: 90000 | AB18: =metas[[#This Row],[Meta Individual]]/10000 -> 0.45798 | AC18: =metas[[#This Row],[Meta Equipe]]/30000/3 -> 0.33639744
A19: Meta Projetos | B19: 90000 | C19: 85015.22 | D19: 0.94461356 | E19: Meta Projetos | F19: 90000 | G19: 121887.86 | H19: 1.3543096 | I19: Meta Projetos | J19: 90000 | K19: 19104 | L19: 0.21226667 | M19: 2025 | N19: 45809 | O19: Paulo Souza | Q19: =K55 -> 3 | R19: =K56 -> 1 | S19: =K57 -> 21435.01 | T19: =K58 -> 30275.77 | U19: =K59 -> 211246 | V19: 150 | W19: 15 | X19: 12 | Y19: 10 | Z19: 30 | AA19: 90000 | AB19: =metas[[#This Row],[Meta Individual]]/10000 -> 2.143501 | AC19: =metas[[#This Row],[Meta Equipe]]/30000/3 -> 0.33639744
M20: 2025 | N20: 45839 | O20: Rayssa Karapeticov | Q20: =C65 -> 22 | R20: =C66 -> 14 | S20: =C67 -> 1733.34 | T20: =C68 -> 11875.9 | U20: =C69 -> 86932.5 | V20: 150 | W20: 15 | X20: 12 | Y20: 10 | Z20: 30 | AA20: 90000 | AB20: =metas[[#This Row],[Meta Individual]]/10000 -> 0.173334 | AC20: =metas[[#This Row],[Meta Equipe]]/30000/3 -> 0.13195444
A21: FECHAMENTO DE: 01/03/2025 até 31/03/2025 | M21: 2025 | N21: 45839 | O21: Junior Lopes | Q21: =G65 -> 17 | R21: =G66 -> 12 | S21: =G67 -> 142.56 | T21: =G68 -> 11875.9 | U21: =G69 -> 6071.21 | V21: 150 | W21: 15 | X21: 12 | Y21: 10 | Z21: 30 | AA21: 90000 | AB21: =metas[[#This Row],[Meta Individual]]/10000 -> 0.014256 | AC21: =metas[[#This Row],[Meta Equipe]]/30000/3 -> 0.13195444
A22: COBERTURA DE METAS | M22: 2025 | N22: 45839 | O22: Paulo Souza | Q22: =K65 -> 2 | R22: =K66 -> 1 | S22: =K67 -> 10000 | T22: =K68 -> 11875.9 | U22: =K69 -> 90575 | V22: 150 | W22: 15 | X22: 12 | Y22: 10 | Z22: 30 | AA22: 90000 | AB22: =metas[[#This Row],[Meta Individual]]/10000 -> 1 | AC22: =metas[[#This Row],[Meta Equipe]]/30000/3 -> 0.13195444
A23: RAYSSA | E23: JUNIOR | I23: PAULO | M23: 2025 | N23: 45870 | O23: Rayssa Karapeticov | Q23: =C75 -> 25 | R23: =C76 -> 17 | S23: =C77 -> 1667.4 | T23: =C78 -> 14580.27 | U23: =C79 -> 37218.92 | V23: 150 | W23: 15 | X23: 12 | Y23: 10 | Z23: 30 | AA23: 90000 | AB23: =metas[[#This Row],[Meta Individual]]/10000 -> 0.16674 | AC23: =metas[[#This Row],[Meta Equipe]]/30000/3 -> 0.162003
B24: Meta | C24: Realizado | D24: Cobertura | F24: Meta | G24: Realizado | H24: Cobertura | J24: Meta | K24: Realizado | L24: Cobertura | M24: 2025 | N24: 45870 | O24: Junior Lopes | Q24: =G75 -> 16 | R24: =G76 -> 13 | S24: =G77 -> 5551.4 | T24: =G78 -> 14580.27 | U24: =G79 -> 69366.4 | V24: 150 | W24: 15 | X24: 12 | Y24: 10 | Z24: 30 | AA24: 90000 | AB24: =metas[[#This Row],[Meta Individual]]/10000 -> 0.55514 | AC24: =metas[[#This Row],[Meta Equipe]]/30000/3 -> 0.162003
A25: Proposta | B25: 15 | C25: 17 | D25: 1.1333333 | E25: Proposta | F25: 15 | G25: 17 | H25: 1.1333333 | I25: Proposta | J25: 15 | K25: 4 | L25: 0.26666667 | M25: 2025 | N25: 45870 | O25: Paulo Souza | Q25: =K75 -> 8 | R25: =K76 -> 8 | S25: =K77 -> 7361.47 | T25: =K78 -> 14580.27 | U25: =K79 -> 57100 | V25: 150 | W25: 15 | X25: 12 | Y25: 10 | Z25: 30 | AA25: 90000 | AB25: =metas[[#This Row],[Meta Individual]]/10000 -> 0.736147 | AC25: =metas[[#This Row],[Meta Equipe]]/30000/3 -> 0.162003
A26: Apresentações | B26: 12 | C26: 7 | D26: 0.58333333 | E26: Apresentações | F26: 12 | G26: 12 | H26: 1 | I26: Apresentações | J26: 12 | K26: 4 | L26: 0.33333333 | M26: 2025 | N26: 45901 | O26: Rayssa Karapeticov | Q26: =C85 -> 25 | R26: =C86 -> 16 | S26: =C87 -> 3619.87 | T26: =C88 -> 12925.19 | U26: =C89 -> 156911.7 | V26: 150 | W26: 15 | X26: 12 | Y26: 10 | Z26: 30 | AA26: 90000 | AB26: =metas[[#This Row],[Meta Individual]]/10000 -> 0.361987 | AC26: =metas[[#This Row],[Meta Equipe]]/30000/3 -> 0.14361322
A27: Meta Individual | B27: 10000 | C27: 6712.41 | D27: 0.671241 | E27: Meta Individual | F27: 10000 | G27: 3064.57 | H27: 0.306457 | I27: Meta Individual | J27: 10000 | K27: 5124.72 | L27: 0.512472 | M27: 2025 | N27: 45901 | O27: Junior Lopes | Q27: =G85 -> 16 | R27: =G86 -> 18 | S27: =G87 -> 6448.22 | T27: =G88 -> 12925.19 | U27: =G89 -> 134306.46 | V27: 150 | W27: 15 | X27: 12 | Y27: 10 | Z27: 30 | AA27: 90000 | AB27: =metas[[#This Row],[Meta Individual]]/10000 -> 0.644822 | AC27: =metas[[#This Row],[Meta Equipe]]/30000/3 -> 0.14361322
A28: Meta Equipe | B28: 30000 | C28: 14901.7 | D28: 0.49672333 | E28: Meta Equipe | F28: 30000 | G28: 14901.7 | H28: 0.49672333 | I28: Meta Equipe | J28: 30000 | K28: 14901.7 | L28: 0.49672333 | M28: 2025 | N28: 45901 | O28: Paulo Souza | Q28: =K85 -> 11 | R28: =K86 -> 11 | S28: =K87 -> 2857.1 | T28: =K88 -> 12925.19 | U28: =K89 -> 47500 | V28: 150 | W28: 15 | X28: 12 | Y28: 10 | Z28: 30 | AA28: 90000 | AB28: =metas[[#This Row],[Meta Individual]]/10000 -> 0.28571 | AC28: =metas[[#This Row],[Meta Equipe]]/30000/3 -> 0.14361322
A29: Meta Projetos | B29: 90000 | C29: 111207.36 | D29: 1.2356373 | E29: Meta Projetos | F29: 90000 | G29: 70833.33 | H29: 0.787037 | I29: Meta Projetos | J29: 90000 | K29: 73632 | L29: 0.81813333 | M29: 2025 | N29: 45931 | O29: Rayssa Karapeticov | Q29: =C95 -> 15 | R29: =C96 -> 12 | S29: =C97 -> 1927.89 | T29: =C98 -> 1927.89 | U29: =C99 -> 117851.89 | V29: 150 | W29: 15 | X29: 12 | Y29: 10 | Z29: 30 | AA29: 90000 | AB29: =metas[[#This Row],[Meta Individual]]/10000 -> 0.192789 | AC29: =metas[[#This Row],[Meta Equipe]]/30000/3 -> 0.021421
M30: 2025 | N30: 45931 | O30: Junior Lopes | Q30: =G95 -> 15 | R30: =G96 -> 12 | S30: =G97 -> 0 | T30: =G98 -> 1927.89 | U30: =G99 -> 39131.15 | V30: 150 | W30: 15 | X30: 12 | Y30: 10 | Z30: 30 | AA30: 90000 | AB30: =metas[[#This Row],[Meta Individual]]/10000 -> 0 | AC30: =metas[[#This Row],[Meta Equipe]]/30000/3 -> 0.021421
A31: FECHAMENTO DE: 01/04/2025 até 30/04/2025 | M31: 2025 | N31: 45931 | O31: Paulo Souza | Q31: =K95 -> 15 | R31: =K96 -> 12 | S31: =K97 -> 0 | T31: =K98 -> 1927.89 | U31: =K99 -> 0 | V31: 150 | W31: 15 | X31: 12 | Y31: 10 | Z31: 30 | AA31: 90000 | AB31: =metas[[#This Row],[Meta Individual]]/10000 -> 0 | AC31: =metas[[#This Row],[Meta Equipe]]/30000/3 -> 0.021421
A32: COBERTURA DE METAS | M32: 2025 | N32: 45962 | O32: Rayssa Karapeticov | Q32: =C105 -> 20 | R32: =C106 -> 18 | S32: =C107 -> 285.12 | T32: =C108 -> 641.52 | U32: =C109 -> 49993.72 | V32: 150 | W32: 15 | X32: 12 | Y32: 10 | Z32: 30 | AA32: 90000 | AB32: =metas[[#This Row],[Meta Individual]]/10000 -> 0.028512 | AC32: =metas[[#This Row],[Meta Equipe]]/30000/3 -> 0.007128
A33: RAYSSA | E33: JUNIOR | I33: PAULO | M33: 2025 | N33: 45962 | O33: Junior Lopes | Q33: =G105 -> 15 | R33: =G106 -> 13 | S33: =G107 -> 356.4 | T33: =G108 -> 641.52 | U33: =G109 -> 3307.14 | V33: 150 | W33: 15 | X33: 12 | Y33: 10 | Z33: 30 | AA33: 90000 | AB33: =metas[[#This Row],[Meta Individual]]/10000 -> 0.03564 | AC33: =metas[[#This Row],[Meta Equipe]]/30000/3 -> 0.007128
B34: Meta | C34: Realizado | D34: Cobertura | F34: Meta | G34: Realizado | H34: Cobertura | J34: Meta | K34: Realizado | L34: Cobertura | M34: 2025 | N34: 45962 | O34: Paulo Souza | Q34: =K105 -> 12 | R34: =K106 -> 12 | S34: =K108 -> 641.52 | T34: =K108 -> 641.52 | U34: =K109 -> 6253 | V34: 150 | W34: 15 | X34: 12 | Y34: 10 | Z34: 30 | AA34: 90000 | AB34: =metas[[#This Row],[Meta Individual]]/10000 -> 0.064152 | AC34: =metas[[#This Row],[Meta Equipe]]/30000/3 -> 0.007128
A35: Proposta | B35: 15 | C35: 29 | D35: 1.9333333 | E35: Proposta | F35: 15 | G35: 15 | H35: 1 | I35: Proposta | J35: 15 | K35: 5 | L35: 0.33333333 | M35: 2025 | N35: 45992 | O35: Rayssa Karapeticov | Q35: 10 | R35: 8 | S35: 3149.32 | T35: 10160.04 | U35: 97189.92 | V35: 150 | W35: 15 | X35: 12 | Y35: 6 | Z35: 26 | AA35: 90000 | AB35: =metas[[#This Row],[Meta Individual]]/6000 -> 0.52488667 | AC35: =metas[[#This Row],[Meta Equipe]]/26000/3 -> 0.13025692
A36: Apresentações | B36: 12 | C36: 15 | D36: 1.25 | E36: Apresentações | F36: 12 | G36: 13 | H36: 1.0833333 | I36: Apresentações | J36: 12 | K36: 6 | L36: 0.5 | M36: 2025 | N36: 45992 | O36: Junior Lopes | Q36: 10 | R36: 11 | S36: 6440.48 | T36: 10160.04 | U36: 38960 | V36: 150 | W36: 15 | X36: 12 | Y36: 10 | Z36: 26 | AA36: 90000 | AB36: =metas[[#This Row],[Meta Individual]]/10000 -> 0.644048 | AC36: =metas[[#This Row],[Meta Equipe]]/26000/3 -> 0.13025692
A37: Meta Individual | B37: 10000 | C37: 193 | D37: 0.0193 | E37: Meta Individual | F37: 10000 | G37: 11064.68 | H37: 1.106468 | I37: Meta Individual | J37: 10000 | K37: 2088 | L37: 0.2088 | M37: 2025 | N37: 45992 | O37: Paulo Souza | Q37: 8 | R37: 8 | S37: 570.24 | T37: 10160.04 | U37: =K112 -> 0 | V37: 150 | W37: 15 | X37: 12 | Y37: 10 | Z37: 26 | AA37: 90000 | AB37: =metas[[#This Row],[Meta Individual]]/10000 -> 0.057024 | AC37: =metas[[#This Row],[Meta Equipe]]/26000/3 -> 0.13025692
A38: Meta Equipe | B38: 30000 | C38: 13345.68 | D38: 0.444856 | E38: Meta Equipe | F38: 30000 | G38: 13345.68 | H38: 0.444856 | I38: Meta Equipe | J38: 30000 | K38: 13345.68 | L38: 0.444856 | M38: 2026 | N38: 46023 | O38: Rayssa Karapeticov | Q38: 24 | R38: 16 | S38: 2698.22 | T38: 17506.46 | U38: 58587.27 | V38: 150 | W38: 15 | X38: 12 | Y38: 6 | Z38: 26 | AA38: 90000 | AB38: =metas[[#This Row],[Meta Individual]]/6000 -> 0.44970333 | AC38: =metas[[#This Row],[Meta Equipe]]/26000/3 -> 0.22444179
A39: Meta Projetos | B39: 90000 | C39: 29258.82 | D39: 0.325098 | E39: Meta Projetos | F39: 90000 | G39: 124112.08 | H39: 1.3790231 | I39: Meta Projetos | J39: 90000 | K39: 32058 | L39: 0.3562 | M39: 2026 | N39: 46023 | O39: Junior Lopes | Q39: 16 | R39: 16 | S39: 4434.5 | T39: 17506.46 | U39: 101301 | V39: 150 | W39: 15 | X39: 12 | Y39: 10 | Z39: 26 | AA39: 90000 | AB39: =metas[[#This Row],[Meta Individual]]/10000 -> 0.44345 | AC39: =metas[[#This Row],[Meta Equipe]]/26000/3 -> 0.22444179
M40: 2026 | N40: 46023 | O40: Paulo Souza | Q40: 10 | R40: 10 | S40: 10373.74 | T40: 17506.46 | U40: 97790.97 | V40: 150 | W40: 15 | X40: 12 | Y40: 10 | Z40: 26 | AA40: 90000 | AB40: =metas[[#This Row],[Meta Individual]]/10000 -> 1.037374 | AC40: =metas[[#This Row],[Meta Equipe]]/26000/3 -> 0.22444179
A41: FECHAMENTO DE: 01/05/2025 até 31/05/2025 | M41: 2026 | N41: 46054 | O41: Rayssa Karapeticov | Q41: 26 | R41: 31 | S41: 2413.68 | T41: 71696.53 | U41: 96796.8 | V41: 150 | W41: 15 | X41: 12 | Y41: 6.5 | Z41: 26.5 | AA41: 90000 | AB41: =metas[[#This Row],[Meta Individual]]/6500 -> 0.37133538 | AC41: =metas[[#This Row],[Meta Equipe]]/26500/3 -> 0.90184314
A42: COBERTURA DE METAS | M42: 2026 | N42: 46054 | O42: Junior Lopes | Q42: 16 | R42: 13 | S42: 14107.5 | T42: 71696.53 | U42: 97230 | V42: 150 | W42: 15 | X42: 12 | Y42: 10 | Z42: 26.5 | AA42: 90000 | AB42: =metas[[#This Row],[Meta Individual]]/10000 -> 1.41075 | AC42: =metas[[#This Row],[Meta Equipe]]/26500/3 -> 0.90184314
A43: RAYSSA | E43: JUNIOR | I43: PAULO | M43: 2026 | N43: 46054 | O43: Paulo Souza | Q43: 15 | R43: 17 | S43: 55175.4 | T43: 71696.53 | U43: 367161.6 | V43: 150 | W43: 15 | X43: 12 | Y43: 10 | Z43: 26.5 | AA43: 90000 | AB43: =metas[[#This Row],[Meta Individual]]/10000 -> 5.51754 | AC43: =metas[[#This Row],[Meta Equipe]]/26500/3 -> 0.90184314
B44: Meta | C44: Realizado | D44: Cobertura | F44: Meta | G44: Realizado | H44: Cobertura | J44: Meta | K44: Realizado | L44: Cobertura | M44: 2026 | N44: 46082 | O44: Rayssa Karapeticov | Q44: 21 | R44: 16 | S44: 6425.28 | T44: 23015.18 | U44: 72913.24 | V44: 150 | W44: 15 | X44: 12 | Y44: 7 | Z44: 27 | AA44: 90000 | AB44: =metas[[#This Row],[Meta Individual]]/7000 -> 0.91789714 | AC44: =metas[[#This Row],[Meta Equipe]]/27000/3 -> 0.28413802
A45: Proposta | B45: 15 | C45: 23 | D45: 1.5333333 | E45: Proposta | F45: 15 | G45: 17 | H45: 1.1333333 | I45: Proposta | J45: 15 | K45: 2 | L45: 0.13333333 | M45: 2026 | N45: 46082 | O45: Junior Lopes | Q45: 18 | R45: 16 | S45: 16288.54 | T45: 23015.18 | U45: 99854.09 | V45: 150 | W45: 15 | X45: 12 | Y45: 10 | Z45: 27 | AA45: 90000 | AB45: =metas[[#This Row],[Meta Individual]]/10000 -> 1.628854 | AC45: =metas[[#This Row],[Meta Equipe]]/27000/3 -> 0.28413802
A46: Apresentações | B46: 12 | C46: 20 | D46: 1.6666667 | E46: Apresentações | F46: 12 | G46: 14 | H46: 1.1666667 | I46: Apresentações | J46: 12 | K46: 1 | L46: 0.083333333 | M46: 2026 | N46: 46082 | O46: Paulo Souza | Q46: 7 | R46: 6 | S46: 301.26 | T46: 23015.18 | U46: 7400 | V46: 150 | W46: 15 | X46: 12 | Y46: 10 | Z46: 27 | AA46: 90000 | AB46: =metas[[#This Row],[Meta Individual]]/10000 -> 0.030126 | AC46: =metas[[#This Row],[Meta Equipe]]/27000/3 -> 0.28413802
B47: Meta | C47: Realizado | D47: Cobertura | F47: Meta | G47: Realizado | H47: Cobertura | J47: Meta | K47: Realizado | L47: Cobertura | M47: 2026 | N47: 46113 | O47: Rayssa Karapeticov | Q47: 9 | R47: 13 | S47: 2691.36 | T47: 15596.61 | U47: 55648 | V47: 150 | W47: 15 | X47: 12 | Y47: 7.5 | Z47: 27.5 | AA47: 90000 | AB47: =S47/7500 -> 0.358848 | AC47: =T47/27500/3 -> 0.18904982
A48: Proposta | B48: 15 | C48: 23 | D48: 1.5333333 | E48: Proposta | F48: 15 | G48: 17 | H48: 1.1333333 | I48: Proposta | J48: 15 | K48: 2 | L48: 0.13333333 | M48: 2026 | N48: 46113 | O48: Junior Lopes | Q48: 7 | R48: 7 | S48: 5224.65 | T48: 15596.61 | U48: 45200 | V48: 150 | W48: 15 | X48: 12 | Y48: 10 | Z48: 27.5 | AA48: 90000 | AB48: =S48/10000 -> 0.522465 | AC48: =T48/27500/3 -> 0.18904982
A49: Apresentações | B49: 12 | C49: 20 | D49: 1.6666667 | E49: Apresentações | F49: 12 | G49: 14 | H49: 1.1666667 | I49: Apresentações | J49: 12 | K49: 1 | L49: 0.083333333 | M49: 2026 | N49: 46113 | O49: Paulo Souza | Q49: 2 | R49: 2 | S49: 7680.6 | T49: 15596.61 | U49: 38800.64 | V49: 150 | W49: 15 | X49: 12 | Y49: 10 | Z49: 27.5 | AA49: 90000 | AB49: =S49/10000 -> 0.76806 | AC49: =T49/27500/3 -> 0.18904982
M50: 2026 | N50: 46143 | O50: Rayssa Karapeticov | Q50: 16 | R50: 15 | S50: 1254.53 | T50: 11164.25 | U50: 94263.71 | V50: 150 | W50: 15 | X50: 12 | Y50: 8 | Z50: 34 | AA50: 90000 | AB50: =metas[[#This Row],[Meta Individual]]/8000 -> 0.15681625 | AC50: =metas[[#This Row],[Meta Equipe]]/34000/4 -> 0.082090074
A51: FECHAMENTO DE: 01/06/2025 até 30/06/2025 | M51: 2026 | N51: 46143 | O51: Junior Lopes | Q51: 18 | R51: 19 | S51: 7194.36 | T51: 11164.25 | U51: 129305.78 | V51: 150 | W51: 15 | X51: 12 | Y51: 10 | Z51: 34 | AA51: 90000 | AB51: =metas[[#This Row],[Meta Individual]]/10000 -> 0.719436 | AC51: =metas[[#This Row],[Meta Equipe]]/34000/4 -> 0.082090074
A52: COBERTURA DE METAS | M52: 2026 | N52: 46143 | O52: Paulo Souza | Q52: 2 | R52: 1 | S52: 2715.36 | T52: 11164.25 | U52: 0 | V52: 150 | W52: 15 | X52: 12 | Y52: 10 | Z52: 34 | AA52: 90000 | AB52: =metas[[#This Row],[Meta Individual]]/10000 -> 0.271536 | AC52: =metas[[#This Row],[Meta Equipe]]/34000/4 -> 0.082090074
A53: RAYSSA | E53: JUNIOR | I53: PAULO | M53: 2026 | N53: 46143 | O53: Ronaldo Nascimento | Q53: 2 | R53: 4 | S53: 0 | T53: 11164.25 | U53: 0 | V53: 150 | W53: 15 | X53: 12 | Y53: 6 | Z53: 34 | AA53: 54000 | AB53: =metas[[#This Row],[Meta Individual]]/6000 -> 0 | AC53: =metas[[#This Row],[Meta Equipe]]/34000/4 -> 0.082090074
B54: Meta | C54: Realizado | D54: Cobertura | F54: Meta | G54: Realizado | H54: Cobertura | J54: Meta | K54: Realizado | L54: Cobertura | M54: 2026 | N54: 46174 | O54: Rayssa Karapeticov | Q54: 18 | R54: 15 | S54: 1638.14 | T54: 24028.3 | U54: 37716 | V54: 150 | W54: 15 | X54: 12 | Y54: 8.5 | Z54: 35 | AA54: 90000 | AB54: =metas[[#This Row],[Meta Individual]]/8500 -> 0.19272235 | AC54: =metas[[#This Row],[Meta Equipe]]/35000/4 -> 0.17163071
A55: Proposta | B55: 15 | C55: 25 | D55: 1.6666667 | E55: Proposta | F55: 15 | G55: 18 | H55: 1.2 | I55: Proposta | J55: 15 | K55: 3 | L55: 0.2 | M55: 2026 | N55: 46174 | O55: Junior Lopes | Q55: 16 | R55: 17 | S55: 14728 | T55: 24028.3 | U55: 49343.12 | V55: 150 | W55: 15 | X55: 12 | Y55: 10 | Z55: 35 | AA55: 90000 | AB55: =metas[[#This Row],[Meta Individual]]/10000 -> 1.4728 | AC55: =metas[[#This Row],[Meta Equipe]]/35000/4 -> 0.17163071
A56: Apresentações | B56: 12 | C56: 19 | D56: 1.5833333 | E56: Apresentações | F56: 12 | G56: 13 | H56: 1.0833333 | I56: Apresentações | J56: 12 | K56: 1 | L56: 0.083333333 | M56: 2026 | N56: 46174 | O56: Paulo Souza | Q56: 0 | R56: 0 | S56: 0 | T56: 24028.3 | U56: 0 | V56: 150 | W56: 15 | X56: 12 | Y56: 10 | Z56: 35 | AA56: 90000 | AB56: =metas[[#This Row],[Meta Individual]]/10000 -> 0 | AC56: =metas[[#This Row],[Meta Equipe]]/35000/4 -> 0.17163071
A57: Meta Individual | B57: 10000 | C57: 4260.96 | D57: 0.426096 | E57: Meta Individual | F57: 10000 | G57: 4579.8 | H57: 0.45798 | I57: Meta Individual | J57: 10000 | K57: 21435.01 | L57: 2.143501 | M57: 2026 | N57: 46174 | O57: Ronaldo Nascimento | Q57: 3 | R57: 8 | S57: 7662.16 | T57: 24028.3 | U57: 82160 | V57: 150 | W57: 15 | X57: 12 | Y57: 6.5 | Z57: 35 | AA57: 58500 | AB57: =metas[[#This Row],[Meta Individual]]/6500 -> 1.1787938 | AC57: =metas[[#This Row],[Meta Equipe]]/35000/4 -> 0.17163071
A58: Meta Equipe | B58: 30000 | C58: 30275.77 | D58: 1.0091923 | E58: Meta Equipe | F58: 30000 | G58: 30275.77 | H58: 1.0091923 | I58: Meta Equipe | J58: 30000 | K58: 30275.77 | L58: 1.0091923 | M58: 2026 | N58: 46204 | O58: Rayssa Karapeticov | Q58: 17 | R58: 12 | S58: 720 | T58: 2880 | U58: 112904 | V58: 150 | W58: 15 | X58: 12 | Y58: 9 | Z58: 36 | AA58: 90000 | AB58: =metas[[#This Row],[Meta Individual]]/9000 -> 0.08 | AC58: =metas[[#This Row],[Meta Equipe]]/36000/4 -> 0.02
A59: Meta Projetos | B59: 90000 | C59: 85918.58 | D59: 0.95465089 | E59: Meta Projetos | F59: 90000 | G59: 33826.34 | H59: 0.37584822 | I59: Meta Projetos | J59: 90000 | K59: 211246 | L59: 2.3471778 | M59: 2026 | N59: 46204 | O59: Junior Lopes | Q59: 14 | R59: 15 | S59: 0 | T59: =T58 -> 2880 | U59: 7042.9 | V59: 150 | W59: 15 | X59: 12 | Y59: 10 | Z59: 36 | AA59: 90000 | AB59: =metas[[#This Row],[Meta Individual]]/10000 -> 0 | AC59: =metas[[#This Row],[Meta Equipe]]/36000/4 -> 0.02
M60: 2026 | N60: 46204 | O60: Paulo Souza | Q60: 0 | R60: 0 | S60: 2160 | T60: =T59 -> 2880 | U60: 12680 | V60: 150 | W60: 15 | X60: 12 | Y60: 10 | Z60: 36 | AA60: 90000 | AB60: =metas[[#This Row],[Meta Individual]]/10000 -> 0.216 | AC60: =metas[[#This Row],[Meta Equipe]]/36000/4 -> 0.02
A61: FECHAMENTO DE: 01/07/2025 até 31/07/2025 | M61: 2026 | N61: 46204 | O61: Ronaldo Nascimento | Q61: 7 | R61: 11 | S61: ='Metas Quadro'!C18 -> 0 | T61: =T60 -> 2880 | U61: ='Metas Quadro'!C17 -> 0 | V61: 150 | W61: 15 | X61: 12 | Y61: 7 | Z61: 36 | AA61: 63000 | AB61: =metas[[#This Row],[Meta Individual]]/7000 -> 0 | AC61: =metas[[#This Row],[Meta Equipe]]/36000/4 -> 0.02
A62: COBERTURA DE METAS | M62: 2026 | N62: 46235 | O62: Rayssa Karapeticov | Q62: 11 | R62: 6 | S62: ='Metas Quadro'!C9 -> 10463.76 | T62: ='Metas Quadro'!C25 -> 10911.76 | U62: ='Metas Quadro'!C8 -> 16300 | V62: 150 | W62: 15 | X62: 12 | Y62: 9.5 | Z62: 37 | AA62: 90000 | AB62: =metas[[#This Row],[Meta Individual]]/9500 -> 1.1014484 | AC62: =metas[[#This Row],[Meta Equipe]]/36000/4 -> 0.075776111
A63: RAYSSA | E63: JUNIOR | I63: PAULO | M63: 2026 | N63: 46235 | O63: Junior Lopes | Q63: 1 | R63: 0 | S63: ='Metas Quadro'!C5 -> 448 | T63: =T62 -> 10911.76 | U63: ='Metas Quadro'!C4 -> 86455.76 | V63: 150 | W63: 15 | X63: 12 | Y63: 10 | Z63: 37 | AA63: 90000 | AB63: =metas[[#This Row],[Meta Individual]]/10000 -> 0.0448 | AC63: =metas[[#This Row],[Meta Equipe]]/36000/4 -> 0.075776111
B64: Meta | C64: Realizado | D64: Cobertura | F64: Meta | G64: Realizado | H64: Cobertura | J64: Meta | K64: Realizado | L64: Cobertura | M64: 2026 | N64: 46235 | O64: Paulo Souza | Q64: 1 | R64: 2 | S64: ='Metas Quadro'!C14 -> 0 | T64: =T63 -> 10911.76 | U64: ='Metas Quadro'!C13 -> 0 | V64: 150 | W64: 15 | X64: 12 | Y64: 10 | Z64: 37 | AA64: 90000 | AB64: =metas[[#This Row],[Meta Individual]]/metas[[#This Row],[OB Individual]] -> 0 | AC64: =metas[[#This Row],[Meta Equipe]]/36000/4 -> 0.075776111
A65: Proposta | B65: 15 | C65: 22 | D65: 1.4666667 | E65: Proposta | F65: 15 | G65: 17 | H65: 1.1333333 | I65: Proposta | J65: 15 | K65: 2 | L65: 0.13333333 | M65: 2026 | N65: 46235 | O65: Ronaldo Nascimento | Q65: 4 | R65: 0 | S65: ='Metas Quadro'!C18 -> 0 | T65: =T64 -> 10911.76 | U65: ='Metas Quadro'!C17 -> 0 | V65: 150 | W65: 15 | X65: 12 | Y65: 7.5 | Z65: 37 | AA65: 67500 | AB65: =metas[[#This Row],[Meta Individual]]/metas[[#This Row],[OB Individual]] -> 0 | AC65: =metas[[#This Row],[Meta Equipe]]/36000/4 -> 0.075776111
A66: Apresentações | B66: 12 | C66: 14 | D66: 1.1666667 | E66: Apresentações | F66: 12 | G66: 12 | H66: 1 | I66: Apresentações | J66: 12 | K66: 1 | L66: 0.083333333
A67: Meta Individual | B67: 10000 | C67: 1733.34 | D67: 0.173334 | E67: Meta Individual | F67: 10000 | G67: 142.56 | H67: 0.014256 | I67: Meta Individual | J67: 10000 | K67: 10000 | L67: 1
A68: Meta Equipe | B68: 30000 | C68: 11875.9 | D68: 0.39586333 | E68: Meta Equipe | F68: 30000 | G68: 11875.9 | H68: 0.39586333 | I68: Meta Equipe | J68: 30000 | K68: 11875.9 | L68: 0.39586333
A69: Meta Projetos | B69: 90000 | C69: 86932.5 | D69: 0.96591667 | E69: Meta Projetos | F69: 90000 | G69: 6071.21 | H69: 0.067457889 | I69: Meta Projetos | J69: 90000 | K69: 90575 | L69: 1.0063889
A71: FECHAMENTO DE: 01/08/2025 até 31/08/2025
A72: COBERTURA DE METAS
A73: RAYSSA | E73: JUNIOR | I73: PAULO
B74: Meta | C74: Realizado | D74: Cobertura | F74: Meta | G74: Realizado | H74: Cobertura | J74: Meta | K74: Realizado | L74: Cobertura
A75: Proposta | B75: 15 | C75: 25 | D75: 1.6666667 | E75: Proposta | F75: 15 | G75: 16 | H75: 1.0666667 | I75: Proposta | J75: 15 | K75: 8 | L75: 0.53333333
A76: Apresentações | B76: 12 | C76: 17 | D76: 1.4166667 | E76: Apresentações | F76: 12 | G76: 13 | H76: 1.0833333 | I76: Apresentações | J76: 12 | K76: 8 | L76: 0.66666667
A77: Meta Individual | B77: 10000 | C77: 1667.4 | D77: 0.16674 | E77: Meta Individual | F77: 10000 | G77: 5551.4 | H77: 0.55514 | I77: Meta Individual | J77: 10000 | K77: 7361.47 | L77: 0.736147
A78: Meta Equipe | B78: 30000 | C78: 14580.27 | D78: 0.486009 | E78: Meta Equipe | F78: 30000 | G78: 14580.27 | H78: 0.486009 | I78: Meta Equipe | J78: 30000 | K78: 14580.27 | L78: 0.486009
A79: Meta Projetos | B79: 90000 | C79: 37218.92 | D79: 0.41354356 | E79: Meta Projetos | F79: 90000 | G79: 69366.4 | H79: 0.77073778 | I79: Meta Projetos | J79: 90000 | K79: 57100 | L79: 0.63444444
A81: FECHAMENTO DE: 01/09/2025 até 30/09/2025
A82: COBERTURA DE METAS
A83: RAYSSA | E83: JUNIOR | I83: PAULO
B84: Meta | C84: Realizado | D84: Cobertura | F84: Meta | G84: Realizado | H84: Cobertura | J84: Meta | K84: Realizado | L84: Cobertura
A85: Proposta | B85: 15 | C85: 25 | D85: 1.6666667 | E85: Proposta | F85: 15 | G85: 16 | H85: 1.0666667 | I85: Proposta | J85: 15 | K85: 11 | L85: 0.73333333
A86: Apresentações | B86: 12 | C86: 16 | D86: 1.3333333 | E86: Apresentações | F86: 12 | G86: 18 | H86: 1.5 | I86: Apresentações | J86: 12 | K86: 11 | L86: 0.91666667
A87: Meta Individual | B87: 10000 | C87: 3619.87 | D87: 0.361987 | E87: Meta Individual | F87: 10000 | G87: 6448.22 | H87: 0.644822 | I87: Meta Individual | J87: 10000 | K87: 2857.1 | L87: 0.28571
A88: Meta Equipe | B88: 30000 | C88: 12925.19 | D88: 0.43083967 | E88: Meta Equipe | F88: 30000 | G88: 12925.19 | H88: 0.43083967 | I88: Meta Equipe | J88: 30000 | K88: 12925.19 | L88: 0.43083967
A89: Meta Projetos | B89: 90000 | C89: 156911.7 | D89: 1.7434633 | E89: Meta Projetos | F89: 90000 | G89: 134306.46 | H89: 1.492294 | I89: Meta Projetos | J89: 90000 | K89: 47500 | L89: 0.52777778
A91: FECHAMENTO DE: 01/10/2025 até 31/10/2025
A92: COBERTURA DE METAS
A93: RAYSSA | E93: JUNIOR | I93: PAULO
B94: Meta | C94: Realizado | D94: Cobertura | F94: Meta | G94: Realizado | H94: Cobertura | J94: Meta | K94: Realizado | L94: Cobertura
A95: Proposta | B95: 15 | C95: 15 | D95: 1 | E95: Proposta | F95: 15 | G95: 15 | H95: 1 | I95: Proposta | J95: 15 | K95: 15 | L95: 1
A96: Apresentações | B96: 12 | C96: 12 | D96: 1 | E96: Apresentações | F96: 12 | G96: 12 | H96: 1 | I96: Apresentações | J96: 12 | K96: 12 | L96: 1
A97: Meta Individual | B97: 6000 | C97: 1927.89 | D97: 0.321315 | E97: Meta Individual | F97: 10000 | G97: 0 | H97: 0 | I97: Meta Individual | J97: 10000 | K97: 0 | L97: 0
A98: Meta Equipe | B98: 30000 | C98: 1927.89 | D98: 0.064263 | E98: Meta Equipe | F98: 30000 | G98: 1927.89 | H98: 0.064263 | I98: Meta Equipe | J98: 30000 | K98: 1927.89 | L98: 0.064263
A99: Meta Projetos | B99: 90000 | C99: 117851.89 | D99: 1.3094654 | E99: Meta Projetos | F99: 90000 | G99: 39131.15 | H99: 0.43479056 | I99: Meta Projetos | J99: 90000 | K99: 0 | L99: 0
A101: FECHAMENTO DE: 01/11/2025 até 31/11/2025
A102: COBERTURA DE METAS
A103: RAYSSA | E103: JUNIOR | I103: PAULO
B104: Meta | C104: Realizado | D104: Cobertura | F104: Meta | G104: Realizado | H104: Cobertura | J104: Meta | K104: Realizado | L104: Cobertura
...

Sheet KPI
A2: RAYSSA KARAPETICOV
D18: COBERTURA METAS | H18: COBERTURA METAS EQUIPES | N18: APRESENTAÇÃO RAYSSA | Q18: APRESENTAÇÃO JUNIOR LOPES | T18: APRESENTAÇÃO PAULO | W18: APRESENTAÇÃO RONALDO | AA18: APRESENTAÇÃO BASE RAYSSA | AD18: APRESENTAÇÃO BASE PAULO
D19: Vendedor | E19: Rayssa Karapeticov | H19: Ano | I19: (Vários itens) | N19: Responsável | O19: Rayssa Karapeticov | Q19: Responsável | R19: Junior Lopes | T19: Responsável | U19: Paulo Souza | W19: Responsável | X19: Ronaldo Nascimento | AA19: Responsável | AB19: Rayssa Karapeticov | AD19: Responsável | AE19: Paulo Souza
D20: Ano | E20: (Vários itens) | H20: Vendedor | I20: (Tudo) | N20: DataApresentação1 | O20: (Vários itens) | Q20: DataApresentação1 | R20: (Vários itens) | T20: DataApresentação1 | U20: (Vários itens) | W20: DataApresentação1 | X20: (Vários itens) | AA20: DataApresentação1 | AB20: (Vários itens) | AD20: DataApresentação1 | AE20: (Vários itens)
D22: Rótulos de Linha | E22: Cobertura | F22: Objetivo | H22: Rótulos de Linha | I22: Cobertura | J22: Objetivo | N22: Rótulos de Linha | O22: Soma de qtde | Q22: Rótulos de Linha | R22: Soma de QTDE | T22: Rótulos de Linha | U22: Soma de QTDE | W22: Rótulos de Linha | X22: Soma de qtde | AA22: Rótulos de Linha | AB22: Soma de Qdte | AD22: Rótulos de Linha | AE22: Soma de Qdte
D23: jan | E23: 0.44970333 | F23: 6 | H23: jan | I23: 0.67332538 | J23: 78 | N23: max led | O23: 1 | Q23: startools ferramentas, comercio, importacao e exportacao ltda | R23: 1 | T23: Total Geral | W23: estilo ar | X23: 1 | AA23: Mta Panelas | AB23: 1 | AD23: Total Geral
D24: fev | E24: 0.37133538 | F24: 6.5 | H24: fev | I24: 2.7055294 | J24: 79.5 | N24: Total Geral | O24: 1 | Q24: encartelados nina - erp | R24: 1 | W24: fikssar distribuidora | X24: 1 | AA24: Campeao | AB24: 1
D25: mar | E25: 0.91789714 | F25: 7 | H25: mar | I25: 0.85241407 | J25: 81 | Q25: encartelados nina - cloud | R25: 1 | W25: marden medical | X25: 1 | AA25: QUALITY HOUSE - WMS | AB25: 1
D26: abr | E26: 0.358848 | F26: 7.5 | H26: abr | I26: 0.56714945 | J26: 82.5 | Q26: tecelagem castilho (e-commerce) | R26: 1 | W26: Total Geral | X26: 3 | AA26: SUTT IMPORTADORA - Cloud | AB26: 1
D27: mai | E27: 0.14790625 | F27: 8 | H27: mai | I27: 0.27155794 | J27: 136 | Q27: istok comercio importacao (erp) | R27: 1 | AA27: Univendas - BI | AB27: 1
D28: Total Geral | E28: 2.2456901 | F28: 35 | H28: Total Geral | I28: 5.0699763 | J28: 457 | Q28: istok comercio importação (cloud) | R28: 1 | AA28: SHOCK IMPORTS - Tray | AB28: 1
Q29: startools ferramentas (erp) | R29: 1 | AA29: Total Geral | AB29: 6
Q30: mdl - boleto whats | R30: 1
Q31: star distribuidora - boleto whats | R31: 1
Q32: Total Geral | R32: 9
N1330: PROPOSTA RAYSSA | Q1330: PROPOSTA JUNIOR LOPES | T1330: PROPOSTA PAULO | W1330: PROPOSTA RONALDO | AA1330: PROPOSTA RAYSSA | AD1330: PROPOSTA PAULO
N1331: Responsável | O1331: Rayssa Karapeticov | Q1331: Responsável | R1331: Junior Lopes | T1331: Responsável | U1331: Paulo Souza | W1331: Responsável | X1331: Ronaldo Nascimento | AA1331: Responsável | AB1331: Rayssa Karapeticov | AD1331: Responsável | AE1331: Paulo Souza
N1332: Data Proposta | O1332: (Vários itens) | Q1332: Data Proposta | R1332: (Vários itens) | T1332: Data Proposta | U1332: (Vários itens) | W1332: Data Proposta | X1332: (Vários itens) | AA1332: Data Proposta | AB1332: (Vários itens) | AD1332: Data Proposta | AE1332: (Vários itens)
N1334: Rótulos de Linha | O1334: Soma de QTDE | Q1334: Rótulos de Linha | R1334: Soma de QTDE | T1334: Rótulos de Linha | U1334: Soma de QTDE | W1334: Rótulos de Linha | X1334: Soma de qtde | AA1334: Rótulos de Linha | AB1334: Soma de Qdte | AD1334: Rótulos de Linha | AE1334: Soma de Qdte
N1335: simao distribuidora | O1335: 1 | Q1335: encartelados nina - erp | R1335: 1 | T1335: hober artefatos plasticos ltda | U1335: 1 | W1335: fikssar distribuidora | X1335: 1 | AA1335: Campeao | AB1335: 1 | AD1335: Total Geral
N1336: fernandopolis industria e comercio de piscinas e acessorios ltda | O1336: 1 | Q1336: encartelados nina - cloud | R1336: 1 | T1336: Total Geral | U1336: 1 | W1336: Total Geral | X1336: 1 | AA1336: Mta Panelas | AB1336: 1
N1337: Total Geral | O1337: 2 | Q1337: mdl (horas) | R1337: 1 | AA1337: QUALITY HOUSE - WMS | AB1337: 1
Q1338: istok comercio importacao (erp) | R1338: 1 | AA1338: SUTT IMPORTADORA - Cloud | AB1338: 1
Q1339: istok comercio importação (cloud) | R1339: 1 | AA1339: Univendas - BI | AB1339: 1
Q1340: baag - horas | R1340: 1 | AA1340: Precisa Import - Power BI | AB1340: 1
Q1341: mdl - comex | R1341: 1 | AA1341: SHOCK IMPORTS - Tray | AB1341: 1
Q1342: mdl - boleto whats | R1342: 1 | AA1342: Total Geral | AB1342: 7
Q1343: star distribuidora - boleto whats | R1343: 1
Q1344: Total Geral | R1344: 9

Sheet Forecast
A1: Qtde | B1: Cliente | C1: Produto | D1: Responsável | E1: Vlr Projeto | F1: Mensalidade | G1: Horas | H1: Pipeline | I1: Temperatura
A2: 1 | B2: Porto Brasil Cerâmica – AFV | C2: AFV | D2: Junior Lopes | E2: 33920 | F2: 3768 | G2: 160 | H2: Vendas | I2: 0.5
A3: 1 | B3: Renovação Porcelanas – AFV | C3: AFV | D3: Junior Lopes | E3: 55713 | F3: 6391 | G3: 292 | H3: Vendas | I3: 0.3
A4: 1 | B4: Tiago Eletrônicos – B2B | C4: B2B | D4: Junior Lopes | E4: 26200 | F4: 3000 | G4: 80 | H4: Vendas | I4: 0.9
A5: 1 | B5: Amilplast Ind – ERP | C5: ERP | D5: Junior Lopes | E5: 51300 | F5: 1734 | G5: 270 | H5: Vendas | I5: 0.9
A6: 1 | B6: MDL Import – Cloud | C6: CLOUD | D6: Junior Lopes | E6: 1600 | F6: 2568 | G6: 16 | H6: Vendas | I6: 0.8
A7: 1 | B7: Plasbrink Embalagens Plásticas Ltda – ERP | C7: ERP | D7: Junior Lopes | E7: 81786 | F7: 7965 | G7: 430 | H7: Vendas | I7: 0.5
A8: 1 | B8: Plasbrink Embalagens Plásticas Ltda – Cloud | C8: CLOUD | D8: Junior Lopes | E8: 1600 | F8: 3356 | G8: 16 | H8: Vendas | I8: 0.5
A9: 1 | B9: Preciza Import – Boleto WhatsApp | C9: ADDON BOLETO WHATSAPP | D9: Junior Lopes | E9: 0 | F9: 356.4 | G9: 0 | H9: Vendas | I9: 0.5
A10: 1 | B10: Marka Têxtil – ERP | C10: ERP | D10: Junior Lopes | E10: 118908 | F10: 13048 | G10: 540 | H10: Vendas | I10: 0.8
A11: 1 | B11: Marka Têxtil – Cloud | C11: CLOUD | D11: Junior Lopes | E11: 1600 | F11: 6846 | G11: 16 | H11: Vendas | I11: 0.8
A12: 1 | B12: Sevilla Trade – ERP | C12: ERP | D12: Junior Lopes | E12: 38380 | F12: 1075 | G12: 190 | H12: Vendas | I12: 0.3
A13: 1 | B13: Sevilla Trade – Cloud | C13: CLOUD | D13: Junior Lopes | E13: 1600 | F13: 2174 | G13: 16 | H13: Vendas | I13: 0.3
... A18: 1 | B18: Conthey – ERP | C18: ERP | D18: Junior Lopes | E18: 72000 | F18: 4215 | G18: 360 | H18: Vendas | I18: 0.5
A19: 1 | B19: Conthey – AFV | C19: AFV | D19: Junior Lopes | E19: =40*180 -> 7200 | F19: 1964.2 | G19: 8 | H19: Vendas | I19: 0.5
A20: 1 | B20: Conthey – Cloud | C20: CLOUD | D20: Junior Lopes | E20: 1600 | F20: 5242 | G20: 16 | H20: Vendas | I20: 0.5
A21: 1 | B21: Star – B2B | C21: B2B | D21: Junior Lopes | E21: 26200 | F21: 3400 | G21: 80 | H21: Vendas | I21: 0.3
A22: 1 | B22: Erca Alumínio – Imp. XML | C22: ADDON IMPORTAÇÃO XML | D22: Junior Lopes | E22: 3392 | F22: 356.4 | G22: 16 | H22: Vendas | I22: 0.5
A23: 1 | B23: Toptem – ERP | C23: ERP | D23: Junior Lopes | E23: 44000 | F23: 1102 | G23: 220 | H23: Vendas | I23: 0.3
A24: 1 | B24: Toptem – AFV | C24: AFV | D24: Junior Lopes | E24: 8000 | F24: 1865 | G24: 40 | H24: Vendas | I24: 0.3
A25: 1 | B25: Chavetas Comércio de Peças e Ferramentas Ltda | C25: QUALIFICANDO | D25: Junior Lopes | E25: apresentando | F25: apresentando | G25: apresentando | H25: Vendas | I25: 0.3
A26: 1 | B26: Color Unhas | C26: QUALIFICANDO | D26: Junior Lopes | E26: apresentando | F26: apresentando | G26: apresentando | H26: Vendas | I26: 0.3
A27: 1 | B27: Folha Dourada Tabacos Ltda | C27: QUALIFICANDO | D27: Junior Lopes | E27: apresentando | F27: apresentando | G27: apresentando | H27: Vendas | I27: 0.3
A28: 1 | B28: Atacadão Delfino | C28: QUALIFICANDO | D28: Junior Lopes | E28: qualificando | F28: qualificando | G28: qualificando | H28: Vendas | I28: 0.3
A29: 1 | B29: BK Comércio | C29: QUALIFICANDO | D29: Junior Lopes | E29: qualificando | F29: qualificando | G29: qualificando | H29: Vendas | I29: 0.3
A30: 1 | B30: Sunguider Importador/Distribuidor | C30: ERP | D30: Paulo Souza | E30: apresentando | F30: apresentando | G30: apresentando | H30: Vendas | I30: 0.5
A31: 1 | B31: Indústria Oyshi | C31: AFV | D31: Paulo Souza | E31: 16000 | F31: 1558 | G31: 80 | H31: Vendas | I31: 0.5
A32: 1 | B32: Alumínio Ramos | C32: ERP | D32: Paulo Souza | E32: 153599 | F32: 9247.44 | G32: 768 | H32: Vendas | I32: 0.3
A33: 1 | B33: Wellmix – ERP | C33: ERP | D33: Paulo Souza | E33: 254760 | F33: 15786 | G33: 1158 | H33: Vendas | I33: 0.3
A34: 1 | B34: Medihosp | C34: AFV | D34: Paulo Souza | E34: 20000 | F34: 5880 | G34: 80 | H34: Vendas | I34: 0.3
A35: 1 | B35: Bela Flor | C35: ERP, AFV, WMS | D35: Paulo Souza | E35: 130600 | F35: 16809 | G35: 653 | H35: Vendas | I35: 0.3
A36: 1 | B36: Imev Proteínas | C36: AFV | D36: Paulo Souza | E36: 16000 | F36: 5880 | G36: 80 | H36: Vendas | I36: 0.9
A37: 1 | B37: AIH Importadora de Artigos de Presentes Ltda | C37: ERP, AFV | D37: Paulo Souza | E37: 72000 | F37: 8045 | G37: 360 | H37: Vendas | I37: 0.3
A38: 1 | B38: Maia 4 | C38: ERP | D38: Paulo Souza | E38: apresentando | F38: apresentando | G38: apresentando | H38: Vendas | I38: 0.3
A39: 1 | B39: Zomax | C39: AFV | D39: Paulo Souza | E39: apresentando | F39: apresentando | G39: apresentando | H39: Vendas | I39: 0.3
A40: 1 | B40: Val Port | C40: ERP, PDV | D40: Paulo Souza | E40: apresentando | F40: apresentando | G40: apresentando | H40: Vendas | I40: 0.3
A41: 1 | B41: Tron | C41: ERP | D41: Paulo Souza | E41: 315000 | F41: 32575 | G41: 1500 | H41: Vendas | I41: 0.3
A42: 1 | B42: HF Utilidades | C42: ERP | D42: Paulo Souza | E42: 47200 | F42: 2298.1 | G42: 236 | H42: Vendas | I42: 0.3
A43: 1 | B43: Valport – B2B | C43: B2B | D43: Paulo Souza | E43: apresentando | F43: apresentando | G43: apresentando | H43: Vendas | I43: 0.3
A44: 1 | B44: Atual Mix | C44: ERP | D44: Paulo Souza | E44: apresentando | F44: apresentando | G44: apresentando | H44: Vendas | I44: 0.3
A45: 1 | B45: Union Ind | C45: ERP | D45: Paulo Souza | E45: apresentando | F45: apresentando | G45: apresentando | H45: Vendas | I45: 0.3
A46: 1 | B46: Distribuidora do Wicca | C46: ERP | D46: Paulo Souza | E46: apresentando | F46: apresentando | G46: apresentando | H46: Vendas | I46: 0.3
A47: 1 | B47: JP Distribuidora – Agenda Visita | C47: ADDON AGENDA | D47: Paulo Souza | E47: 0 | F47: 66 | G47: 0 | H47: Vendas | I47: 0.9
A48: 1 | B48: Alumínio Nacional | C48: TREINAMENTO | D48: Paulo Souza | E48: 63200 | F48: 0 | G48: 316 | H48: Upselling | I48: 0.5
A49: 1 | B49: Afey Peças | C49: ERP | D49: Paulo Souza | E49: apresentando | F49: apresentando | G49: apresentando | H49: Vendas | I49: 0.3
A50: 1 | B50: NVT Importadora | C50: ERP, AFV | D50: Paulo Souza | E50: 72000 | F50: 8241 | G50: 360 | H50: Vendas | I50: 0.3
A51: 1 | B51: Olé Alimentos | C51: AFV | D51: Paulo Souza | E51: 16000 | F51: 18330 | G51: 80 | H51: Vendas | I51: 0.9
A52: 1 | B52: Loggix Serviços Material Escolar | C52: QUALIFICANDO | D52: Paulo Souza | E52: qualificando | F52: qualificando | G52: qualificando | H52: Vendas | I52: 0.3
A53: 1 | B53: Zini Home | C53: QUALIFICANDO | D53: Paulo Souza | E53: apresentando | F53: apresentando | G53: apresentando | H53: Vendas | I53: 0.3
A54: 1 | B54: Russa 7 Berg Distribuidora | C54: QUALIFICANDO | D54: Paulo Souza | E54: apresentando | F54: apresentando | G54: apresentando | H54: Vendas | I54: 0.3
A55: 1 | B55: Stok Frios | C55: QUALIFICANDO | D55: Paulo Souza | E55: qualificando | F55: qualificando | G55: qualificando | H55: Vendas | I55: 0.3
A56: 1 | B56: Deltamed Comércio | C56: QUALIFICANDO | D56: Paulo Souza | H56: Vendas | I56: 0.3
A57: 1 | B57: Evolux – ERP · PCP · WMS · AFV | C57: ERP, PCP, WMS, AFV | D57: Rayssa Karapeticov | E57: 46200 | F57: 1460.47 | G57: 220 | H57: Vendas | I57: 0.5
A58: 1 | B58: Doce Festa – ERP · AFV | C58: ERP | D58: Rayssa Karapeticov | E58: apresentando | F58: apresentando | G58: apresentando | H58: Vendas | I58: 0.3
A59: 1 | B59: Irriga House | C59: ERP, AFV | D59: Rayssa Karapeticov | E59: apresentando | F59: apresentando | G59: apresentando | H59: Vendas | I59: 0.3
A60: 1 | B60: CLS Indústria de Produtos Químicos Ltda | C60: ERP | D60: Rayssa Karapeticov | E60: apresentando | F60: apresentando | G60: apresentando | H60: Vendas | I60: 0.3
A61: 1 | B61: Maral | C61: QUALIFICANDO | D61: Rayssa Karapeticov | E61: qualificando | F61: qualificando | G61: qualificando | H61: Vendas | I61: 0.3
A62: 1 | B62: Fisiohosp | C62: QUALIFICANDO | D62: Rayssa Karapeticov | E62: qualificando | F62: qualificando | G62: qualificando | H62: Vendas | I62: 0.3
A63: 1 | B63: Vida Fitness | C63: QUALIFICANDO | D63: Rayssa Karapeticov | E63: qualificando | F63: qualificando | G63: qualificando | H63: Vendas | I63: 0.3
A64: 1 | B64: Horto das Acácias | C64: QUALIFICANDO | D64: Rayssa Karapeticov | E64: qualificando | F64: qualificando | G64: qualificando | H64: Vendas | I64: 0.3
A65: 1 | B65: Devons Hair | C65: QUALIFICANDO | D65: Rayssa Karapeticov | E65: qualificando | F65: qualificando | G65: qualificando | H65: Vendas | I65: 0.3
A66: 1 | B66: Alpinpro | C66: QUALIFICANDO | D66: Rayssa Karapeticov | E66: qualificando | F66: qualificando | G66: qualificando | H66: Vendas | I66: 0.3
A67: 1 | B67: DUS – Mercado Livre Full | C67: Addon Mercado Livrefull | D67: Rayssa Karapeticov | E67: 3360 | F67: 712.8 | G67: 16 | H67: Upselling | I67: 0.3
A68: 1 | B68: Gyn Atacado Ltda – Integrador E-commerce | C68: Hub Ecommerce | D68: Rayssa Karapeticov | E68: 16200 | F68: 712.8 | G68: 80 | H68: Upselling | I68: 0.5
A69: 1 | B69: Univendas – Cloud | C69: Cloud | D69: Rayssa Karapeticov | E69: 1600 | F69: 4718.3 | G69: 8 | H69: Upselling | I69: 0.8
A70: 1 | B70: Qualyplas – PCP | C70: PCP | D70: Rayssa Karapeticov | E70: apresentando | F70: apresentando | G70: apresentando | H70: Upselling | I70: 0.3
A71: 1 | B71: Qualyplas – MDE | C71: MDE | D71: Rayssa Karapeticov | E71: 3360 | F71: 356.4 | G71: 16 | H71: Upselling | I71: 0.3
A72: 1 | B72: Qualyplas – Contábil | C72: Contábil | D72: Rayssa Karapeticov | E72: 25200 | F72: 1045.44 | G72: 120 | H72: Upselling | I72: 0.3
A73: 1 | B73: Rischioto – Routeasy | C73: Routeasy | D73: Rayssa Karapeticov | E73: 3360 | F73: 712.8 | G73: 16 | H73: Upselling | I73: 0.3
A74: 1 | B74: Colorflex – AFV | C74: AFV | D74: Rayssa Karapeticov | E74: 3360 | F74: 196.42 | G74: 16 | H74: Upselling | I74: 0.5
A75: 1 | B75: Parolar – Checkout | C75: Checkout | D75: Rayssa Karapeticov | E75: 5040 | F75: 1140.48 | G75: 24 | H75: Upselling | I75: 0.8
A76: 1 | B76: Multipresentes Presentes e Brinquedos Ltda | C76: Proposta WEB | D76: Rayssa Karapeticov | E76: 0 | F76: 2613.6 | G76: 0 | H76: Upselling | I76: 0.3
A77: 1 | B77: Chahin – Alteração Empresa Integrador | C77: Treinamento | D77: Rayssa Karapeticov | E77: 3360 | F77: 0 | G77: 16 | H77: Upselling | I77: 0.3
A78: 1 | B78: Gyn Atacado Ltda – B2B | C78: B2B | D78: Rayssa Karapeticov | E78: 13100 | F78: 1700 | G78: 80 | H78: Upselling | I78: 0.3
A79: 1 | B79: Gyn Atacado Ltda – BI | C79: BI | D79: Rayssa Karapeticov | E79: apresentando | F79: apresentando | G79: apresentando | H79: Upselling | I79: 0.3
A80: 1 | B80: Rischioto – CNPJ | C80: CNPJ | D80: Rayssa Karapeticov | E80: 10671 | F80: 1680 | G80: 8 | H80: Upselling | I80: 0.3
A81: 1 | B81: Quality House – BI | C81: BI | D81: Rayssa Karapeticov | E81: 8100 | F81: 1080 | G81: 60 | H81: Upselling | I81: 0.3
A82: 1 | B82: Quality House – WMS | C82: WMS | D82: Rayssa Karapeticov | E82: 29400 | F82: 0 | G82: 160 | H82: Upselling | I82: 0.3
A83: 1 | B83: Dvidros – Estoque Futuro | C83: Treinamento | D83: Rayssa Karapeticov | E83: 5040 | F83: 0 | G83: 28 | H83: Upselling | I83: 0.3

Sheet ||

Sheet KPI-Metas
A1: RELATÓTIO APURAÇÃO OBJETIVOS DE FEVEREIRO 2026 | Q1: =A1 -> RELATÓTIO APURAÇÃO OBJETIVOS DE FEVEREIRO 2026 | AH1: =Q1 -> RELATÓTIO APURAÇÃO OBJETIVOS DE FEVEREIRO 2026 | AY1: RELATÓTIO APURAÇÃO OBJETIVOS DE MARÇO 2026 | BO1: =AY1 -> RELATÓTIO APURAÇÃO OBJETIVOS DE MARÇO 2026 | CF1: =BO1 -> RELATÓTIO APURAÇÃO OBJETIVOS DE MARÇO 2026 | CW1: RELATÓTIO APURAÇÃO OBJETIVOS DE MARÇO 2026 | DM1: =CW1 -> RELATÓTIO APURAÇÃO OBJETIVOS DE MARÇO 2026 | ED1: =DM1 -> RELATÓTIO APURAÇÃO OBJETIVOS DE MARÇO 2026
A2: APURAÇÃO: 02/03/2026 | Q2: =A2 -> APURAÇÃO: 02/03/2026 | AH2: =Q2 -> APURAÇÃO: 02/03/2026 | AY2: APURAÇÃO: 02/04/2026 | BO2: =AY2 -> APURAÇÃO: 02/04/2026 | CF2: =BO2 -> APURAÇÃO: 02/04/2026 | CW2: APURAÇÃO: 03/05/2026 | DM2: =CW2 -> APURAÇÃO: 03/05/2026 | ED2: =DM2 -> APURAÇÃO: 03/05/2026
A3: PERÍODO: 01/02/2026 até 28/02/2026 | Q3: =A3 -> PERÍODO: 01/02/2026 até 28/02/2026 | AH3: =Q3 -> PERÍODO: 01/02/2026 até 28/02/2026 | AY3: PERÍODO: 01/03/2026 até 31/03/2026 | BO3: =AY3 -> PERÍODO: 01/03/2026 até 31/03/2026 | CF3: =BO3 -> PERÍODO: 01/03/2026 até 31/03/2026 | CW3: PERÍODO: 01/04/2026 até 30/04/2026 | DM3: =CW3 -> PERÍODO: 01/04/2026 até 30/04/2026 | ED3: =DM3 -> PERÍODO: 01/04/2026 até 30/04/2026
A5: RAYSSA | F5: VENDAS | W5: VENDAS | AH5: PAULO | AM5: VENDAS | AY5: RAYSSA | BD5: VENDAS | BO5: JUNIOR | BU5: VENDAS | CF5: PAULO | CK5: VENDAS | CW5: RAYSSA | DB5: VENDAS | DM5: JUNIOR | DS5: VENDAS | ED5: PAULO | EI5: VENDAS
B6: Meta | C6: Realizado | D6: Cobertura | F6: RAYSSA | J6: RAYSSA | R6: Meta | S6: Realizado | T6: Cobertura | W6: JUNIOR | AI6: Meta | AJ6: Realizado | AK6: Cobertura | AM6: PAULO | AZ6: Meta | BA6: Realizado | BB6: Cobertura | BD6: RAYSSA | BH6: RAYSSA | BP6: Meta | BQ6: Realizado | BR6: Cobertura | BU6: JUNIOR | CG6: Meta | CH6: Realizado | CI6: Cobertura | CK6: PAULO | CX6: Meta | CY6: Realizado | CZ6: Cobertura | DB6: RAYSSA | DF6: RAYSSA | DN6: Meta | DO6: Realizado | DP6: Cobertura | DS6: JUNIOR | EE6: Meta | EF6: Realizado | EG6: Cobertura | EI6: PAULO
A7: Proposta (15) | B7: 15 | C7: 26 | D7: =C7/B7 -> 1.7333333 | F7: Data | G7: Ticket | H7: Vendedor | I7: Cliente | J7: Produto | K7: TipoReceita | L7: Qtde | M7: VlrUnitário | N7: VlrTotal | O7: Vlr Meta | Q7: Proposta | R7: 15 | S7: 16 | T7: =S7/R7 -> 1.0666667 | W7: Data | X7: Ticket | Y7: Vendedor | Z7: Cliente | AA7: Produto | AB7: TipoReceita | AC7: Qtde | AD7: VlrUnitário | AE7: VlrTotal | AF7: Vlr Meta | AH7: Proposta | AI7: 15 | AJ7: 17 | AK7: =AJ7/AI7 -> 1.1333333 | AM7: Data | AN7: Ticket | AO7: Vendedor | AP7: Cliente | AQ7: Produto | AR7: TipoReceita | AS7: Qtde | AT7: VlrUnitário | AU7: VlrTotal | AV7: Vlr Meta | AY7: Proposta (15) | AZ7: 15 | BA7: 21 | BB7: =BA7/AZ7 -> 1.4 | BD7: Data | BE7: Ticket | BF7: Vendedor | BG7: Cliente | BH7: Produto | BI7: TipoReceita | BJ7: Qtde | BK7: VlrUnitário | BL7: VlrTotal | BM7: Vlr Meta | BO7: Proposta | BP7: 15 | BQ7: 18 | BR7: =BQ7/BP7 -> 1.2 | BU7: Data | BV7: Ticket | BW7: Vendedor | BX7: Cliente | BY7: Produto | BZ7: TipoReceita | CA7: Qtde | CB7: VlrUnitário | CC7: VlrTotal | CD7: Vlr Meta | CF7: Proposta | CG7: 15 | CH7: 7 | CI7: =CH7/CG7 -> 0.46666667 | CK7: Data | CL7: Ticket | CM7: Vendedor | CN7: Cliente | CO7: Produto | CP7: TipoReceita | CQ7: Qtde | CR7: VlrUnitário | CS7: VlrTotal | CT7: Vlr Meta | CW7: Proposta (15) | CX7: 15 | CY7: 9 | CZ7: =CY7/CX7 -> 0.6 | DB7: Data | DC7: Ticket | DD7: Vendedor | DE7: Cliente | DF7: Produto | DG7: TipoReceita | DH7: Qtde | DI7: VlrUnitário | DJ7: VlrTotal | DK7: Vlr Meta | DM7: Proposta | DN7: 15 | DO7: 7 | DP7: =DO7/DN7 -> 0.46666667 | DS7: Data | DT7: Ticket | DU7: Vendedor | DV7: Cliente | DW7: Produto | DX7: TipoReceita | DY7: Qtde | DZ7: VlrUnitário | EA7: VlrTotal | EB7: Vlr Meta | ED7: Proposta | EE7: 15 | EF7: 2 | EG7: =EF7/EE7 -> 0.13333333 | EI7: Data | EJ7: Ticket | EK7: Vendedor | EL7: Cliente | EM7: Produto | EN7: TipoReceita | EO7: Qtde | EP7: VlrUnitário | EQ7: VlrTotal | ER7: Vlr Meta
A8: Apresentações (12) | B8: 12 | C8: 31 | D8: =C8/B8 -> 2.5833333 | F8: 46059 | G8: 137739 | H8: Rayssa Karapeticov | I8: Textil Regimara | J8: BI | K8: CDU | L8: 1 | M8: 8100 | N8: 8100 | O8: 9720 | Q8: Apresentações | R8: 12 | S8: 13 | T8: =S8/R8 -> 1.0833333 | W8: 46055 | X8: 130904 | Y8: Junior Lopes | Z8: Tiago eletronicos | AA8: B2B | AB8: CDU | AC8: 1 | AD8: 22270 | AE8: 22270 | AF8: 22270 | AH8: Apresentações | AI8: 12 | AJ8: 15 | AK8: =AJ8/AI8 -> 1.25 | AM8: 46055 | AN8: 128860 | AO8: Paulo Souza | AP8: Sagol | AQ8: Treinamento | AR8: Treinamentos e Implantações | AS8: 110 | AT8: 185 | AU8: 20350 | AV8: 20350 | AY8: Apresentações (12) | AZ8: 12 | BA8: 16 | BB8: =BA8/AZ8 -> 1.3333333 | BD8: 46083 | BE8: 137844 | BF8: Rayssa Karapeticov | BG8: FWB | BH8: Melhoria | BI8: Melhoria | BJ8: 3 | BK8: 176 | BL8: 528 | BM8: 528 | BO8: Apresentações | BP8: 12 | BQ8: 16 | BR8: =BQ8/BP8 -> 1.3333333 | BU8: 46092 | BV8: 139463 | BW8: Junior Lopes | BX8: Clean Tech | BY8: ERP | BZ8: Treinamentos e Implantações | CA8: 340 | CB8: 171 | CC8: 58140 | CD8: 58140 | CF8: Apresentações | CG8: 12 | CH8: 6 | CI8: =CH8/CG8 -> 0.5 | CK8: Data | CL8: Ticket | CM8: Vendedor | CN8: Cliente | CO8: Produto | CP8: TipoReceita | CQ8: Qtde | CR8: VlrUnitário | CS8: VlrTotal | CT8: Vlr Meta | CW8: Apresentações (12) | CX8: 12 | CY8: 13 | CZ8: =CY8/CX8 -> 1.0833333 | DB8: 46119 | DC8: 138780 | DD8: Rayssa Karapeticov | DE8: MTA | DF8: Melhoria | DG8: Melhoria | DH8: 8 | DI8: 176 | DJ8: 1408 | DK8: 1408 | DM8: Apresentações | DN8: 12 | DO8: 7 | DP8: =DO8/DN8 -> 0.58333333 | DS8: 46113 | DT8: 138583 | DU8: Junior Lopes | DV8: Porto Brasil | DW8: AFV | DX8: CDU | DY8: 1 | DZ8: 24000 | EA8: 24000 | EB8: 24000 | ED8: Apresentações | EE8: 12 | EF8: 2 | EG8: =EF8/EE8 -> 0.16666667 | EI8: Data | EJ8: Ticket | EK8: Vendedor | EL8: Cliente | EM8: Produto | EN8: TipoReceita | EO8: Qtde | EP8: VlrUnitário | EQ8: VlrTotal | ER8: Vlr Meta
A9: Meta Individual (6,5k) | B9: 6500 | C9: 2413.68 | D9: =C9/B9 -> 0.37133538 | F9: 46059 | G9: 137739 | H9: Rayssa Karapeticov | I9: Textil Regimara | J9: BI | K9: Mensalidade | L9: 1 | M9: 1080 | N9: 1080 | O9: 1296 | Q9: Meta Individual | R9: 10000 | S9: 14107.5 | T9: =S9/R9 -> 1.41075 | W9: 46055 | X9: 130904 | Y9: Junior Lopes | Z9: Tiago eletronicos | AA9: B2B | AB9: Mensalidade | AC9: 1 | AD9: 3000 | AE9: 3000 | AF9: 3600 | AH9: Meta Individual | AI9: 10000 | AJ9: 55175.35 | AK9: =AJ9/AI9 -> 5.517535 | AM9: 46055 | AN9: 128860 | AO9: Paulo Souza | AP9: Sagol | AQ9: AFV | AR9: Mensalidade | AS9: 15 | AT9: 87 | AU9: 1305 | AV9: 1305 | AY9: Meta Individual (7k) | AZ9: 7000 | BA9: 6425.28 | BB9: =BA9/AZ9 -> 0.91789714 | BD9: 46083 | BE9: 138891 | BF9: Rayssa Karapeticov | BG9: Dasplast | BH9: MDe | BI9: Treinamentos e Implantações | BJ9: 8 | BK9: 210 | BL9: 1680 | BM9: 2016 | BO9: Meta Individual | BP9: 10000 | BQ9: 16288.54 | BR9: =BQ9/BP9 -> 1.628854 | BU9: 46092 | BV9: 139463 | BW9: Junior Lopes | BX9: Clean Tech | BY9: AFV | BZ9: Treinamentos e Implantações | CA9: 60 | CB9: 171 | CC9: 10260 | CD9: 10260 | CF9: Meta Individual | CG9: 10000 | CH9: 301.26 | CI9: =CH9/CG9 -> 0.030126 | CK9: 46092 | CL9: 128860 | CM9: Paulo Souza | CN9: Sagol | CO9: Treinamento | CP9: Treinamentos e Implantações | CQ9: 40 | CR9: 185 | CS9: 7400 | CT9: 7400 | CW9: Meta Individual (7k) | CX9: 7500 | CY9: 2691.36 | CZ9: =CY9/CX9 -> 0.358848 | DB9: 46119 | DC9: 138897 | DD9: Rayssa Karapeticov | DE9: Nixhouse | DF9: Melhoria | DG9: Melhoria | DH9: 64 | DI9: 156.25 | DJ9: 10000 | DK9: 10000 | DM9: Meta Individual | DN9: 10000 | DO9: 5224.65 | DP9: =DO9/DN9 -> 0.522465 | DS9: 46113 | DT9: 138583 | DU9: Junior Lopes | DV9: Porto Brasil | DW9: AFV | DX9: Treinamentos e Implantações | DY9: 100 | DZ9: 212 | EA9: 21200 | EB9: 21200 | ED9: Meta Individual | EE9: 10000 | EF9: 7680.6 | EG9: =EF9/EE9 -> 0.76806 | EI9: 46119 | EJ9: 138641 | EK9: Paulo Souza | EL9: Dinatale | EM9: WMS | EN9: Mensalidade | EO9: 10 | EP9: 142.56 | EQ9: 1425.6 | ER9: 1425.6
A10: Meta Equipe (26,5k) | B10: 26500 | C10: =C9+S9+AJ9 -> 71696.53 | D10: =C10/B10 -> 2.7055294 | F10: 46059 | G10: 137720 | H10: Rayssa Karapeticov | I10: Shock Import | J10: AFV | K10: Mensalidade | L10: 5 | M10: 115 | N10: 575 | O10: 690 | Q10: Meta Equipe | R10: 26500 | S10: =C10 -> 71696.53 | T10: =S10/R10 -> 2.7055294 | W10: 46059 | X10: 137190 | Y10: Junior Lopes | Z10: Conthey | AA10: ERP | AB10: Treinamentos e Implantações | AC10: 290 | AD10: 200 | AE10: 58000 | AF10: 58000 | AH10: Meta Equipe | AI10: 26500 | AJ10: =C10 -> 71696.53 | AK10: =AJ10/AI10 -> 2.7055294 | AM10: 46055 | AN10: 128860 | AO10: Paulo Souza | AP10: Sagol | AQ10: AFV Preposto | AR10: Mensalidade | AS10: 10 | AT10: 43.5 | AU10: 435 | AV10: 435 | AY10: Meta Equipe (26,5k) | AZ10: 27000 | BA10: =BA9+BQ9+CH9 -> 23015.08 | BB10: =BA10/AZ10 -> 0.85241037 | BD10: 46083 | BE10: 138891 | BF10: Rayssa Karapeticov | BG10: Dasplast | BH10: MDe | BI10: Mensalidade | BJ10: 1 | BK10: 356.4 | BL10: 356.4 | BM10: 427.68 | BO10: Meta Equipe | BP10: 27000 | BQ10: =BA10 -> 23015.08 | BR10: =BQ10/BP10 -> 0.85241037 | BU10: 46092 | BV10: 139463 | BW10: Junior Lopes | BX10: Clean Tech | BY10: WMS | BZ10: Treinamentos e Implantações | CA10: 48 | CB10: 171 | CC10: 0 | CD10: 0 | CF10: Meta Equipe | CG10: 27000 | CH10: =BA10 -> 23015.08 | CI10: =CH10/CG10 -> 0.85241037 | CK10: 46100 | CL10: 140072 | CM10: Paulo Souza | CN10: Rafinha Alimentos | CO10: Cloud Upgrade | CP10: Mensalidade | CQ10: 1 | CR10: 301.26 | CS10: 301.26 | CT10: 301.26 | CW10: Meta Equipe (26,5k) | CX10: 27500 | CY10: =CY9+DO9+EF9 -> 15596.61 | CZ10: =CY10/CX10 -> 0.56714945 | DB10: 46119 | DC10: 140964 | DD10: Rayssa Karapeticov | DE10: Rio Home | DF10: Znia | DG10: Treinamentos e Implantações | DH10: 16 | DI10: 210 | DJ10: 3360 | DK10: 4032 | DM10: Meta Equipe | DN10: 27000 | DO10: =CY10 -> 15596.61 | DP10: =DO10/DN10 -> 0.57765222 | DS10: 46113 | DT10: 138583 | DU10: Junior Lopes | DV10: Porto Brasil | DW10: AFV | DX10: Mensalidade | DY10: 61 | DZ10: 85.65 | EA10: 5224.65 | EB10: 5224.65 | ED10: Meta Equipe | EE10: 27000 | EF10: =CY10 -> 15596.61 | EG10: =EF10/EE10 -> 0.57765222 | EI10: 46120 | EJ10: 138614 | EK10: Paulo Souza | EL10: Dinatale | EM10: addon Loja B2B | EN10: Mensalidade | EO10: 60 | EP10: 19.25 | EQ10: 1155 | ER10: 1155
A11: Meta Projetos (90k) | B11: 90000 | C11: 96796.8 | D11: =C11/B11 -> 1.07552 | F11: 46059 | G11: 137481 | H11: Rayssa Karapeticov | I11: Kascao | J11: Treinamento | K11: Treinamentos e Implantações | L11: 8 | M11: 189 | N11: 1512 | O11: 1814.4 | Q11: Meta Projetos | R11: 90000 | S11: 97230 | T11: =S11/R11 -> 1.0803333 | W11: 46059 | X11: 137370 | Y11: Junior Lopes | Z11: Conthey | AA11: ERP | AB11: Mensalidade | AC11: 20 | AD11: 255 | AE11: 5100 | AF11: 5100 | AH11: Meta Projetos | AI11: 90000 | AJ11: 367161.6 | AK11: =AJ11/AI11 -> 4.0795733 | AM11: 46065 | AN11: 128860 | AO11: Paulo Souza | AP11: Sagol | AQ11: Envio Boleto Whatsapp | AR11: Mensalidade | AS11: 1 | AT11: 356.4 | AU11: 356.4 | AV11: 427.68 | AY11: Meta Projetos (90k) | AZ11: 90000 | BA11: 72913.14 | BB11: =BA11/AZ11 -> 0.810146 | BD11: 46092 | BE11: 134510 | BF11: Rayssa Karapeticov | BG11: Gyn | BH11: Treinamento | BI11: Treinamentos e Implantações | BJ11: 14 | BK11: 178.5 | BL11: 2499 | BM11: 2998.8 | BO11: Meta Projetos | BP11: 90000 | BQ11: 99854.09 | BR11: =BQ11/BP11 -> 1.1094899 | BU11: 46092 | BV11: 139465 | BW11: Junior Lopes | BX11: Clean Tech | BY11: Cloud | BZ11: Mensalidade | CA11: 1 | CB11: 3844.54 | CC11: 3844.54 | CD11: 3844.54 | CF11: Meta Projetos | CG11: 90000 | CH11: 7400 | CI11: =CH11/CG11 -> 0.082222222 | CK11: Total | CS11: 7701.26 | CT11: 7701.26 | CW11: Meta Projetos (90k) | CX11: 90000 | CY11: 55648 | CZ11: =CY11/CX11 -> 0.61831111 | DB11: 46119 | DC11: 140964 | DD11: Rayssa Karapeticov | DE11: Rio Home | DF11: Znia | DG11: Mensalidade | DH11: 1 | DI11: 712.8 | DJ11: 712.8 | DK11: 855.36 | DM11: Meta Projetos | DN11: 90000 | DO11: 45200 | DP11: =DO11/DN11 -> 0.50222222 | DS11: Total | EA11: =SUM(EA8:EA10) -> 50424.65 | EB11: =SUM(EB8:EB10) -> 50424.65 | ED11: Meta Projetos | EE11: 90000 | EF11: 38800.64 | EG11: =EF11/EE11 -> 0.43111822 | EI11: 46126 | EJ11: 125596 | EK11: Paulo Souza | EL11: Agua Sana | EM11: Treinamento | EN11: Treinamentos e Implantações | EO11: 43 | EP11: 169.78 | EQ11: 7300.54 | ER11: 7300.54
A12: Total Projetos (270k) | B12: =90000*3 -> 270000 | C12: =C11+S11+AJ11 -> 561188.4 | D12: =C12/B12 -> 2.0784756 | F12: 46066 | G12: 138101 | H12: Rayssa Karapeticov | I12: Univendas | J12: Treinamento | K12: Treinamentos e Implantações | L12: 24 | M12: 125 | N12: 3000 | O12: 3600 | Q12: Total Projetos (270k) | R12: =90000*3 -> 270000 | S12: =C12 -> 561188.4 | T12: =S12/R12 -> 2.0784756 | W12: 46059 | X12: 137370 | Y12: Junior Lopes | Z12: Conthey | AA12: AFV | AB12: Mensalidade | AC12: 20 | AD12: 90 | AE12: 1800 | AF12: 1800 | AH12: Total Projetos (270k) | AI12: =90000*3 -> 270000 | AJ12: =C12 -> 561188.4 | AK12: =AJ12/AI12 -> 2.0784756 | AM12: 46078 | AN12: 138540 ..138541 | AO12: Paulo Souza | AP12: Iracema | AQ12: ERP | AR12: Treinamentos e Implantações | AS12: 316 | AT12: 200 | AU12: 63200 | AV12: 63200 | AY12: Total Projetos (270k) | AZ12: =90000*3 -> 270000 | BA12: =BA11+BQ11+CH11 -> 180167.23 | BB12: =BA12/AZ12 -> 0.66728604 | BD12: 46092 | BE12: 139165 | BF12: Rayssa Karapeticov | BG12: Millenium | BH12: CNPJ | BI12: CDU | BJ12: 1 | BK12: 7472.2 | BL12: 7472.2 | BM12: 8966.64 | BO12: Total Projetos (270k) | BP12: =90000*3 -> 270000 | BQ12: =BA12 -> 180167.23 | BR12: =BQ12/BP12 -> 0.66728604 | BU12: 46092 | BV12: 139463 | BW12: Junior Lopes | BX12: Clean Tech | BY12: ERP | BZ12: Mensalidade | CA12: 15 + 5 | CB12: 285.62 | CC12: 4284.3 | CD12: 4284.3 | CF12: Total Projetos (270k) | CG12: =90000*3 -> 270000 | CH12: =BA12 -> 180167.23 | CI12: =CH12/CG12 -> 0.66728604 | CW12: Total Projetos (270k) | CX12: =90000*3 -> 270000 | CY12: =CY11+DO11+EF11 -> 139648.64 | CZ12: =CY12/CX12 -> 0.51721719 | DB12: 46120 | DC12: 140153 | DD12: Rayssa Karapeticov | DE12: Aliança | DF12: Melhoria | DG12: Melhoria | DH12: 48 | DI12: 176 | DJ12: 8448 | DK12: 8448 | DM12: Total Projetos (270k) | DN12: =90000*3 -> 270000 | DO12: =CY12 -> 139648.64 | DP12: =DO12/DN12 -> 0.51721719 | ED12: Total Projetos (270k) | EE12: =90000*3 -> 270000 | EF12: =CY12 -> 139648.64 | EG12: =EF12/EE12 -> 0.51721719 | EI12: 46140 | EJ12: 142146 | EK12: Paulo Souza | EL12: Dinatale | EM12: B2B | EN12: CDU | EO12: 1 | EP12: 10500 | EQ12: 10500 | ER12: 10500
A13: =IF(C9<6500,"NÃO CUMPRIU A META INDIVIDUAL","CUMPRIU A META INDIVIDUAL") -> NÃO CUMPRIU A META INDIVIDUAL | F13: 46070 | G13: 135881...65 | H13: Rayssa Karapeticov | I13: Inga | J13: Melhoria | K13: Melhoria | L13: 236 | M13: 176 | N13: 41536 | O13: 41536 | Q13: =IF(S9<6500,"NÃO CUMPRIU A META INDIVIDUAL","CUMPRIU A META INDIVIDUAL") -> CUMPRIU A META INDIVIDUAL | W13: 46059 | X13: 137370 | Y13: Junior Lopes | Z13: Conthey | AA13: MDE | AB13: Mensalidade | AC13: 1 | AD13: 330 | AE13: 330 | AF13: 330 | AH13: =IF(AJ10<6500,"NÃO CUMPRIU A META INDIVIDUAL","CUMPRIU A META INDIVIDUAL") -> CUMPRIU A META INDIVIDUAL | AM13: 46078 | AN13: 138540 ..138541 | AO13: Paulo Souza | AP13: Iracema | AQ13: ERP | AR13: CDU | AS13: 1 | AT13: 35502.9 | AU13: 35502.9 | AV13: 35502.9 | AY13: =IF(BA9<7000,"NÃO CUMPRIU A META INDIVIDUAL","CUMPRIU A META INDIVIDUAL") -> NÃO CUMPRIU A META INDIVIDUAL | BD13: 46092 | BE13: 138115 | BF13: Rayssa Karapeticov | BG13: Brl Alimentos | BH13: Melhoria | BI13: Melhoria | BJ13: 6 | BK13: 176 | BL13: 1056 | BM13: 1056 | BO13: =IF(BQ9<10000,"NÃO CUMPRIU A META INDIVIDUAL","CUMPRIU A META INDIVIDUAL") -> CUMPRIU A META INDIVIDUAL | BU13: 46092 | BV13: 139463 | BW13: Junior Lopes | BX13: Clean Tech | BY13: WMS | BZ13: Mensalidade | CA13: 15 + 5 | CB13: 148 | CC13: 2220 | CD13: 2220 | CF13: =IF(CH9<10000,"NÃO CUMPRIU A META INDIVIDUAL","CUMPRIU A META INDIVIDUAL") -> NÃO CUMPRIU A META INDIVIDUAL | CW13: =IF(CY9<7000,"NÃO CUMPRIU A META INDIVIDUAL","CUMPRIU A META INDIVIDUAL") -> NÃO CUMPRIU A META INDIVIDUAL | DB13: 46126 | DC13: 141238 | DD13: Rayssa Karapeticov | DE13: Culturama | DF13: B2B | DG13: Mensalidade | DH13: 1 | DI13: 1530 | DJ13: 1530 | DK13: 1836 | DM13: =IF(DO9<10000,"NÃO CUMPRIU A META INDIVIDUAL","CUMPRIU A META INDIVIDUAL") -> NÃO CUMPRIU A META INDIVIDUAL | ED13: =IF(EF9<10000,"NÃO CUMPRIU A META INDIVIDUAL","CUMPRIU A META INDIVIDUAL") -> NÃO CUMPRIU A META INDIVIDUAL | EI13: 46140 | EJ13: 142146 | EK13: Paulo Souza | EL13: Dinatale | EM13: B2B | EN13: Mensalidade | EO13: 1 | EP13: 1700 | EQ13: 1700 | ER13: 1700
A14: =IF(C10<26500,"NÃO CUMPRIU A META EQUIPE","CUMPRIU A META EQUIPE") -> CUMPRIU A META EQUIPE | F14: 46072 | G14: 135372 | H14: Rayssa Karapeticov | I14: Sagol | J14: Melhoria | K14: Melhoria | L14: 24 | M14: 176 | N14: 4224 | O14: 4224 | Q14: =IF(S10<26500,"NÃO CUMPRIU A META EQUIPE","CUMPRIU A META EQUIPE") -> CUMPRIU A META EQUIPE | W14: 46065 | X14: 138938 | Y14: Junior Lopes | Z14: Orbhes Colchoes | AA14: AFV | AB14: Treinamentos e Implantações | AC14: 80 | AD14: 212 | AE14: 16960 | AF14: 16960 | AH14: =IF(AJ11<26500,"NÃO CUMPRIU A META EQUIPE","CUMPRIU A META EQUIPE") -> CUMPRIU A META EQUIPE | AM14: 46078 | AN14: 138540 ..138541 | AO14: Paulo Souza | AP14: Iracema | AQ14: ERP | AR14: Mensalidade | AS14: 15 | AT14: 275.62 | AU14: 4134.3 | AV14: 4134.3 | AY14: =IF(BA10<27000,"NÃO CUMPRIU A META EQUIPE","CUMPRIU A META EQUIPE") -> NÃO CUMPRIU A META EQUIPE | BD14: 46092 | BE14: 137749 | BF14: Rayssa Karapeticov | BG14: Flora nectar | BH14: Melhoria | BI14: Melhoria | BJ14: 20 | BK14: 176 | BL14: 3520 | BM14: 3520 | BO14: =IF(BQ10<26500,"NÃO CUMPRIU A META EQUIPE","CUMPRIU A META EQUIPE") -> NÃO CUMPRIU A META EQUIPE | BU14: 46092 | BV14: 139463 | BW14: Junior Lopes | BX14: Clean Tech | BY14: MDe | BZ14: Mensalidade | CA14: 1 | CB14: 356.4 | CC14: 356.4 | CD14: 356.4 | CF14: =IF(CH11<26500,"NÃO CUMPRIU A META EQUIPE","CUMPRIU A META EQUIPE") -> NÃO CUMPRIU A META EQUIPE | CW14: =IF(CY10<27000,"NÃO CUMPRIU A META EQUIPE","CUMPRIU A META EQUIPE") -> NÃO CUMPRIU A META EQUIPE | DB14: 46126 | DC14: 141238 | DD14: Rayssa Karapeticov | DE14: Culturama | DF14: B2B | DG14: CDU | DH14: 1 | DI14: 10480 | DJ14: 10480 | DK14: 12576 | DM14: =IF(DO10<26500,"NÃO CUMPRIU A META EQUIPE","CUMPRIU A META EQUIPE") -> NÃO CUMPRIU A META EQUIPE | ED14: =IF(EF10<26500,"NÃO CUMPRIU A META EQUIPE","CUMPRIU A META EQUIPE") -> NÃO CUMPRIU A META EQUIPE | EI14: 46140 | EJ14: 142325 | EK14: Paulo Souza | EL14: Iracema | EM14: B2B | EN14: CDU | EO14: 1 | EP14: 10500 | EQ14: 10500 | ER14: 10500
F15: 46076 | G15: 138313 | H15: Rayssa Karapeticov | I15: Universal Quimica | J15: CNPJ | K15: CDU | L15: 1 | M15: 3150.4 | N15: 3150.4 | O15: 3780.48 | W15: 46065 | X15: 138938 | Y15: Junior Lopes | Z15: Orbhes Colchoes | AA15: AFV | AB15: Mensalidade | AC15: 30 | AD15: 109.25 | AE15: 3277.5 | AF15: 3277.5 | AM15: 46078 | AN15: 138540 ..138541 | AO15: Paulo Souza | AP15: Iracema | AQ15: AFV | AR15: Mensalidade | AS15: 40 | AT15: 115 | AU15: 4600 | AV15: 4600 | BD15: 46092 | BE15: 137612...137592 | BF15: Rayssa Karapeticov | BG15: Inga | BH15: Melhoria | BI15: Melhoria | BJ15: 56 | BK15: 176 | BL15: 9856 | BM15: 9856 | BU15: 46092 | BV15: 139463 | BW15: Junior Lopes | BX15: Clean Tech | BY15: AFV | BZ15: Mensalidade | CA15: 40 +5 | CB15: 115 | CC15: 4600 | CD15: 4600 | DB15: 46131 | DC15: 140455 | DD15: Rayssa Karapeticov | DE15: Pupi | DF15: Melhoria | DG15: Melhoria | DH15: 1 | DI15: 1056 | DJ15: 1056 | DK15: 1056 | EI15: 46140 | EJ15: 142325 | EK15: Paulo Souza | EL15: Iracema | EM15: B2B | EN15: Mensalidade | EO15: 1 | EP15: 1700 | EQ15: 1700 | ER15: 1700
F16: 46076 | G16: 138313 | H16: Rayssa Karapeticov | I16: Universal Quimica | J16: Treinamento | K16: Treinamentos e Implantações | L16: 40 | M16: 146.24 | N16: 5849.6 | O16: 7019.52 | W16: Total | AE16: 110737.5 | AF16: 111337.5 | AM16: 46078 | AN16: 138540 ..138541 | AO16: Paulo Souza | AP16: Iracema | AQ16: MDE | AR16: Mensalidade | AS16: 1 | AT16: 356.4 | AU16: 356.4 | AV16: 356.4 | BD16: 46092 | BE16: 137391 | BF16: Rayssa Karapeticov | BG16: MTA | BH16: Melhoria | BI16: Melhoria | BJ16: 2 | BK16: 176 | BL16: 352 | BM16: 352 | BU16: 46094 | BV16: 116031 | BW16: Junior Lopes | BX16: Preciza | BY16: Treinamento | BZ16: Treinamentos e Implantações | CA16: 101.75 | CB16: 162.45 | CC16: 16529.287 | CD16: 16529.287 | DB16: 46136 | DC16: 141764 | DD16: Rayssa Karapeticov | DE16: NDI | DF16: Melhoria | DG16: Melhoria | DH16: 2 | DI16: 176 | DJ16: 352 | DK16: 352 | EI16: 46140 | EJ16: 142326 | EK16: Paulo Souza | EL16: Mc Flores | EM16: B2B | EN16: CDU | EO16: 1 | EP16: 10500 | EQ16: 10500 | ER16: 10500
F17: 46078 | G17: 136629 | H17: Rayssa Karapeticov | I17: Fu Xing | J17: Melhoria | K17: Melhoria | L17: 80 | M17: 150 | N17: 12000 | O17: 12000 | AM17: 46078 | AN17: 138540 ..138541 | AO17: Paulo Souza | AP17: Iracema | AQ17: BI | AR17: Mensalidade | AS17: 1 | AT17: 1080 | AU17: 1080 | AV17: 1080 | BD17: 46093 | BE17: 137729 | BF17: Rayssa Karapeticov | BG17: Paramount | BH17: Melhoria | BI17: Melhoria | BJ17: 48 | BK17: 176 | BL17: 8448 | BM17: 8448 | BU17: 46104 | BV17: 140133 | BW17: Junior Lopes | BX17: Plasberg | BY17: AFV | BZ17: Treinamentos e Implantações | CA17: 80 | CB17: 186.56 | CC17: 14924.8 | CD17: 14924.8 | DB17: 46140 | DC17: 140910 | DD17: Rayssa Karapeticov | DE17: Aço Mix | DF17: Melhoria | DG17: Melhoria | DH17: 8 | DI17: 176 | DJ17: 1408 | DK17: 1408 | EI17: 46140 | EJ17: 142326 | EK17: Paulo Souza | EL17: Mc Flores | EM17: B2B | EN17: Mensalidade | EO17: 1 | EP17: 1700 | EQ17: 1700 | ER17: 1700
F18: 46078 | G18: 138487 | H18: Rayssa Karapeticov | I18: AD & AD | J18: Envio Boleto Whatsapp | K18: Treinamentos e Implantações | L18: 2 | M18: 210 | N18: 420 | O18: 504 | AM18: 46078 | AN18: 138540 ..138541 | AO18: Paulo Souza | AP18: Iracema | AQ18: WMS | AR18: Mensalidade | AS18: 5 | AT18: 142.53 | AU18: 712.65 | AV18: 712.65 | BD18: 46093 | BE18: 138126 | BF18: Rayssa Karapeticov | BG18: Nixhouse | BH18: Melhoria | BI18: Melhoria | BJ18: 8 | BK18: 176 | BL18: 1408 | BM18: 1408 | BU18: 46104 | BV18: 140133 | BW18: Junior Lopes | BX18: Plasberg | BY18: AFV | BZ18: Mensalidade | CA18: 10 | CB18: 98.33 | CC18: 983.3 | CD18: 983.3 | DB18: 46140 | DC18: 141508 | DD18: Rayssa Karapeticov | DE18: Culturama | DF18: Melhoria | DG18: Melhoria | DH18: 3 | DI18: 176 | DJ18: 528 | DK18: 528 | EQ18: =SUM(EQ9:EQ17) -> 46481.14 | ER18: =SUM(ER9:ER17) -> 46481.14
A19: PROPOSTA | F19: 46078 | G19: 138487 | H19: Rayssa Karapeticov | I19: AD & AD | J19: Envio Boleto Whatsapp | K19: Mensalidade | L19: 1 | M19: 356.4 | N19: 356.4 | O19: 427.68 | Q19: PROPOSTA | AH19: PROPOSTA | AM19: 46078 | AN19: 138540 ..138541 | AO19: Paulo Souza | AP19: Iracema | AQ19: Contabil | AR19: Mensalidade | AS19: 1 | AT19: 689 | AU19: 689 | AV19: 689 | AY19: PROPOSTA | BD19: 46099 | BE19: 139762 | BF19: Rayssa Karapeticov | BG19: Brasimpex | BH19: Melhoria | BI19: Melhoria | BJ19: 3 | BK19: 176 | BL19: 528 | BM19: 528 | BO19: PROPOSTA | BU19: Total | CC19: 116142.63 | CD19: 116142.63 | CF19: PROPOSTA | CW19: PROPOSTA | DB19: 46140 | DC19: 140836 | DD19: Rayssa Karapeticov | DE19: Dinatale | DF19: Melhoria | DG19: Melhoria | DH19: 52 | DI19: 176 | DJ19: 9152 | DK19: 9152 | DM19: PROPOSTA | ED19: PROPOSTA
A20: Título | B20: Data | C20: Qtde | F20: 46078 | G20: 138723 | H20: Rayssa Karapeticov | I20: Inga | J20: Treinamento | K20: Treinamentos e Implantações | L20: 40 | M20: 210 | N20: 8400 | O20: 10080 | Q20: Título | R20: Data | S20: Qtde | AH20: Título | AI20: Data | AJ20: Qtde | AM20: 46078 | AN20: 138540 ..138541 | AO20: Paulo Souza | AP20: Iracema | AQ20: Rd Station | AR20: Mensalidade | AS20: 1 | AT20: 712 | AU20: 712 | AV20: 712 | AY20: Título | AZ20: Qtde | BD20: 46099 | BE20: 137720 | BF20: Rayssa Karapeticov | BG20: Shock Import | BH20: Treinamento | BI20: Treinamentos e Implantações | BJ20: 10 | BK20: 210 | BL20: 2100 | BM20: 2100 | BO20: Título | BP20: Qtde | CF20: Título | CG20: Qtde | CW20: Título | CX20: Qtde | DB20: 46140 | DC20: 138986 | DD20: Rayssa Karapeticov | DE20: Dcarte | DF20: Melhoria | DG20: Melhoria | DH20: 12 | DI20: 176 | DJ20: 2112 | DK20: 2112 | DM20: Título | DN20: Qtde | ED20: Título | EE20: Qtde
A21: rg distribuidora de bebidas ltda | B21: 25/02/2026 | C21: 1 | F21: 46078 | G21: 134770 | H21: Rayssa Karapeticov | I21: Dcarte | J21: Melhoria | K21: Melhoria | L21: 4 | M21: 176 | N21: 704 | O21: 704 | Q21: colorunhas | R21: 05/02/2026 | S21: 1 | AH21: futuro brasil | AI21: 06/02/2026 | AJ21: 1 | AM21: 46078 | AN21: 138575..138580 | AO21: Paulo Souza | AP21: Casart | AQ21: ERP | AR21: Treinamentos e Implantações | AS21: 196 | AT21: 200 | AU21: 39200 | AV21: 39200 | AY21: purai souvenirs ltda | AZ21: 1 | BD21: 46099 | BE21: 139891 | BF21: Rayssa Karapeticov | BG21: Genex | BH21: Cloud | BI21: CDU | BJ21: 1 | BK21: 1600 | BL21: 1600 | BM21: 1920 | BO21: goal comercial ltda | BP21: 2 | CF21: metal adm | CG21: 1 | CW21: ags administracao de bens sociedade unipessoal ltda | CX21: 1 | DB21: 46140 | DC21: 130958 | DD21: Rayssa Karapeticov | DE21: Rischioto | DF21: Melhoria | DG21: Melhoria | DH21: 20 | DI21: 176 | DJ21: 3520 | DK21: 3520 | DM21: simas | DN21: 1 | ED21: kopermax | EE21: 1
A22: micromax industria e comercio ltda | B22: 23/02/2026 | C22: 1 | F22: 46078 | G22: 138211 | H22: Rayssa Karapeticov | I22: Millenium | J22: Treinamento | K22: Treinamentos e Implantações | L22: 8 | M22: 189 | N22: 1512 | O22: 1814.4 | Q22: encartelados nina - erp | R22: 20/02/2026 | S22: 1 | AH22: russa 7 berg distribuidora | AI22: 27/02/2026 | AJ22: 1 | AM22: 46078 | AN22: 138575..138580 | AO22: Paulo Souza | AP22: Casart | AQ22: ERP | AR22: CDU | AS22: 1 | AT22: 35502.9 | AU22: 35502.9 | AV22: 35502.9 | AY22: on import ltda | AZ22: 1 | BD22: 46099 | BE22: 139891 | BF22: Rayssa Karapeticov | BG22: Genex | BH22: Cloud | BI22: Mensalidade | BJ22: 1 | BK22: 3442.8 | BL22: 3442.8 | BM22: 4131.36 | BO22: plastianna | BP22: 1 | CF22: kopermax | CG22: 1 | CW22: ns iguacu eletronicos ltda | CX22: 1 | DB22: 46140 | DC22: 139375 | DD22: Rayssa Karapeticov | DE22: Kascão | DF22: Melhoria | DG22: Melhoria | DH22: 6 | DI22: 176 | DJ22: 1056 | DK22: 1056 | DM22: logrosoft comercio erp | DN22: 1 | ED22: hober artefatos plasticos ltda | EE22: 1
A23: home brands - erp - afv | B23: 20/02/2026 00:00 | C23: 1 | F23: Total | N23: 92419.4 | O23: 99210.48 | Q23: ad & ad (comex) | R23: 11/02/2026 | S23: 1 | AH23: ramfisa participacoes | AI23: 13/02/2026 | AJ23: 1 | AM23: 46078 | AN23: 138575..138580 | AO23: Paulo Souza | AP23: Casart | AQ23: ERP | AR23: Mensalidade | AS23: 12 | AT23: 275.62 | AU23: 3307.44 | AV23: 3307.44 | AY23: matrix brinquedos | AZ23: 1 | BD23: 46100 | BE23: 136464 | BF23: Rayssa Karapeticov | BG23: FWB | BH23: Melhoria | BI23: Melhoria | BJ23: 8 | BK23: 176 | BL23: 1408 | BM23: 1408 | BO23: plug lar u.d. | BP23: 1 | CF23: union rebite | CG23: 1 | CW23: sqcomercio | CX23: 1 | DB23: Total | DJ23: =SUM(DJ8:DJ22) -> 55122.8 | DK23: =SUM(DK8:DK22) -> 58339.36 | DM23: logro soft | DN23: 1 | EE23: =SUM(EE21:EE26)
A24: home brands - afv | B24: 20/02/2026 00:00 | C24: 1 | Q24: ck hospitalar | R24: 23/02/2026 | S24: 1 | AH24: dinatale import ltda | AI24: 06/02/2026 | AJ24: 1 | AM24: 46078 | AN24: 138575..138580 | AO24: Paulo Souza | AP24: Casart | AQ24: AFV | AR24: Mensalidade | AS24: 40 | AT24: 115 | AU24: 4600 | AV24: 4600 | AY24: verti flores e plantas permanentes | AZ24: 1 | BD24: 46100 | BE24: 137380 | BF24: Rayssa Karapeticov | BG24: Millenium | BH24: Melhoria | BI24: Melhoria | BJ24: 16 | BK24: 140.8 | BL24: 2252.8 | BM24: 2252.8 | BO24: vaeso | BP24: 1 | CF24: brl alimentos wms | CG24: 1 | CW24: marcamix (comex) | CX24: 1 | DM24: baag - bi | DN24: 1
A25: FACINATO - Comex | B25: 12/02/2026 | C25: 1 | Q25: atacadão das tripas - erp | R25: 20/02/2026 | S25: 1 | AH25: auto volth | AI25: 02/02/2026 | AJ25: 1 | AM25: 46078 | AN25: 138575..138580 | AO25: Paulo Souza | AP25: Casart | AQ25: BI | AR25: Mensalidade | AS25: 1 | AT25: 1080 | AU25: 1080 | AV25: 1080 | AY25: plus atacadista | AZ25: 1 | BD25: 46100 | BE25: 138380 | BF25: Rayssa Karapeticov | BG25: Parolar | BH25: Melhoria | BI25: Melhoria | BJ25: 16 | BK25: 140.8 | BL25: 2252.8 | BM25: 2252.8 | BO25: fratelli / euroquadros | BP25: 1 | CF25: comercial gaviao | CG25: 1 | CW25: Arcaplast | CX25: 1 | DM25: mdl (horas) | DN25: 1
A26: MARES - WMS | B26: 11/02/2026 | C26: 1 | Q26: startools ferramentas | R26: 11/02/2026 | S26: 1 | AH26: atacado forte vale | AI26: 06/02/2026 | AJ26: 1 | AM26: 46078 | AN26: 138575..138580 | AO26: Paulo Souza | AP26: Casart | AQ26: Contabil | AR26: Mensalidade | AS26: 1 | AT26: 689 | AU26: 689 | AV26: 689 | AY26: auto peças taurus | AZ26: 1 | BD26: 46100 | BE26: 139938 | BF26: Rayssa Karapeticov | BG26: Mares | BH26: Melhoria | BI26: Melhoria | BJ26: 4 | BK26: 176 | BL26: 704 | BM26: 704 | BO26: globalmix - erp | BP26: 1 | CF26: bene tu confeccoes ltda | CG26: 1 | CW26: C.R.I (Gnex) | CX26: 1 | DM26: tecelagem castilho (e-commerce) | DN26: 1
A27: SORVETES KASCAO - compras | B27: 02/02/2026 00:00 | C27: 1 | Q27: clean tech - erp | R27: 11/02/2026 | S27: 1 | AH27: armando nacionais | AI27: 27/02/2026 | AJ27: 1 | AM27: 46078 | AN27: 138575..138580 | AO27: Paulo Souza | AP27: Casart | AQ27: Rd Station | AR27: Mensalidade | AS27: 1 | AT27: 712 | AU27: 712 | AV27: 712 | AY27: ATIVA ATACADO - CNPJ | AZ27: 1 | BD27: 46104 | BE27: 139635 | BF27: Rayssa Karapeticov | BG27: Dute | BH27: Melhoria | BI27: Melhoria | BJ27: 4 | BK27: 176 | BL27: 704 | BM27: 704 | BO27: banana toys - erp | BP27: 1 | CG27: =SUM(CG21:CG26) -> 6 | CW27: RIO HOME - ZNIA | CX27: 1 | DM27: logro soft - comex | DN27: 1
A28: Wellmix - B2B | B28: 02/02/2026 00:00 | C28: 1 | Q28: ama | R28: 25/02/2026 | S28: 1 | AH28: iracema importadora | AI28: 06/02/2026 | AJ28: 1 | AM28: 46078 | AN28: 138641 | AO28: Paulo Souza | AP28: Dinatale | AQ28: ERP | AR28: Treinamentos e Implantações | AS28: 316 | AT28: 200 | AU28: 63200 | AV28: 63200 | AY28: C.R.I (Gnex) | AZ28: 1 | BD28: 46104 | BE28: 138651 | BF28: Rayssa Karapeticov | BG28: Mundi | BH28: Melhoria | BI28: Melhoria | BJ28: 2 | BK28: 176 | BL28: 352 | BM28: 352 | BO28: preciza imports | BP28: 1 | CW28: DAS'PLAST - Comex | CX28: 1 | DN28: =SUM(DN21:DN37)
A29: SHOCK IMPORTS- AFV | B29: 05/02/2026 00:00 | C29: 1 | Q29: vitta estrutural | R29: 25/02/2026 | S29: 1 | AH29: casart importadora | AI29: 06/02/2026 00:00 | AJ29: 1 | AM29: 46078 | AN29: 138641 | AO29: Paulo Souza | AP29: Dinatale | AQ29: ERP | AR29: CDU | AS29: 1 | AT29: 35502.9 | AU29: 35502.9 | AV29: 35502.9 | AY29: FACINATO - BI | AZ29: 1 | BD29: 46105 | BE29: 138954 | BF29: Rayssa Karapeticov | BG29: Mundi | BH29: Melhoria | BI29: Melhoria | BJ29: 36 | BK29: 176 | BL29: 6336 | BM29: 6336 | BO29: globalmix - cloud | BP29: 1 | CW29: Fwb - Comex | CX29: 1
A30: PAROLAR - RD Station | B30: 05/02/2026 00:00 | C30: 1 | Q30: teodoro cosmeticos - erp | R30: 26/02/2026 | S30: 1 | AH30: reobote mult-service | AI30: 27/02/2026 | AJ30: 1 | AM30: 46078 | AN30: 138641 | AO30: Paulo Souza | AP30: Dinatale | AQ30: ERP | AR30: Mensalidade | AS30: 30 | AT30: 275.62 | AU30: 8268.6 | AV30: 8268.6 | AY30: MILLENIUM DISTRIBUIDORA - CNPJ | AZ30: 1 | BD30: 46111 | BE30: 140520 | BF30: Rayssa Karapeticov | BG30: Mokfa | BH30: BI | BI30: Mensalidade | BJ30: 1 | BK30: 1080 | BL30: 1080 | BM30: 1296 | BO30: globalmix - b2b | BP30: 1 | CX30: =SUM(CX21:CX30)
A31: MULTIPRESENTES PRESENTES | B31: 11/02/2026 00:00 | C31: 1 | Q31: teodoro cosméticos - afv | R31: 26/02/2026 | S31: 1 | AH31: agropecuaria agromais | AI31: 27/02/2026 | AJ31: 1 | AM31: 46078 | AN31: 138641 | AO31: Paulo Souza | AP31: Dinatale | AQ31: AFV | AR31: Mensalidade | AS31: 60 | AT31: 105 | AU31: 6300 | AV31: 6300 | AY31: ZEIN IMPORTACAO E COMERCIO LTDA | AZ31: 1 | BD31: 46111 | BE31: 140267 | BF31: Rayssa Karapeticov | BG31: Interponte | BH31: Proposta WEB | BI31: Mensalidade | BJ31: 32 | BK31: 14.85 | BL31: 475.2 | BM31: 570.24 | BO31: banana toys - cloud | BP31: 1
A32: NEDO - RD Stantion | B32: 05/02/2026 00:00 | C32: 1 | Q32: teodoro cosméticos - cloud | R32: 26/02/2026 | S32: 1 | AH32: sucos prats | AI32: 27/02/2026 | AJ32: 1 | AM32: 46078 | AN32: 138641 | AO32: Paulo Souza | AP32: Dinatale | AQ32: MDE | AR32: Mensalidade | AS32: 1 | AT32: 356.4 | AU32: 356.4 | AV32: 356.4 | AY32: SHOCK IMPORTS COMERCIAL LTDA | AZ32: 1 | BD32: 46111 | BE32: 140084 | BF32: Rayssa Karapeticov | BG32: Açomix | BH32: Melhoria | BI32: Melhoria | BJ32: 48 | BK32: 176 | BL32: 8448 | BM32: 8448 | BO32: util ud - pcp / wms | BP32: 1
A33: PAROLAR - CRM RD Stantion | B33: 11/02/2026 | C33: 1 | Q33: encartelados nina - cloud | R33: 20/02/2026 | S33: 1 | AH33: mc flores | AI33: 26/02/2026 | AJ33: 1 | AM33: 46078 | AN33: 138641 | AO33: Paulo Souza | AP33: Dinatale | AQ33: BI | AR33: Mensalidade | AS33: 1 | AT33: 1080 | AU33: 1080 | AV33: 1080 | AY33: MOKFA IMPORT - BI | AZ33: 1 | BD33: 46107 | BE33: 133508 | BF33: Rayssa Karapeticov | BG33: Dute | BH33: Melhoria | BI33: Melhoria | BJ33: 38.4 | BK33: 176 | BL33: 6758.4 | BM33: 6758.4 | BO33: weck - horas | BP33: 1
A34: Universal Quimica - BI | B34: 11/02/2026 00:00 | C34: 1 | Q34: atacadão das tripas - cloud | R34: 19/02/2026 | S34: 1 | AH34: azul importadora | AI34: 27/02/2026 | AJ34: 1 | AM34: 46078 | AN34: 138641 | AO34: Paulo Souza | AP34: Dinatale | AQ34: WMS | AR34: Mensalidade | AS34: 5 | AT34: 142.56 | AU34: 712.8 | AV34: 712.8 | AY34: SULTEX - B2B | AZ34: 1 | BD34: Total | BL34: 75617.6 | BM34: 79338.72 | BO34: casabella claudio teixeira - erp | BP34: 1
A35: Universal Quimica | B35: 09/02/2026 00:00 | C35: 1 | Q35: clean tech - comex | R35: 11/02/2026 | S35: 1 | AH35: kopermax | AI35: 27/02/2026 | AJ35: 1 | AM35: 46078 | AN35: 138641 | AO35: Paulo Souza | AP35: Dinatale | AQ35: Contabil | AR35: Mensalidade | AS35: 1 | AT35: 689 | AU35: 689 | AV35: 689 | AY35: RUVOLO - Comex | AZ35: 1 | BO35: casabella claudio teixeira - cloud | BP35: 1
A36: Universal Quimica - Cloud | B36: 11/02/2026 00:00 | C36: 1 | Q36: startools - comex | R36: 11/02/2026 | S36: 1 | AJ36: =SUM(AJ21:AJ35) -> 15 | AM36: 46078 | AN36: 138641 | AO36: Paulo Souza | AP36: Dinatale | AQ36: Rd Station | AR36: Mensalidade | AS36: 1 | AT36: 712 | AU36: 712 | AV36: 712 | AY36: Arqplast - Md-e | AZ36: 1 | BO36: baag - cloud | BP36: 1
A37: DUTE - B2B | B37: 16/02/2026 00:00 | C37: 1 | S37: =SUM(S21:S36) -> 16 | AM37: 46078 | AN37: 138643 | AO37: Paulo Souza | AP37: MC Flore | AQ37: ERP | AR37: Treinamentos e Implantações | AS37: 196 | AT37: 200 | AU37: 39200 | AV37: 39200 | AY37: Dislar - Treinamento de Custos | AZ37: 1 | BO37: baag - televendas | BP37: 1
A38: MILLENIUM DISTRIBUIDORA | B38: 17/02/2026 00:00 | C38: 1 | AM38: 46078 | AN38: 138643 | AO38: Paulo Souza | AP38: MC Flore | AQ38: ERP | AR38: CDU | AS38: 1 | AT38: 35502.9 | AU38: 35502.9 | AV38: 35502.9 | AY38: INGA - Contábil | AZ38: 1 | BP38: =SUM(BP21:BP37) -> 18
A39: SORVETES KASCAO - Cloud | B39: 12/02/2026 00:00 | C39: 1 | AM39: 46078 | AN39: 138643 | AO39: Paulo Souza | AP39: MC Flore | AQ39: ERP | AR39: Mensalidade | AS39: 14 | AT39: 275.62 | AU39: 3858.68 | AV39: 3858.68 | AY39: Interponte - Proposta WEB | AZ39: 1
A40: INGA - Reciclagem | B40: 17/02/2026 00:00 | C40: 1 | AM40: 46078 | AN40: 138643 | AO40: Paulo Souza | AP40: MC Flore | AQ40: AFV | AR40: Mensalidade | AS40: 48 | AT40: 115 | AU40: 5520 | AV40: 5520 | AY40: NIX HOUSE - Rd Station | AZ40: 1
A41: Ingá - redimensionamento de picking | B41: 17/02/2026 00:00 | C41: 1 | AM41: 46078 | AN41: 138643 | AO41: Paulo Souza | AP41: MC Flore | AQ41: MDe | AR41: Mensalidade | AS41: 1 | AT41: 356.4 | AU41: 356.4 | AV41: 356.4 | AY41: CULTURAMA - B2B | AZ41: 1
A42: QUALITY HOUSE - BI | B42: 18/02/2026 00:00 | C42: 1 | AM42: 46078 | AN42: 138643 | AO42: Paulo Souza | AP42: MC Flore | AQ42: BI | AR42: Mensalidade | AS42: 1 | AT42: 1080 | AU42: 1080 | AV42: 1080 | AZ42: =SUM(AZ21:AZ41) -> 21
A43: Precisa Import - Power BI | B43: 20/02/2026 | C43: 1 | AM43: 46078 | AN43: 138643 | AO43: Paulo Souza | AP43: MC Flore | AQ43: Contabil | AR43: Mensalidade | AS43: 1 | AT43: 689 | AU43: 689 | AV43: 689
A44: AD & AD COMERCIO DE IMPORTACAO E EXPORTACAO LTDA | B44: 20/02/2026 00:00 | C44: 1 | AM44: 46078 | AN44: 138643 | AO44: Paulo Souza | AP44: MC Flore | AQ44: Rd Station | AR44: Mensalidade | AS44: 1 | AT44: 712 | AU44: 712 | AV44: 712
A45: Embalavi - Tray | B45: 20/02/2026 00:00 | C45: 1 | AM45: Total | AU45: 422265.67 | AV45: 422336.95
A46: DAS'PLAST - Mde | B46: 26/02/2026 00:00 | C46: 1
C47: =SUM(C21:C46) -> 26

Sheet FU - Vendas2026-fev
A1: Data | B1: Ticket | C1: Vendedor | D1: Cliente | E1: Produto | F1: TipoReceita | G1: Qtde | H1: VlrUnitário | I1: VlrTotal | J1: Vlr Meta | K1: %Comissão | L1: %ComissãoSupervisor | M1: Base | N1: ComissãoVendedor | O1: ComissãoSupervisor | P1: Clicksign | Q1: Contrato_Termo Aditivo | R1: Obs | S1: Parcelas | T1: Contrato | U1: SDR_RESPONSÁVEL
A2: 46055 | B2: 130904 | C2: Junior Lopes | D2: Tiago eletronicos | E2: B2B | F2: CDU | G2: 1 | H2: 22270 | I2: 22270 | J2: 22270 | K2: 0.07 | L2: 0.0175 | M2: Não | N2: 1558.9 | O2: 389.725 | P2: Feito | Q2: Feito | S2: 10 | T2: Assinado | U2: Junior Lopes
A3: 46055 | B3: 130904 | C3: Junior Lopes | D3: Tiago eletronicos | E3: B2B | F3: Mensalidade | G3: 1 | H3: 3000 | I3: 3000 | J3: 3600 | K3: 1 | L3: 0.25 | M3: Não | N3: 3000 | O3: 750 | P3: Feito | Q3: Feito | S3: 1 | T3: Assinado | U3: Junior Lopes
A4: 46055 | B4: 128860 | C4: Paulo Souza | D4: Sagol | E4: Treinamento | F4: Treinamentos e Implantações | G4: 110 | H4: 185 | I4: 20350 | J4: 20350 | K4: 0.07 | L4: 0 | M4: Não | N4: 1424.5 | O4: 0 | P4: Não tem | Q4: não tem | S4: 6 | T4: não tem | U4: Paulo Souza
A5: 46055 | B5: 128860 | C5: Paulo Souza | D5: Sagol | E5: AFV | F5: Mensalidade | G5: 15 | H5: 87 | I5: 1305 | J5: 1305 | K5: 1 | L5: 0 | M5: Não | N5: 1305 | O5: 0 | P5: Não tem | Q5: não tem | S5: 1 | T5: não tem | U5: Paulo Souza
A6: 46055 | B6: 128860 | C6: Paulo Souza | D6: Sagol | E6: AFV Preposto | F6: Mensalidade | G6: 10 | H6: 43.5 | I6: 435 | J6: 435 | K6: 1 | L6: 0 | M6: Não | N6: 435 | O6: 0 | P6: Não tem | Q6: não tem | S6: 1 | T6: não tem | U6: Paulo Souza
A7: 46059 | B7: 137190 | C7: Junior Lopes | D7: Conthey | E7: ERP | F7: Treinamentos e Implantações | G7: 290 | H7: 200 | I7: 58000 | J7: 58000 | K7: 0.05 | L7: 0.0125 | M7: Não | N7: 2900 | O7: 725 | P7: Feito | Q7: Feito | S7: 12 | T7: Assinado | U7: Junior Lopes
A8: 46059 | B8: 137370 | C8: Junior Lopes | D8: Conthey | E8: ERP | F8: Mensalidade | G8: 20 | H8: 255 | I8: 5100 | J8: 5100 | K8: 1 | L8: 0.25 | M8: Não | N8: 5100 | O8: 1275 | P8: Feito | Q8: Feito | S8: 1 | T8: Assinado | U8: Junior Lopes
A9: 46059 | B9: 137370 | C9: Junior Lopes | D9: Conthey | E9: AFV | F9: Mensalidade | G9: 20 | H9: 90 | I9: 1800 | J9: 1800 | K9: 1 | L9: 0.25 | M9: Não | N9: 1800 | O9: 450 | P9: Feito | Q9: Feito | S9: 1 | T9: Assinado | U9: Junior Lopes
A10: 46059 | B10: 137370 | C10: Junior Lopes | D10: Conthey | E10: MDE | F10: Mensalidade | G10: 1 | H10: 330 | I10: 330 | J10: 330 | K10: 1 | L10: 0.25 | M10: Não | N10: 330 | O10: 82.5 | P10: Feito | Q10: Feito | S10: 1 | T10: Assinado | U10: Junior Lopes
A11: 46059 | B11: 137739 | C11: Rayssa Karapeticov | D11: Textil Regimara | E11: BI | F11: CDU | G11: 1 | H11: 8100 | I11: 8100 | J11: 9720 | K11: 0.25 | L11: 0.0625 | M11: Sim | N11: 2025 | O11: 506.25 | P11: Feito | Q11: Feito | S11: 6 | T11: Assinado | U11: Rayssa Karapeticov
A12: 46059 | B12: 137739 | C12: Rayssa Karapeticov | D12: Textil Regimara | E12: BI | F12: Mensalidade | G12: 1 | H12: 1080 | I12: 1080 | J12: 1296 | K12: 1 | L12: 0.25 | M12: Sim | N12: 1080 | O12: 270 | P12: Feito | Q12: Feito | S12: 1 | T12: Assinado | U12: Rayssa Karapeticov
A13: 46059 | B13: 137720 | C13: Rayssa Karapeticov | D13: Shock Import | E13: AFV | F13: Mensalidade | G13: 5 | H13: 115 | I13: 575 | J13: 690 | K13: 1 | L13: 0.25 | M13: Sim | N13: 575 | O13: 143.75 | P13: Feito | Q13: Feito | S13: 1 | T13: Assinado | U13: Rayssa Karapeticov
... A18: 46066 | B18: 138101 | C18: Rayssa Karapeticov | D18: Univendas | E18: Treinamento | F18: Treinamentos e Implantações | G18: 24 | H18: 125 | I18: 3000 | J18: 3600 | K18: 0.21 | L18: 0.0525 | M18: Sim | N18: 630 | O18: 157.5 | P18: Não tem | Q18: não tem | S18: 5 | T18: não tem | U18: Rayssa Karapeticov
A19: 46070 | B19: 135881...65 | C19: Rayssa Karapeticov | D19: Inga | E19: Melhoria | F19: Melhoria | G19: 236 | H19: 176 | I19: 41536 | J19: 41536 | K19: 0.01 | L19: 0.0025 | M19: Sim | N19: 415.36 | O19: 103.84 | P19: Não tem | Q19: não tem | S19: 4 | T19: não tem | U19: Rayssa Karapeticov
A20: 46072 | B20: 135372 | C20: Rayssa Karapeticov | D20: Sagol | E20: Melhoria | F20: Melhoria | G20: 24 | H20: 176 | I20: 4224 | J20: 4224 | K20: 0.01 | L20: 0.0025 | M20: Sim | N20: 42.24 | O20: 10.56 | P20: Não tem | Q20: não tem | S20: 3 | T20: não tem | U20: Rayssa Karapeticov
A21: 46076 | B21: 138313 | C21: Rayssa Karapeticov | D21: Universal Quimica | E21: CNPJ | F21: CDU | G21: 1 | H21: 3150.4 | I21: 3150.4 | J21: 3780.48 | K21: 0.25 | L21: 0.0625 | M21: Sim | N21: 787.6 | O21: 196.9 | P21: Não tem | Q21: não tem | S21: 6 | T21: não tem | U21: Rayssa Karapeticov
A22: 46076 | B22: 138313 | C22: Rayssa Karapeticov | D22: Universal Quimica | E22: Treinamento | F22: Treinamentos e Implantações | G22: 40 | H22: 146.24 | I22: 5849.6 | J22: 7019.52 | K22: 0.25 | L22: 0.0625 | M22: Sim | N22: 1462.4 | O22: 365.6 | P22: Não tem | Q22: não tem | S22: 6 | T22: não tem | U22: Rayssa Karapeticov
A23: 46078 | B23: 138540 ..138541 | C23: Paulo Souza | D23: Iracema | E23: ERP | F23: Treinamentos e Implantações | G23: 316 | H23: 200 | I23: 63200 | J23: 63200 | K23: 0.07 | L23: 0 | M23: Não | N23: 4424 | O23: 0 | P23: Feito | Q23: Feito | S23: 6 | T23: Assinado | U23: Paulo Souza
A24: 46078 | B24: 138540 ..138541 | C24: Paulo Souza | D24: Iracema | E24: ERP | F24: CDU | G24: 1 | H24: 35502.9 | I24: 35502.9 | J24: 35502.9 | K24: 0.25 | L24: 0 | M24: Não | N24: 8875.725 | O24: 0 | P24: Feito | Q24: Feito | S24: 6 | T24: Assinado | U24: Paulo Souza
A25: 46078 | B25: 138540 ..138541 | C25: Paulo Souza | D25: Iracema | E25: ERP | F25: Mensalidade | G25: 15 | H25: 275.62 | I25: 4134.3 | J25: 4134.3 | K25: 1 | L25: 0 | M25: Não | N25: 4134.3 | O25: 0 | P25: Feito | Q25: Feito | S25: 1 | T25: Assinado | U25: Paulo Souza
A26: 46078 | B26: 138540 ..138541 | C26: Paulo Souza | D26: Iracema | E26: AFV | F26: Mensalidade | G26: 40 | H26: 115 | I26: 4600 | J26: 4600 | K26: 1 | L26: 0 | M26: Não | N26: 4600 | O26: 0 | P26: Feito | Q26: Feito | S26: 1 | T26: Assinado | U26: Paulo Souza
A27: 46078 | B27: 138540 ..138541 | C27: Paulo Souza | D27: Iracema | E27: MDE | F27: Mensalidade | G27: 1 | H27: 356.4 | I27: 356.4 | J27: 356.4 | K27: 1 | L27: 0 | M27: Não | N27: 356.4 | O27: 0 | P27: Feito | Q27: Feito | S27: 1 | T27: Assinado | U27: Paulo Souza
A28: 46078 | B28: 138540 ..138541 | C28: Paulo Souza | D28: Iracema | E28: BI | F28: Mensalidade | G28: 1 | H28: 1080 | I28: 1080 | J28: 1080 | K28: 1 | L28: 0 | M28: Não | N28: 1080 | O28: 0 | P28: Feito | Q28: Feito | S28: 1 | T28: Assinado | U28: Paulo Souza
A29: 46078 | B29: 138540 ..138541 | C29: Paulo Souza | D29: Iracema | E29: WMS | F29: Mensalidade | G29: 5 | H29: 142.53 | I29: 712.65 | J29: 712.65 | K29: 1 | L29: 0 | M29: Não | N29: 712.65 | O29: 0 | P29: Feito | Q29: Feito | S29: 1 | T29: Assinado | U29: Paulo Souza
A30: 46078 | B30: 138540 ..138541 | C30: Paulo Souza | D30: Iracema | E30: Contabil | F30: Mensalidade | G30: 1 | H30: 689 | I30: 689 | J30: 689 | K30: 1 | L30: 0 | M30: Não | N30: 689 | O30: 0 | P30: Feito | Q30: Feito | S30: 1 | T30: Assinado | U30: Paulo Souza
A31: 46078 | B31: 138540 ..138541 | C31: Paulo Souza | D31: Iracema | E31: Rd Station | F31: Mensalidade | G31: 1 | H31: 712 | I31: 712 | J31: 712 | K31: 1 | L31: 0 | M31: Não | N31: 712 | O31: 0 | P31: Feito | Q31: Feito | S31: 1 | T31: Assinado | U31: Paulo Souza
A32: 46078 | B32: 138575..138580 | C32: Paulo Souza | D32: Casart | E32: ERP | F32: Treinamentos e Implantações | G32: 196 | H32: 200 | I32: 39200 | J32: 39200 | K32: 0.07 | L32: 0 | M32: Não | N32: 2744 | O32: 0 | P32: Feito | Q32: Feito | S32: 6 | T32: Assinado | U32: Paulo Souza
A33: 46078 | B33: 138575..138580 | C33: Paulo Souza | D33: Casart | E33: ERP | F33: CDU | G33: 1 | H33: 35502.9 | I33: 35502.9 | J33: 35502.9 | K33: 0.25 | L33: 0 | M33: Não | N33: 8875.725 | O33: 0 | P33: Feito | Q33: Feito | S33: 6 | T33: Assinado | U33: Paulo Souza
A34: 46078 | B34: 138575..138580 | C34: Paulo Souza | D34: Casart | E34: ERP | F34: Mensalidade | G34: 12 | H34: 275.62 | I34: 3307.44 | J34: 3307.44 | K34: 1 | L34: 0 | M34: Não | N34: 3307.44 | O34: 0 | P34: Feito | Q34: Feito | S34: 1 | T34: Assinado | U34: Paulo Souza
... A38: 46078 | B38: 138575..138580 | C38: Paulo Souza | D38: Casart | E38: Rd Station | F38: Mensalidade | G38: 1 | H38: 712 | I38: 712 | J38: 712 | K38: 1 | L38: 0 | M38: Não | N38: 712 | O38: 0 | P38: Feito | Q38: Feito | S38: 1 | T38: Assinado | U38: Paulo Souza
A39: 46078 | B39: 138641 | C39: Paulo Souza | D39: Dinatale | E39: ERP | F39: Treinamentos e Implantações | G39: 316 | H39: 200 | I39: 63200 | J39: 63200 | K39: 0.07 | L39: 0 | M39: Não | N39: 4424 | O39: 0 | P39: Feito | Q39: Feito | S39: 6 | T39: Assinado | U39: Paulo Souza
A40: 46078 | B40: 138641 | C40: Paulo Souza | D40: Dinatale | E40: ERP | F40: CDU | G40: 1 | H40: 35502.9 | I40: 35502.9 | J40: 35502.9 | K40: 0.25 | L40: 0 | M40: Não | N40: 8875.725 | O40: 0 | P40: Feito | Q40: Feito | S40: 6 | T40: Assinado | U40: Paulo Souza
A41: 46078 | B41: 138641 | C41: Paulo Souza | D41: Dinatale | E41: ERP | F41: Mensalidade | G41: 30 | H41: 275.62 | I41: 8268.6 | J41: 8268.6 | K41: 1 | L41: 0 | M41: Não | N41: 8268.6 | O41: 0 | P41: Feito | Q41: Feito | S41: 1 | T41: Assinado | U41: Paulo Souza
A42: 46078 | B42: 138641 | C42: Paulo Souza | D42: Dinatale | E42: AFV | F42: Mensalidade | G42: 60 | H42: 105 | I42: 6300 | J42: 6300 | K42: 1 | L42: 0 | M42: Não | N42: 6300 | O42: 0 | P42: Feito | Q42: Feito | S42: 1 | T42: Assinado | U42: Paulo Souza
A43: 46078 | B43: 138641 | C43: Paulo Souza | D43: Dinatale | E43: MDE | F43: Mensalidade | G43: 1 | H43: 356.4 | I43: 356.4 | J43: 356.4 | K43: 1 | L43: 0 | M43: Não | N43: 356.4 | O43: 0 | P43: Feito | Q43: Feito | S43: 1 | T43: Assinado | U43: Paulo Souza
A44: 46078 | B44: 138641 | C44: Paulo Souza | D44: Dinatale | E44: BI | F44: Mensalidade | G44: 1 | H44: 1080 | I44: 1080 | J44: 1080 | K44: 1 | L44: 0 | M44: Não | N44: 1080 | O44: 0 | P44: Feito | Q44: Feito | S44: 1 | T44: Assinado | U44: Paulo Souza
A45: 46078 | B45: 138641 | C45: Paulo Souza | D45: Dinatale | E45: WMS | F45: Mensalidade | G45: 5 | H45: 142.56 | I45: 712.8 | J45: 712.8 | K45: 1 | L45: 0 | M45: Não | N45: 712.8 | O45: 0 | P45: Feito | Q45: Feito | S45: 1 | T45: Assinado | U45: Paulo Souza
A46: 46078 | B46: 138641 | C46: Paulo Souza | D46: Dinatale | E46: Contabil | F46: Mensalidade | G46: 1 | H46: 689 | I46: 689 | J46: 689 | K46: 1 | L46: 0 | M46: Não | N46: 689 | O46: 0 | P46: Feito | Q46: Feito | S46: 1 | T46: Assinado | U46: Paulo Souza
A47: 46078 | B47: 138641 | C47: Paulo Souza | D47: Dinatale | E47: Rd Station | F47: Mensalidade | G47: 1 | H47: 712 | I47: 712 | J47: 712 | K47: 1 | L47: 0 | M47: Não | N47: 712 | O47: 0 | P47: Feito | Q47: Feito | S47: 1 | T47: Assinado | U47: Paulo Souza
A48: 46078 | B48: 138643 | C48: Paulo Souza | D48: MC Flore | E48: ERP | F48: Treinamentos e Implantações | G48: 196 | H48: 200 | I48: 39200 | J48: 39200 | K48: 0.07 | L48: 0 | M48: Não | N48: 2744 | O48: 0 | P48: Feito | Q48: Feito | S48: 6 | T48: Assinado | U48: Paulo Souza
A49: 46078 | B49: 138643 | C49: Paulo Souza | D49: MC Flore | E49: ERP | F49: CDU | G49: 1 | H49: 35502.9 | I49: 35502.9 | J49: 35502.9 | K49: 0.25 | L49: 0 | M49: Não | N49: 8875.725 | O49: 0 | P49: Feito | Q49: Feito | S49: 6 | T49: Assinado | U49: Paulo Souza
A50: 46078 | B50: 138643 | C50: Paulo Souza | D50: MC Flore | E50: ERP | F50: Mensalidade | G50: 14 | H50: 275.62 | I50: 3858.68 | J50: 3858.68 | K50: 1 | L50: 0 | M50: Não | N50: 3858.68 | O50: 0 | P50: Feito | Q50: Feito | S50: 1 | T50: Assinado | U50: Paulo Souza
... A61: 46078 | B61: 138211 | C61: Rayssa Karapeticov | D61: Millenium | E61: Treinamento | F61: Treinamentos e Implantações | G61: 8 | H61: 189 | I61: 1512 | J61: 1814.4 | K61: 0.25 | L61: 0.0625 | M61: Sim | N61: 378 | O61: 94.5 | P61: Não tem | Q61: não tem | S61: 1 | T61: não tem | U61: Rayssa Karapeticov
A62: Total | I62: =SUBTOTAL(109,Tabela11[VlrTotal]) -> 625422.57 | J62: =SUBTOTAL(109,Tabela11[Vlr Meta]) -> 632884.93 | N62: =SUBTOTAL(109,Tabela11[[ComissãoVendedor ]]) -> 135598.15 | O62: =SUBTOTAL(109,Tabela11[ComissãoSupervisor]) -> 7286.97 | U62: =SUBTOTAL(103,Tabela11[SDR_RESPONSÁVEL]) -> 60
C65: FECHAMENTO DE: 01/02/2026 até 28/02/2026
C66: COBERTURA DE METAS
C67: RAYSSA | G67: JUNIOR | K67: PAULO
D68: Meta | E68: Realizado | F68: Cobertura | H68: Meta | I68: Realizado | J68: Cobertura | L68: Meta | M68: Realizado | N68: Cobertura
C69: Proposta | D69: 15 | E69: 26 | F69: =E69/D69 -> 1.7333333 | G69: Proposta | H69: 15 | I69: 16 | J69: =I69/H69 -> 1.0666667 | K69: Proposta | L69: 15 | M69: 17 | N69: =M69/L69 -> 1.1333333
C70: Apresentações | D70: 12 | E70: 31 | F70: =E70/D70 -> 2.5833333 | G70: Apresentações | H70: 12 | I70: 13 | J70: =I70/H70 -> 1.0833333 | K70: Apresentações | L70: 12 | M70: 15 | N70: =M70/L70 -> 1.25
C71: Meta Individual | D71: 6500 | E71: 2413.68 | F71: =E71/D71 -> 0.37133538 | G71: Meta Individual | H71: 10000 | I71: 14107.5 | J71: =I71/H71 -> 1.41075 | K71: Meta Individual | L71: 10000 | M71: 55175.35 | N71: =M71/L71 -> 5.517535
C72: Meta Equipe | D72: 26500 | E72: =E71+I71+M71 -> 71696.53 | F72: =E72/D72 -> 2.7055294 | G72: Meta Equipe | H72: 26500 | I72: =E72 -> 71696.53 | J72: =I72/H72 -> 2.7055294 | K72: Meta Equipe | L72: 26500 | M72: =E72 -> 71696.53 | N72: =M72/L72 -> 2.7055294
C73: Meta Projetos | D73: 90000 | E73: 96796.8 | F73: =E73/D73 -> 1.07552 | G73: Meta Projetos | H73: 90000 | I73: 97230 | J73: =I73/H73 -> 1.0803333 | K73: Meta Projetos | L73: 90000 | M73: 367161.6 | N73: =M73/L73 -> 4.0795733
C75: REFERÊNCIAS
E78: Bônus ou Ônus se cobrir Meta Recorrente
F79: Percentual | G79: Hora | H79: Mensalidade
E80: Cobriu Meta + | F80: 0.1 | G80: 0.007 | H80: 0.1
E81: Cobriu Meta Equipe + | F81: 0.1 | G81: 0.007 | H81: 0.1
E82: Não Cobriu Meta - | F82: 0.1 | G82: 0.007 | H82: 0.1
C84: COMISSÃO
D86: JÚNIOR | E86: VALOR VENDIDO | F86: COMISSÃO | G86: BÔNUS META | H86: ÔNUS META | I86: META RECORRENTE | J86: META EQUIPE | K86: % COLABORAÇÃO META | L86: BÔNUS TIME
D87: Horas | E87: 97230 | F87: 5646.1 | G87: =F87*0.1 -> 564.61 | H87: 0 | I87: =IF(J71<100%,"NÃO BATEU","CUMPRIU") -> CUMPRIU | J87: =IF(J72<100%,"NÃO BATEU","CUMPRIU") -> CUMPRIU | K87: =E87/E106 -> 0.17525247 | L87: =G106*K87 -> 1138.7061
D88: Mensalidade | E88: 13507.5 | F88: 13507.5 | G88: =F88*0.1 -> 1350.75 | H88: 0 | K88: =IFERROR(E88/E107,0) -> 0.19126213 | L88: =G107*K88 -> 1350.75
E89: =SUM(E87:E88) -> 110737.5 | F89: =F87+F88 -> 19153.6 | G89: =SUM(G87:G88) -> 1915.36 | H89: =SUM(H87:H88)*-1 -> 0 | L89: =SUM(L87:L88) -> 2489.4561 | M89: =G89+H89+L89 -> 4404.8161
D91: RAYSSA | E91: VALOR VENDIDO | F91: COMISSÃO | G91: BÔNUS META | H91: ÔNUS META | I91: META RECORRENTE | J91: META EQUIPE | K91: % COLABORAÇÃO META | L91: BÔNUS TIME
D92: Horas | E92: 31944 | F92: 7518.24 | G92: 0 | H92: =F92*0.1 -> 751.824 | I92: =IF(F71<100%,"NÃO BATEU","CUMPRIU") -> NÃO BATEU | J92: =IF(F72<100%,"NÃO BATEU","CUMPRIU") -> CUMPRIU | K92: =E92/E106 -> 0.057577547 | L92: =K92*G106 -> 374.11115
D93: Mensalidade | E93: 2011.4 | F93: 2011.4 | G93: 0 | H93: =F93*0.1 -> 201.14 | K93: =E93/E107 -> 0.028480819 | L93: =K93*G107 -> 201.14
D94: Melhoria | E94: 58464 | F94: 547.44 | G94: 0 | H94: =F94*0.1 -> 54.744 | K94: =E94/E106 -> 0.10537859 | L94: =K94*G106 -> 684.69929
E95: =SUM(E92:E94) -> 92419.4 | F95: =SUM(F92:F94) -> 10077.08 | G95: =SUM(G92:G94) -> 0 | H95: =SUM(H92:H94)*-1 -> -1007.708 | L95: =SUM(L92:L94) -> 1259.9504 | M95: =G95+H95+L95 -> 252.24244
D97: PAULO | E97: VALOR VENDIDO | F97: COMISSÃO | G97: BÔNUS META | H97: ÔNUS META | I97: META RECORRENTE | J97: META EQUIPE | K97: % COLABORAÇÃO META | L97: BÔNUS TIME | M97: BÔNUS/ÔNUS META | N97: COMISSÃO SUPERVISOR
D98: Horas | E98: 367161.6 | F98: 51263.4 | G98: =F98*0.1 -> 5126.34 | H98: 0 | I98: =IF(N71<100%,"NÃO BATEU","CUMPRIU") -> CUMPRIU | J98: =IF(N72<100%,"NÃO BATEU","CUMPRIU") -> CUMPRIU | K98: =E98/E106 -> 0.66179139 | L98: =K98*G106 -> 4300.0015 | M98: =G89*0.1 -> 191.536 | N98: 3291.09
D99: Mensalidade | E99: 55104.07 | F99: 55104.07 | G99: =F99*0.1 -> 5510.407 | H99: 0 | K99: =E99/E107 -> 0.78025705 | L99: =K99*G107 -> 5510.407 | M99: =H95*0.25 -> -251.927 | N99: 3879.73
D100: Melhoria | E100: 0 | F100: 0 | G100: =F100*0.1 -> 0 | H100: 0 | K100: =E100/E106 -> 0 | L100: =K100*G106 -> 0 | M100: =K100*G106 -> 0 | N100: 116.16
E101: =SUM(E98:E100) -> 422265.67 | F101: =SUM(F98:F100) -> 106367.47 | G101: =SUM(G98:G100) -> 10636.747 | H101: =SUM(H98:H100)*-1 -> 0 | L101: =SUM(L98:L100) -> 9810.4085 | M101: =SUM(M98:M100) -> -60.391 | N101: =SUM(N98:N100) -> 7286.98
N102: =G101+H101+N101+M101+L101 -> 27673.744
G103: BÔNUS DO
F104: TOTAIS | G104: TIME
D105: TOTAIS | E105: =E89+E95+E101 -> 625422.57 | F105: =F89+F95+F101 -> 135598.15 | G105: =G106+G107 -> 13559.815
D106: HORAS | E106: =E87+E92+E98+E94+E100 -> 554799.6 | F106: =F87+F92+F98+F94+F100 -> 64975.18 | G106: =IF(F107>26500,(F106*0.1),0) -> 6497.518
D107: MENSALIDADE | E107: =E88+E93+E99 -> 70622.97 | F107: =F88+F93+F99 -> 70622.97 | G107: =IF(F107>26500,(F107*0.1),0) -> 7062.297
D109: LANÇAMENTOS ÚNICOS NA FOLHA COMISSÃO
D110: Vendedor | E110: Comissão
D111: Júnior Lopes | E111: =M89 -> 4404.8161
D112: Rayssa Oliveira | E112: =M95 -> 252.24244
D113: Paulo Souza | E113: =N102 -> 27673.744
D115: Pagamento Único
D116: Valor Total Vendido | F116: =E106 -> 554799.6
D117: % Comissão Vendedor + Supervisor | F117: =F106/F116 -> 0.11711468
D119: Recorrente
D120: Valor Total de Mensalidade | F120: =E107 -> 70622.97
D121: % Comissão Vendedor + Supervisor | F121: =(F107+N99)/F120 -> 1.0549358

Sheet FU - Vendas2026-jan
A1: Data | B1: Ticket | C1: Vendedor | D1: Cliente | E1: Produto | F1: TipoReceita | G1: Qtde | H1: VlrUnitário | I1: VlrTotal | J1: %Comissão | K1: %ComissãoSupervisor | L1: Base | M1: ComissãoVendedor | N1: ComissãoSupervisor | O1: Clicksign | P1: Contrato_Termo Aditivo | Q1: Obs | R1: Parcelas | S1: Contrato | T1: SDR_RESPONSÁVEL
A2: 46027 | B2: 133837 | C2: Paulo Souza | D2: PlastCap | E2: Treinamento | F2: Treinamentos e Implantações | G2: 180 | H2: 117 | I2: 17837.1 | J2: 0.07 | K2: 0 | L2: Sim | M2: 1248.597 | N2: 0 | O2: Feito | P2: Feito | R2: 12 | S2: Assinado | T2: Paulo Souza
A3: 46027 | B3: 133837 | C3: Paulo Souza | D3: PlastCap | E3: ERP-PDV | F3: Mensalidade | G3: 3 | H3: 280 | I3: 840 | J3: 1 | K3: 0 | L3: Sim | M3: 840 | N3: 0 | O3: Feito | P3: Feito | R3: 1 | S3: Assinado | T3: Paulo Souza
A4: 46027 | B4: 135649 | C4: Rayssa Karapeticov | D4: MB Plasticos | E4: Treinamento | F4: Treinamentos e Implantações | G4: 60 | H4: 133.33 | I4: 7999.8 | J4: 0.0667 | K4: 0.016675 | L4: Sim | M4: 533.58666 | N4: 133.39667 | O4: Feito | P4: Feito | R4: 3 | S4: Assinado | T4: Rayssa Karapeticov
A5: 46027 | B5: 135649 | C5: Rayssa Karapeticov | D5: MB Plasticos | E5: AFV Proposta WEB | F5: Mensalidade | G5: 78 | H5: 12.65 | I5: 986.7 | J5: 1 | K5: 0.25 | L5: Sim | M5: 986.7 | N5: 246.675 | O5: Feito | P5: Feito | R5: 1 | S5: Assinado | T5: Rayssa Karapeticov
A6: 46034 | B6: 134739 | C6: Rayssa Karapeticov | D6: Dolce Home | E6: Melhoria | F6: Melhoria | G6: 6 | H6: 158.401 | I6: 950.406 | J6: 0.007 | K6: 0.00175 | L6: Sim | M6: 6.652842 | N6: 1.6632105 | O6: Não tem | P6: não tem | R6: 1 | S6: não tem | T6: Rayssa Karapeticov
A7: 46034 | B7: 136315 | C7: Paulo Souza | D7: Akitem | E7: CNPJ | F7: CDU | G7: 1 | H7: 15053.87 | I7: 15053.87 | J7: 0.07 | K7: 0 | L7: Sim | M7: 1053.7709 | N7: 0 | O7: Feito | P7: Feito | R7: 6 | S7: Assinado | T7: Paulo Souza
A8: 46034 | B8: 136315 | C8: Paulo Souza | D8: Akitem | E8: ERP | F8: Mensalidade | G8: 1 | H8: 275.62 | I8: 275.62 | J8: 1 | K8: 0 | L8: Sim | M8: 275.62 | N8: 0 | O8: Feito | P8: Feito | R8: 1 | S8: Assinado | T8: Paulo Souza
A9: 46043 | B9: 132374 | C9: Rayssa Karapeticov | D9: Keita | E9: Treinamento | F9: Treinamentos e Implantações | G9: 94 | H9: 178.5 | I9: 16779 | J9: 0.0667 | K9: 0.016675 | L9: Sim | M9: 1119.1593 | N9: 279.78983 | O9: Não tem | P9: não tem | R9: 10 | S9: Assinado | T9: Rayssa Karapeticov
A10: 46043 | B10: 132678 | C10: Junior Lopes | D10: Amilplast | E10: Treinamento | F10: Treinamentos e Implantações | G10: 270 | H10: 190 | I10: 51300 | J10: 0.07 | K10: 0.0175 | L10: Não | M10: 3591 | N10: 897.75 | O10: Feito | P10: Feito | R10: 10 | S10: Assinado | T10: Junior Lopes
A11: 46043 | B11: 132678 | C11: Junior Lopes | D11: Amilplast | E11: ERP | F11: Mensalidade | G11: 5 | H11: 275.62 | I11: 1378.1 | J11: 1 | K11: 0.25 | L11: Não | M11: 1378.1 | N11: 344.525 | O11: Feito | P11: Feito | R11: 1 | S11: Assinado | T11: Junior Lopes
A12: 46043 | B12: 132678 | C12: Junior Lopes | D12: Amilplast | E12: MDE | F12: Mensalidade | G12: 1 | H12: 356.4 | I12: 356.4 | J12: 1 | K12: 0.25 | L12: Não | M12: 356.4 | N12: 89.1 | O12: Feito | P12: Feito | R12: 1 | S12: Assinado | T12: Junior Lopes
A13: 46043 | B13: 136662 | C13: Rayssa Karapeticov | D13: Nixhouse | E13: Treinamento | F13: Treinamentos e Implantações | G13: 10 | H13: 210 | I13: 2100 | J13: 0.07 | K13: 0.0175 | L13: Sim | M13: 147 | N13: 36.75 | O13: Não tem | P13: não tem | R13: 4 | S13: não tem | T13: Rayssa Karapeticov
A14: 46043 | B14: 136717,136720,136721 | C14: Paulo Souza | D14: NVT Importadora | E14: ERP | F14: Treinamentos e Implantações | G14: 240 | H14: 200 | I14: 48000 | J14: 0.07 | K14: 0 | L14: Não | M14: 3360 | N14: 0 | O14: Feito | P14: Feito | R14: 6 | S14: Assinado | T14: Paulo Souza
A15: 46043 | B15: 136717,136720,136721 | C15: Paulo Souza | D15: NVT Importadora | E15: BI | F15: CDU | G15: 1 | H15: 8100 | I15: 8100 | J15: 0.07 | K15: 0 | L15: Não | M15: 567 | N15: 0 | O15: Feito | P15: Feito | R15: 6 | S15: Assinado | T15: Paulo Souza
A16: 46043 | B16: 136717,136720,136721 | C16: Paulo Souza | D16: NVT Importadora | E16: CLOUD | F16: CDU | G16: 1 | H16: 1600 | I16: 1600 | J16: 0.07 | K16: 0 | L16: Não | M16: 112 | N16: 0 | O16: Feito | P16: Feito | R16: 6 | S16: Assinado | T16: Paulo Souza
A17: 46043 | B17: 136717,136720,136721 | C17: Paulo Souza | D17: NVT Importadora | E17: ERP | F17: Mensalidade | G17: 8 | H17: 250 | I17: 2000 | J17: 1 | K17: 0 | L17: Não | M17: 2000 | N17: 0 | O17: Feito | P17: Feito | R17: 1 | S17: Assinado | T17: Paulo Souza
A18: 46043 | B18: 136717,136720,136721 | C18: Paulo Souza | D18: NVT Importadora | E18: WMS | F18: Mensalidade | G18: 4 | H18: 100 | I18: 400 | J18: 1 | K18: 0 | L18: Não | M18: 400 | N18: 0 | O18: Feito | P18: Feito | R18: 1 | S18: Assinado | T18: Paulo Souza
A19: 46043 | B19: 136717,136720,136721 | C19: Paulo Souza | D19: NVT Importadora | E19: BI | F19: Mensalidade | G19: 1 | H19: 1080 | I19: 1080 | J19: 1 | K19: 0 | L19: Não | M19: 1080 | N19: 0 | O19: Feito | P19: Feito | R19: 1 | S19: Assinado | T19: Paulo Souza
A20: 46043 | B20: 136717,136720,136721 | C20: Paulo Souza | D20: NVT Importadora | E20: AFV | F20: Mensalidade | G20: 30 | H20: 90 | I20: 2700 | J20: 1 | K20: 0 | L20: Não | M20: 2700 | N20: 0 | O20: Feito | P20: Feito | R20: 1 | S20: Assinado | T20: Paulo Souza
A21: 46043 | B21: 136717,136720,136721 | C21: Paulo Souza | D21: NVT Importadora | E21: MDE | F21: Mensalidade | G21: 1 | H21: 356.4 | I21: 356.4 | J21: 1 | K21: 0 | L21: Não | M21: 356.4 | N21: 0 | O21: Feito | P21: Feito | R21: 1 | S21: Assinado | T21: Paulo Souza
A22: 46043 | B22: 136717,136720,136721 | C22: Paulo Souza | D22: NVT Importadora | E22: Envio Boleto Whatsapp | F22: Mensalidade | G22: 1 | H22: 197 | I22: 197 | J22: 1 | K22: 0 | L22: Não | M22: 197 | N22: 0 | O22: Feito | P22: Feito | R22: 1 | S22: Assinado | T22: Paulo Souza
A23: 46043 | B23: 136717,136720,136721 | C23: Paulo Souza | D23: NVT Importadora | E23: CLOUD | F23: Mensalidade | G23: 1 | H23: 2524.72 | I23: 2524.72 | J23: 1 | K23: 0 | L23: Não | M23: 2524.72 | N23: 0 | O23: Feito | P23: Feito | R23: 1 | S23: Assinado | T23: Paulo Souza
A24: 46043 | B24: 114426 | C24: Rayssa Karapeticov | D24: Culturama | E24: Treinamento | F24: Treinamentos e Implantações | G24: 11 | H24: 210 | I24: 2310 | J24: 0.07 | K24: 0.0175 | L24: Sim | M24: 161.7 | N24: 40.425 | O24: Não tem | P24: não tem | R24: 6 | S24: não tem | T24: Rayssa Karapeticov
A25: 46043 | B25: 136856 | C25: Rayssa Karapeticov | D25: Rischiotto | E25: Adicional Intelipost | F25: Treinamentos e Implantações | G25: 16 | H25: 178.5 | I25: 2856 | J25: 0.0667 | K25: 0.016675 | L25: Sim | M25: 190.4952 | N25: 47.6238 | O25: Feito | P25: Feito | R25: 6 | S25: Assinado | T25: Rayssa Karapeticov
A26: 46043 | B26: 136856 | C26: Rayssa Karapeticov | D26: Rischiotto | E26: Adicional Intelipost | F26: Mensalidade | G26: 1 | H26: 641.52 | I26: 641.52 | J26: 1 | K26: 0.25 | L26: Sim | M26: 641.52 | N26: 160.38 | O26: Feito | P26: Feito | R26: 1 | S26: Assinado | T26: Rayssa Karapeticov
A27: 46044 | B27: 134776 | C27: Rayssa Karapeticov | D27: Qualyplast | E27: Melhoria | F27: Melhoria | G27: 8 | H27: 176 | I27: 1408 | J27: 0.01 | K27: 0.0025 | L27: Sim | M27: 14.08 | N27: 3.52 | O27: Não tem | P27: não tem | R27: 3 | S27: não tem | T27: Rayssa Karapeticov
A28: 46044 | B28: 136981 | C28: Rayssa Karapeticov | D28: Dolce Home | E28: CNPJ | F28: CDU | G28: 1 | H28: 2419.18 | I28: 2419.18 | J28: 0.06667 | K28: 0.0166675 | L28: Sim | M28: 161.28673 | N28: 40.321683 | O28: Feito | P28: Feito | R28: 6 | S28: Assinado | T28: Rayssa Karapeticov
A29: 46044 | B29: 136981 | C29: Rayssa Karapeticov | D29: Dolce Home | E29: CNPJ | F29: Treinamentos e Implantações | G29: 16 | H29: 178.68 | I29: 2858.88 | J29: 0.0667 | K29: 0.016675 | L29: Sim | M29: 190.6873 | N29: 47.671824 | O29: Feito | P29: Feito | R29: 6 | S29: Assinado | T29: Rayssa Karapeticov
A30: 46048 | B30: 137055 | C30: Rayssa Karapeticov | D30: GP Inox | E30: BI | F30: CDU | G30: 1 | H30: 8100 | I30: 8100 | J30: 0.07 | K30: 0.0175 | L30: Sim | M30: 567 | N30: 141.75 | O30: Feito | P30: Feito | R30: 6 | S30: Assinado | T30: Rayssa Karapeticov
A31: 46048 | B31: 137055 | C31: Rayssa Karapeticov | D31: GP Inox | E31: BI | F31: Mensalidade | G31: 1 | H31: 1070 | I31: 1070 | J31: 1 | K31: 0.25 | L31: Sim | M31: 1070 | N31: 267.5 | O31: Feito | P31: Feito | R31: 1 | S31: Assinado | T31: Rayssa Karapeticov
A32: 46052 | B32: 137171 | C32: Junior Lopes | D32: RN Porcelanas | E32: ERP | F32: Treinamentos e Implantações | G32: 300 | H32: 166.67 | I32: 50001 | J32: 0.05 | K32: 0.0125 | L32: Não | M32: 2500.05 | N32: 625.0125 | O32: Feito | P32: Feito | R32: 10 | S32: Assinado | T32: Junior Lopes
A33: 46052 | B33: 137171 | C33: Junior Lopes | D33: RN Porcelanas | E33: ERP | F33: Mensalidade | G33: 7 | H33: 240 | I33: 1680 | J33: 1 | K33: 0.25 | L33: Não | M33: 1680 | N33: 420 | O33: Feito | P33: Feito | R33: 1 | S33: Assinado | T33: Junior Lopes
A34: 46052 | B34: 137171 | C34: Junior Lopes | D34: RN Porcelanas | E34: WMS | F34: Mensalidade | G34: 1 | H34: 140 | I34: 140 | J34: 1 | K34: 0.25 | L34: Não | M34: 140 | N34: 35 | O34: Feito | P34: Feito | R34: 1 | S34: Assinado | T34: Junior Lopes
A35: 46052 | B35: 137171 | C35: Junior Lopes | D35: RN Porcelanas | E35: AFV | F35: Mensalidade | G35: 10 | H35: 88 | I35: 880 | J35: 1 | K35: 0.25 | L35: Não | M35: 880 | N35: 220 | O35: Feito | P35: Feito | R35: 1 | S35: Assinado | T35: Junior Lopes
... A39: 46052 | B39: 125596 | C39: Paulo Souza | D39: Agua Sana | E39: Treinamento | F39: Treinamentos e Implantações | G39: 40 | H39: 180 | I39: 7200 | J39: 0.07 | K39: 0 | L39: Sim | M39: 504 | N39: 0 | O39: Não tem | P39: não tem | R39: 6 | S39: não tem | T39: Paulo Souza
A40: Total | I40: =SUBTOTAL(109,Tabela3[VlrTotal]) -> 275185.7 | M40: =SUBTOTAL(109,Tabela3[[ComissãoVendedor ]]) -> 33642.586 | N40: =SUBTOTAL(109,Tabela3[ComissãoSupervisor]) -> 4105.8695 | T40: =SUBTOTAL(103,Tabela3[SDR_RESPONSÁVEL]) -> 38
C42: FECHAMENTO DE: 01/01/2026 até 31/01/2026
C43: COBERTURA DE METAS
C44: RAYSSA | G44: JUNIOR | K44: PAULO
D45: Meta | E45: Realizado | F45: Cobertura | H45: Meta | I45: Realizado | J45: Cobertura | L45: Meta | M45: Realizado | N45: Cobertura
C46: Proposta | D46: 15 | E46: 24 | F46: =E46/D46 -> 1.6 | G46: Proposta | H46: 15 | I46: 16 | J46: =I46/H46 -> 1.0666667 | K46: Proposta | L46: 15 | M46: 10 | N46: =M46/L46 -> 0.66666667
C47: Apresentações | D47: 12 | E47: 16 | F47: =E47/D47 -> 1.3333333 | G47: Apresentações | H47: 12 | I47: 16 | J47: =I47/H47 -> 1.3333333 | K47: Apresentações | L47: 12 | M47: 10 | N47: =M47/L47 -> 0.83333333
C48: Meta Individual | D48: 6000 | E48: =E70 -> 2698.22 | F48: =E48/D48 -> 0.44970333 | G48: Meta Individual | H48: 10000 | I48: =E65 -> 4434.5 | J48: =I48/H48 -> 0.44345 | K48: Meta Individual | L48: 10000 | M48: =E76 -> 10373.74 | N48: =M48/L48 -> 1.037374
C49: Meta Equipe | D49: 26000 | E49: =E48+I48+M48 -> 17506.46 | F49: =E49/D49 -> 0.67332538 | G49: Meta Equipe | H49: 26000 | I49: =E49 -> 17506.46 | J49: =I49/H49 -> 0.67332538 | K49: Meta Equipe | L49: 26000 | M49: =E49 -> 17506.46 | N49: =M49/L49 -> 0.67332538
C50: Meta Projetos | D50: 90000 | E50: =E69+E71 -> 58587.27 | F50: =E50/D50 -> 0.65096967 | G50: Meta Projetos | H50: 90000 | I50: =E64 -> 101301 | J50: =I50/H50 -> 1.1255667 | K50: Meta Projetos | L50: 90000 | M50: =E75 -> 97790.97 | N50: =M50/L50 -> 1.0865663
C52: REFERÊNCIAS
E55: Bônus ou Ônus se cobrir Meta Recorrente
F56: Percentual | G56: Hora | H56: Mensalidade
E57: Cobriu Meta + | F57: 0.1 | G57: 0.007 | H57: 0.1
E58: Cobriu Meta Equipe + | F58: 0.1 | G58: 0.007 | H58: 0.1
E59: Não Cobriu Meta - | F59: 0.1 | G59: 0.007 | H59: 0.1
C61: COMISSÃO
D63: JÚNIOR | E63: VALOR VENDIDO | F63: COMISSÃO | G63: BÔNUS META | H63: ÔNUS META | I63: META RECORRENTE | J63: META EQUIPE | K63: % COLABORAÇÃO META | L63: BÔNUS TIME
D64: Horas | E64: 101301 | F64: 6091.05 | G64: 0 | H64: =F64*0.1 -> 609.105 | I64: =IF(J48<100%,"NÃO BATEU","CUMPRIU") -> NÃO BATEU | J64: =IF(J49<100%,"NÃO BATEU","CUMPRIU") -> NÃO BATEU | K64: =E64/E83 -> 0.39312829 | L64: =G83*K64 -> 0
D65: Mensalidade | E65: 4434.5 | F65: 4434.5 | G65: 0 | H65: =F65*0.1 -> 443.45 | K65: =IFERROR(E65/E84,0) -> 0.25330649 | L65: =G84*K65 -> 0
E66: =SUM(E64:E65) -> 105735.5 | F66: =F64+F65 -> 10525.55 | G66: =SUM(G64:G65) -> 0 | H66: =SUM(H64:H65)*-1 -> -1052.555 | L66: =SUM(L64:L65) -> 0 | M66: =G66+H66+L66 -> -1052.555
D68: RAYSSA | E68: VALOR VENDIDO | F68: COMISSÃO | G68: BÔNUS META | H68: ÔNUS META | I68: META RECORRENTE | J68: META EQUIPE | K68: % COLABORAÇÃO META | L68: BÔNUS TIME
D69: Horas | E69: 52532.86 | F69: 3142.02 | G69: 0 | H69: =F69*0.1 -> 314.202 | I69: =IF(F48<100%,"NÃO BATEU","CUMPRIU") -> NÃO BATEU | J69: =IF(F49<100%,"NÃO BATEU","CUMPRIU") -> NÃO BATEU | K69: =E69/E83 -> 0.2038692 | L69: =K69*G83 -> 0
D70: Mensalidade | E70: 2698.22 | F70: 2698.22 | G70: 0 | H70: =F70*0.1 -> 269.822 | K70: =E70/E84 -> 0.15412711 | L70: =K70*G84 -> 0
D71: Melhoria | E71: 6054.41 | F71: 57.69 | G71: 0 | H71: =F71*0.1 -> 5.769 | K71: =E71/E83 -> 0.023495917 | L71: =K71*G83 -> 0
E72: =SUM(E69:E71) -> 61285.49 | F72: =SUM(F69:F71) -> 5897.93 | G72: =SUM(G69:G71) -> 0 | H72: =SUM(H69:H71)*-1 -> -589.793 | L72: =SUM(L69:L71) -> 0 | M72: =G72+H72+L72 -> -589.793
D74: PAULO | E74: VALOR VENDIDO | F74: COMISSÃO | G74: BÔNUS META | H74: ÔNUS META | I74: META RECORRENTE | J74: META EQUIPE | K74: % COLABORAÇÃO META | L74: BÔNUS TIME | M74: BÔNUS/ÔNUS META | N74: COMISSÃO SUPERVISOR
D75: Horas | E75: 97790.97 | F75: 6845.37 | G75: =F75*0.1 -> 684.537 | H75: 0 | I75: =IF(N48<100%,"NÃO BATEU","CUMPRIU") -> CUMPRIU | J75: =IF(N49<100%,"NÃO BATEU","CUMPRIU") -> NÃO BATEU | K75: =E75/E83 -> 0.37950659 | L75: =K75*G83 -> 0 | M75: =H66*0.25 -> -263.13875 | N75: 2308.27
D76: Mensalidade | E76: 10373.74 | F76: 10373.74 | G76: =F76*0.1 -> 1037.374 | H76: 0 | K76: =E76/E84 -> 0.5925664 | L76: =K76*G84 -> 0 | M76: =H72*0.25 -> -147.44825 | N76: 1783.18
D77: Melhoria | E77: 0 | F77: 0 | G77: =F77*0.1 -> 0 | H77: 0 | K77: =E77/E83 -> 0 | L77: =K77*G83 -> 0 | M77: =K77*G83 -> 0 | N77: 14.42
E78: =SUM(E75:E77) -> 108164.71 | F78: =SUM(F75:F77) -> 17219.11 | G78: =SUM(G75:G77) -> 1721.911 | H78: =SUM(H75:H77)*-1 -> 0 | L78: =SUM(L75:L77) -> 0 | M78: =SUM(M75:M77) -> -410.587 | N78: =SUM(N75:N77) -> 4105.87
N79: =G78+H78+N78+M78+L78 -> 5417.194
G80: BÔNUS DO
F81: TOTAIS | G81: TIME
D82: TOTAIS | E82: =E66+E72+E78 -> 275185.7 | F82: =F66+F72+F78 -> 33642.59 | G82: =G83+G84 -> 0
D83: HORAS | E83: =E64+E69+E75+E71+E77 -> 257679.24 | F83: =F64+F69+F75+F71+F77 -> 16136.13 | G83: =IF(F84>30000,(F83*0.1),0) -> 0
D84: MENSALIDADE | E84: =E65+E70+E76 -> 17506.46 | F84: =F65+F70+F76 -> 17506.46 | G84: =IF(F84>30000,(F84*0.1),0) -> 0
D86: LANÇAMENTOS ÚNICOS NA FOLHA COMISSÃO
D87: Vendedor | E87: Comissão
D88: Júnior Lopes | E88: =M66 -> -1052.555
D89: Rayssa Oliveira | E89: =M72 -> -589.793
D90: Paulo Souza | E90: =N79 -> 5417.194
D92: Pagamento Único
D93: Valor Total Vendido | F93: =E83 -> 257679.24
D94: % Comissão Vendedor + Supervisor | F94: =F83/F93 -> 0.062620993
D96: Recorrente
D97: Valor Total de Mensalidade | F97: =E84 -> 17506.46
D98: % Comissão Vendedor + Supervisor | F98: =(F84+N76)/F97 -> 1.1018584

Sheet AnaliseT1
B2: RECORRENTE 4T DE 2025 | F2: RECEITA GERADA NO 4T DE 2025 | I2: HORAS DO 4T 2025
B3: TipoReceita | C3: Mensalidade | I3: Meses (Data) | J3: TipoReceita | K3: HORAS
I4: out | J4: Melhoria | K4: 415
B5: Meses (Data) | C5: RECORRENTE | F5: Rótulos de Linha | G5: Soma de VlrTotal | J5: Treinamentos | K5: 488
B6: out | C6: 1286.28 | F6: out | G6: 156983.04 | I6: nov | J6: Melhoria | K6: 235
B7: nov | C7: 641.52 | F7: nov | G7: 60195.38 | J7: Treinamentos | K7: 34
B8: dez | C8: 7660.04 | F8: dez | G8: 110046.04 | I8: dez | J8: Melhoria | K8: 72
B9: Total Geral | C9: 9587.84 | F9: Total Geral | G9: 327224.46 | J9: Treinamentos | K9: 244
I10: Total Geral | K10: 1488
F192: FORECAST 1T 2026
B193: RECEITA POR PRODUTO 4T DE 2025
B194: Meses (Data) | C194: Produto | D194: VENDA | F194: Temperatura | G194: (Vários itens) | H194: Escolha aqui a temperatura
B195: out | C195: Cloud | D195: 258.6
C196: CNPJ | D196: 1472.9 | F196: Cliente | G196: Responsável | H196: Produto | I196: Soma de Qtde | J196: _Vlr Projeto | K196: _Mensalidade | L196: _Horas
C197: Magis | D197: 641.61 | F197: Alumínio Nacional | G197: Paulo Souza | H197: TREINAMENTO | I197: 1 | J197: 63200 | K197: 0 | L197: 316
C198: Melhoria | D198: 71280 | F198: Amilplast Ind – ERP | G198: Junior Lopes | H198: ERP | I198: 1 | J198: 51300 | K198: 1734 | L198: 270
C199: Treinamento | D199: 53238.25 | F199: Colorflex – AFV | G199: Rayssa Karapeticov | H199: AFV | I199: 1 | J199: 3360 | K199: 196.42 | L199: 16
C200: WMS | D200: 30091.68 | F200: Conthey – AFV | G200: Junior Lopes | H200: AFV | I200: 1 | J200: 7200 | K200: 1964.2 | L200: 8
B201: nov | C201: CNPJ | D201: 17948.36 | F201: Conthey – Cloud | G201: Junior Lopes | H201: CLOUD | I201: 1 | J201: 1600 | K201: 5242 | L201: 16
C202: MDFe | D202: 356.4 | F202: Conthey – ERP | G202: Junior Lopes | H202: ERP | I202: 1 | J202: 72000 | K202: 4215 | L202: 360
C203: Melhoria | D203: 38347.5 | F203: Erca Alumínio – Imp. XML | G203: Junior Lopes | H203: ADDON IMPORTAÇÃO XML | I203: 1 | J203: 3392 | K203: 356.4 | L203: 16
C204: Treinamento | D204: 3258 | F204: Evolux – ERP · PCP · WMS · AFV | G204: Rayssa Karapeticov | H204: ERP, PCP, WMS, AFV | I204: 1 | J204: 46200 | K204: 1460.47 | L204: 220
C205: WMS | D205: 285.12 | F205: Fafá Import – WMS | G205: Junior Lopes | H205: WMS | I205: 1 | J205: 23584 | K205: 142.56 | L205: 124
B206: dez | C206: B2B | D206: 24800 | F206: Gyn Atacado Ltda – Integrador E-commerce | G206: Rayssa Karapeticov | H206: Hub Ecommerce | I206: 1 | J206: 16200 | K206: 712.8 | L206: 80
C207: CNPJ | D207: 18000 | F207: Imev Proteínas | G207: Paulo Souza | H207: AFV | I207: 1 | J207: 16000 | K207: 5880 | L207: 80
C208: Contábil | D208: 689.04 | F208: Indústria Oyshi | G208: Paulo Souza | H208: AFV | I208: 1 | J208: 16000 | K208: 1558 | L208: 80
C209: ERP | D209: 48054.4 | F209: JP Distribuidora – Agenda Visita | G209: Paulo Souza | H209: ADDON AGENDA | I209: 1 | J209: 0 | K209: 66 | L209: 0
C210: Intelipost | D210: 3461.88 | F210: Marka Têxtil – Cloud | G210: Junior Lopes | H210: CLOUD | I210: 1 | J210: 1600 | K210: 6846 | L210: 16
C211: Melhoria | D211: 4576 | F211: Marka Têxtil – ERP | G211: Junior Lopes | H211: ERP | I211: 1 | J211: 118908 | K211: 13048 | L211: 540
C212: Treinamento | D212: 8754 | F212: MDL Import – Cloud | G212: Junior Lopes | H212: CLOUD | I212: 1 | J212: 1600 | K212: 2568 | L212: 16
C213: WMS | D213: 1710.72 | F213: Olé Alimentos | G213: Paulo Souza | H213: AFV | I213: 1 | J213: 16000 | K213: 18330 | L213: 80
B214: Total Geral | D214: 327224.46 | F214: Parolar – Checkout | G214: Rayssa Karapeticov | H214: Checkout | I214: 1 | J214: 5040 | K214: 1140.48 | L214: 24
F215: Plasbrink Embalagens Plásticas Ltda – Cloud | G215: Junior Lopes | H215: CLOUD | I215: 1 | J215: 1600 | K215: 3356 | L215: 16
F216: Plasbrink Embalagens Plásticas Ltda – ERP | G216: Junior Lopes | H216: ERP | I216: 1 | J216: 81786 | K216: 7965 | L216: 430
F217: Porto Brasil Cerâmica – AFV | G217: Junior Lopes | H217: AFV | I217: 1 | J217: 33920 | K217: 3768 | L217: 160
F218: Preciza Import – Boleto WhatsApp | G218: Junior Lopes | H218: ADDON BOLETO WHATSAPP | I218: 1 | J218: 0 | K218: 356.4 | L218: 0
F219: Sunguider Importador/Distribuidor | G219: Paulo Souza | H219: ERP | I219: 1 | J219: 0 | K219: 0 | L219: 0
F220: Tiago Eletrônicos – B2B | G220: Junior Lopes | H220: B2B | I220: 1 | J220: 26200 | K220: 3000 | L220: 80
F221: Univendas – Cloud | G221: Rayssa Karapeticov | H221: CLOUD | I221: 1 | J221: 1600 | K221: 4718.3 | L221: 8
F222: VIC Import – AFV | G222: Junior Lopes | H222: AFV | I222: 1 | J222: 8000 | K222: 1964 | L222: 40
F223: VIC Import – Cloud | G223: Junior Lopes | H223: CLOUD | I223: 1 | J223: 1600 | K223: 3442 | L223: 16
F224: VIC Import – ERP | G224: Junior Lopes | H224: ERP | I224: 1 | J224: 44000 | K224: 1378 | L224: 220
F225: Total Geral | I225: 28 | J225: 661890 | K225: 95408.03 | L225: 3232

Sheet Resumo de Vendas
B3: VENDAS POR TIPOS DE RECEITA 2025 | G3: VENDAS POR VENDEDOR 2025
B4: Rótulos de Linha | C4: _VlrTotal | D4: _Qtde | G4: Soma de VlrTotal | H4: Rótulos de Coluna
B5: CDU | C5: 285492.63 | D5: 52 | G5: Rótulos de Linha | H5: CDU | I5: Melhoria | J5: Mensalidade | K5: Treinamentos | L5: Total Geral
B6: Melhoria | C6: 326490.61 | D6: 2000 | G6: Junior Lopes | H6: 41390.26 | J6: 106923.91 | K6: 1015377.1 | L6: 1163691.3
B7: Mensalidade | C7: 186664.98 | D7: 1453 | G7: Paulo Souza | H7: 87602.08 | I7: 4576 | J7: 52414.98 | K7: 468044 | L7: 612637.06
B8: Treinamentos | C8: 1965697.6 | D8: 11106.02 | G8: Rayssa Karapeticov | H8: 156500.29 | I8: 321914.61 | J8: 27326.09 | K8: 482276.46 | L8: 988017.45
B9: Total Geral | C9: 2764345.8 | D9: 14611.02 | G9: Total Geral | H9: 285492.63 | I9: 326490.61 | J9: 186664.98 | K9: 1965697.6 | L9: 2764345.8
B512: VENDAS USUÁRIOS 2025 | G512: VENDAS METAS 2026
B513: TipoReceita | C513: Mensalidade | G513: Vendedor | H513: Rayssa Karapeticov
G514: Ano | H514: (Vários itens)
B515: Rótulos de Linha | C515: _Qtde
B516: AFV | C516: 750 | G516: Rótulos de Linha | H516: Cobertura | I516: Objetivo
B517: Addon Propsta WEB | C517: 233 | G517: mai | H517: 0.14790625 | I517: 8
B518: ERP | C518: 212 | G518: abr | H518: 0.358848 | I518: 7.5
B519: Cloud | C519: 88 | G519: mar | H519: 0.91789714 | I519: 7
B520: WMS | C520: 42 | G520: fev | H520: 0.37133538 | I520: 6.5
B521: Addon Iara | C521: 40 | G521: jan | H521: 0.44970333 | I521: 6
B522: MDe | C522: 16 | G522: Total Geral | H522: 2.2456901 | I522: 35
B523: PDV Pre Venda | C523: 15
B524: PDV | C524: 8
B525: Telemarketing | C525: 5
B526: MDFe | C526: 5
B527: PDV ERP | C527: 4
B528: BI | C528: 4
B529: Contábil | C529: 4
B530: Link de Pagamento | C530: 3
B531: Addon Multilojas | C531: 3
B532: AFV Preposto | C532: 2
B533: Intelipost | C533: 2
B534: B2B | C534: 2 | G534: Ano | H534: (Vários itens)
B535: PDV Server | C535: 2 | G535: Vendedor | H535: (Tudo)
B536: CTE | C536: 2
B537: Importação XML | C537: 2 | G537: Rótulos de Linha | H537: Cobertura | I537: Objetivo
B538: CRM RD Station | C538: 1 | G538: jan | H538: 0.67332538 | I538: 78
B539: Envio de Boleto | C539: 1 | G539: fev | H539: 2.7055294 | I539: 79.5
B540: MDFE e CTE | C540: 1 | G540: mar | H540: 0.85241407 | I540: 81
B541: CIAP | C541: 1 | G541: abr | H541: 0.56714945 | I541: 82.5
B542: PCP | C542: 1 | G542: mai | H542: 0.27155794 | I542: 136
B543: Tray | C543: 1 | G543: Total Geral | H543: 5.0699763 | I543: 457
B544: Lexos | C544: 1
B545: Guarani B2B | C545: 1
B546: Routeasy | C546: 1
B547: Total Geral | C547: 1453

Sheet 2025
A1: Data | B1: Ticket | C1: Vendedor | D1: Cliente | E1: Produto | F1: TipoReceita | G1: Qtde | H1: VlrUnitário | I1: VlrTotal | J1: %Comissão | K1: %ComissãoSupervisor | L1: Base | M1: ComissãoVendedor | N1: ComissãoSupervisor | O1: Clicksign | P1: Contrato_Termo Aditivo | Q1: Obs | R1: Parcelas | S1: Contrato | T1: SDR_RESPONSÁVEL
A2: 45663 | B2: 117043 | C2: Junior Lopes | D2: Culturama | E2: Importação XML | F2: Mensalidade | G2: 1 | H2: 356.4 | I2: =G2*H2 -> 356.4 | J2: 1 | K2: =J2*0.25 -> 0.25 | L2: Não | M2: =J2*I2 -> 356.4 | N2: =I2*K2 -> 89.1 | O2: Feito | P2: Feito | R2: 1 | S2: Assinado | T2: Junior Lopes
A3: 45663 | B3: 117002 | C3: Junior Lopes | D3: GB Importadora | E3: ERP | F3: Treinamentos | G3: 224 | H3: 172.88 | I3: =(G3*H3) -> 38725.12 | J3: 0.05 | K3: =J3*0.25 -> 0.0125 | L3: Não | M3: =J3*I3 -> 1936.256 | N3: =I3*K3 -> 484.064 | O3: Feito | P3: Feito | R3: 10 | S3: Assinado | T3: Junior Lopes
A4: 45663 | B4: 117002 | C4: Junior Lopes | D4: GB Importadora | E4: AFV | F4: Treinamentos | G4: 50 | H4: 172.88 | I4: =(G4*H4) -> 8644 | J4: 0.05 | K4: =J4*0.25 -> 0.0125 | L4: Não | M4: =J4*I4 -> 432.2 | N4: =I4*K4 -> 108.05 | O4: Feito | P4: Feito | R4: 10 | S4: Assinado | T4: Junior Lopes
A5: 45663 | B5: 117002 | C5: Junior Lopes | D5: GB Importadora | E5: ERP | F5: Mensalidade | G5: 3 | H5: 275.62 | I5: =(G5*H5) -> 826.86 | J5: 1 | K5: =J5*0.25 -> 0.25 | L5: Não | M5: =J5*I5 -> 826.86 | N5: =I5*K5 -> 206.715 | O5: Feito | P5: Feito | R5: 1 | S5: Assinado | T5: Junior Lopes
A6: 45663 | B6: 117002 | C6: Junior Lopes | D6: GB Importadora | E6: AFV | F6: Mensalidade | G6: 2 | H6: 78.2 | I6: =(G6*H6) -> 156.4 | J6: 1 | K6: =J6*0.25 -> 0.25 | L6: Não | M6: =J6*I6 -> 156.4 | N6: =I6*K6 -> 39.1 | O6: Feito | P6: Feito | R6: 1 | S6: Assinado | T6: Junior Lopes
A7: 45663 | B7: 117007 | C7: Junior Lopes | D7: GB Importadora | E7: Cloud | F7: CDU | G7: 1 | H7: 1600 | I7: =(G7*H7) -> 1600 | J7: 0.07 | K7: =J7*0.25 -> 0.0175 | L7: Não | M7: =J7*I7 -> 112 | N7: =I7*K7 -> 28 | O7: Feito | P7: Feito | R7: 4 | S7: Assinado | T7: Junior Lopes
A8: 45663 | B8: 117007 | C8: Junior Lopes | D8: GB Importadora | E8: Cloud | F8: Mensalidade | G8: 1 | H8: 1324.26 | I8: =(G8*H8) -> 1324.26 | J8: 1 | K8: =J8*0.25 -> 0.25 | L8: Não | M8: =J8*I8 -> 1324.26 | N8: =I8*K8 -> 331.065 | O8: Feito | P8: Feito | R8: 1 | S8: Assinado | T8: Junior Lopes
A9: 45663 | B9: 117007 | C9: Junior Lopes | D9: GB Importadora | E9: Cloud | F9: Mensalidade | G9: 3 | H9: 84 | I9: =(G9*H9) -> 252 | J9: 1 | K9: =J9*0.25 -> 0.25 | L9: Não | M9: =J9*I9 -> 252 | N9: =I9*K9 -> 63 | O9: Feito | P9: Feito | R9: 1 | S9: Assinado | T9: Junior Lopes
A10: 45663 | B10: 110971 | C10: Junior Lopes | D10: Elmo | E10: ERP | F10: Treinamentos | G10: 324 | H10: 180 | I10: =G10*171.02 -> 55410.48 | J10: 0.07 | K10: =J10*0.25 -> 0.0175 | L10: Não | M10: =J10*I10 -> 3878.7336 | N10: =I10*K10 -> 969.6834 | O10: Feito | P10: Feito | R10: 10 | S10: Assinado | T10: Débora Duarte
A11: 45663 | B11: 110971 | C11: Junior Lopes | D11: Elmo | E11: WMS | F11: Treinamentos | G11: 90 | H11: 180 | I11: =G11*171.02 -> 15391.8 | J11: 0.07 | K11: =J11*0.25 -> 0.0175 | L11: Não | M11: =J11*I11 -> 1077.426 | N11: =I11*K11 -> 269.3565 | O11: Feito | P11: Feito | R11: 10 | S11: Assinado | T11: Débora Duarte
A12: 45663 | B12: 110971 | C12: Junior Lopes | D12: Elmo | E12: PDV | F12: Treinamentos | G12: 36 | H12: 180 | I12: =G12*171.02 -> 6156.72 | J12: 0.07 | K12: =J12*0.25 -> 0.0175 | L12: Não | M12: =J12*I12 -> 430.9704 | N12: =I12*K12 -> 107.7426 | O12: Feito | P12: Feito | R12: 10 | S12: Assinado | T12: Débora Duarte
A13: 45663 | B13: 110971 | C13: Junior Lopes | D13: Elmo | E13: ERP | F13: Mensalidade | G13: 11 | H13: 275.62 | I13: =G13*H13 -> 3031.82 | J13: 1 | K13: =J13*0.25 -> 0.25 | L13: Não | M13: =J13*I13 -> 3031.82 | N13: =I13*K13 -> 757.955 | O13: Feito | P13: Feito | R13: 1 | S13: Assinado | T13: Débora Duarte
A14: 45663 | B14: 110971 | C14: Junior Lopes | D14: Elmo | E14: WMS | F14: Mensalidade | G14: 2 | H14: 142.56 | I14: =G14*H14 -> 285.12 | J14: 1 | K14: =J14*0.25 -> 0.25 | L14: Não | M14: =J14*I14 -> 285.12 | N14: =I14*K14 -> 71.28 | O14: Feito | P14: Feito | R14: 1 | S14: Assinado | T14: Débora Duarte
A15: 45663 | B15: 110971 | C15: Junior Lopes | D15: Elmo | E15: PDV ERP | F15: Mensalidade | G15: 3 | H15: 145.8 | I15: =G15*H15 -> 437.4 | J15: 1 | K15: =J15*0.25 -> 0.25 | L15: Não | M15: =J15*I15 -> 437.4 | N15: =I15*K15 -> 109.35 | O15: Feito | P15: Feito | R15: 1 | S15: Assinado | T15: Débora Duarte
A16: 45663 | B16: 110971 | C16: Junior Lopes | D16: Elmo | E16: AFV | F16: Treinamentos | G16: 40 | H16: 180 | I16: =G16*171.02 -> 6840.8 | J16: 0.07 | K16: =J16*0.25 -> 0.0175 | L16: Não | M16: =J16*I16 -> 478.856 | N16: =I16*K16 -> 119.714 | O16: Feito | P16: Feito | R16: 10 | S16: Assinado | T16: Débora Duarte
A17: 45663 | B17: 110971 | C17: Junior Lopes | D17: Elmo | E17: AFV | F17: Mensalidade | G17: 17 | H17: 82.9 | I17: =G17*H17 -> 1409.3 | J17: 1 | K17: =J17*0.25 -> 0.25 | L17: Não | M17: =J17*I17 -> 1409.3 | N17: =I17*K17 -> 352.325 | O17: Feito | P17: Feito | R17: 1 | S17: Assinado | T17: Débora Duarte
A18: 45663 | B18: 116976 | C18: Junior Lopes | D18: Polimax | E18: ERP | F18: Treinamentos | G18: 224 | H18: 171 | I18: =G18*H18 -> 38304 | J18: 0.05 | K18: =J18*0.25 -> 0.0125 | L18: Não | M18: =J18*I18 -> 1915.2 | N18: =I18*K18 -> 478.8 | O18: Feito | P18: Feito | R18: 8 | S18: Assinado | T18: Junior Lopes
A19: 45663 | B19: 116976 | C19: Junior Lopes | D19: Polimax | E19: AFV | F19: Treinamentos | G19: 50 | H19: 171 | I19: =G19*H19 -> 8550 | J19: 0.05 | K19: =J19*0.25 -> 0.0125 | L19: Não | M19: =J19*I19 -> 427.5 | N19: =I19*K19 -> 106.875 | O19: Feito | P19: Feito | R19: 8 | S19: Assinado | T19: Junior Lopes
A20: 45663 | B20: 116976 | C20: Junior Lopes | D20: Polimax | E20: ERP | F20: Mensalidade | G20: 6 | H20: 275.62 | I20: =G20*H20 -> 1653.72 | J20: 1 | K20: =J20*0.25 -> 0.25 | L20: Não | M20: =J20*I20 -> 1653.72 | N20: =I20*K20 -> 413.43 | O20: Feito | P20: Feito | R20: 1 | S20: Assinado | T20: Junior Lopes
A21: 45663 | B21: 116976 | C21: Junior Lopes | D21: Polimax | E21: MDe | F21: Mensalidade | G21: 1 | H21: 356.4 | I21: =G21*H21 -> 356.4 | J21: 1 | K21: =J21*0.25 -> 0.25 | L21: Não | M21: =J21*I21 -> 356.4 | N21: =I21*K21 -> 89.1 | O21: Feito | P21: Feito | R21: 1 | S21: Assinado | T21: Junior Lopes
A22: 45663 | B22: 116976 | C22: Junior Lopes | D22: Polimax | E22: AFV | F22: Mensalidade | G22: 15 | H22: 98.2 | I22: =G22*H22 -> 1473 | J22: 1 | K22: =J22*0.25 -> 0.25 | L22: Não | M22: =J22*I22 -> 1473 | N22: =I22*K22 -> 368.25 | O22: Feito | P22: Feito | R22: 1 | S22: Assinado | T22: Junior Lopes
A23: 45663 | B23: 116739 | C23: Paulo Souza | D23: Terra Boa | E23: Treinamento | F23: Treinamentos | G23: 16 | H23: 187.5 | I23: =G23*H23 -> 3000 | J23: 0.07 | K23: 0 | L23: Sim | M23: =J23*I23 -> 210 | N23: =I23*K23 -> 0 | O23: Não têm | P23: Não têm | R23: 3 | S23: Não têm | T23: Paulo Souza
A24: 45663 | B24: 116549 | C24: Rayssa Karapeticov | D24: Parolar | E24: Treinamento | F24: Treinamentos | G24: 20 | H24: 212 | I24: =G24*H24 -> 4240 | J24: 0.07 | K24: =J24*0.25 -> 0.0175 | L24: Sim | M24: =J24*I24 -> 296.8 | N24: =I24*K24 -> 74.2 | O24: Não têm | P24: Não têm | R24: 6 | S24: Não têm | T24: Rayssa Karapeticov
A25: 45663 | B25: 117278 | C25: Rayssa Karapeticov | D25: Parolimp | E25: Treinamento | F25: Treinamentos | G25: 2 | H25: 212 | I25: =G25*H25 -> 424 | J25: 0.07 | K25: =J25*0.25 -> 0.0175 | L25: Sim | M25: =J25*I25 -> 29.68 | N25: =I25*K25 -> 7.42 | O25: Não têm | P25: Não têm | R25: 1 | S25: Não têm | T25: Rayssa Karapeticov
A26: 45664 | B26: 106541 | C26: Paulo Souza | D26: Paramount | E26: Treinamento | F26: Treinamentos | G26: 44 | H26: 140 | I26: =G26*H26 -> 6160 | J26: 0.035 | K26: 0 | L26: Sim | M26: =J26*I26 -> 215.6 | N26: =I26*K26 -> 0 | O26: Não têm | P26: Não têm | R26: 1 | S26: Não têm | T26: Paulo Souza
A27: 45664 | B27: 115644 | C27: Rayssa Karapeticov | D27: Marilar | E27: Melhoria | F27: Melhoria | G27: 3 | H27: 176 | I27: =G27*H27 -> 528 | J27: 0.01 | K27: =J27*0.25 -> 0.0025 | L27: Sim | M27: =J27*I27 -> 5.28 | N27: =I27*K27 -> 1.32 | O27: Não têm | P27: Não têm | R27: 1 | S27: Não têm | T27: Rayssa Karapeticov
A28: 45664 | B28: 117327/117329 | C28: Paulo Souza | D28: GiftUtil | E28: CNPJ | F28: CDU | G28: 1 | H28: 862.08 | I28: =G28*H28 -> 862.08 | J28: 0.07 | K28: 0 | L28: Sim | M28: =J28*I28 -> 60.3456 | N28: 0 | O28: Não têm | P28: Não têm | R28: 4 | S28: Não têm | T28: Paulo Souza
A29: 45664 | B29: 117327/117329 | C29: Paulo Souza | D29: GiftUtil | E29: Treinamento | F29: Treinamentos | G29: 20 | H29: 200 | I29: =G29*H29 -> 4000 | J29: 0.07 | K29: 0 | L29: Sim | M29: =J29*I29 -> 280 | N29: =I29*K29 -> 0 | O29: Não têm | P29: Não têm | R29: 4 | S29: Não têm | T29: Paulo Souza
A30: 45664 | B30: 117327/117329 | C30: Paulo Souza | D30: GiftUtil | E30: MDE | F30: Mensalidade | G30: 1 | H30: 356.4 | I30: =G30*H30 -> 356.4 | J30: 1 | K30: 0 | L30: Sim | M30: =J30*I30 -> 356.4 | N30: =I30*K30 -> 0 | O30: Não têm | P30: Não têm | R30: 1 | S30: Não têm | T30: Paulo Souza
A31: 45664 | B31: 114449 | C31: Rayssa Karapeticov | D31: Rishioto | E31: Melhoria | F31: Melhoria | G31: 3 | H31: 176 | I31: =G31*H31 -> 528 | J31: 0.01 | K31: =J31*0.25 -> 0.0025 | L31: Sim | M31: =J31*I31 -> 5.28 | N31: =I31*K31 -> 1.32 | O31: Não têm | P31: Não têm | R31: 1 | S31: Não têm | T31: Rayssa Karapeticov
A32: 45664 | B32: 114449 | C32: Rayssa Karapeticov | D32: Marcamix | E32: Treinamento | F32: Treinamentos | G32: 21 | H32: 215 | I32: =G32*H32 -> 4515 | J32: 0.07 | K32: =J32*0.25 -> 0.0175 | L32: Sim | M32: =J32*I32 -> 316.05 | N32: =I32*K32 -> 79.0125 | O32: Não têm | P32: Não têm | R32: 6 | S32: Não têm | T32: Rayssa Karapeticov
A33: 45665 | B33: 116626 | C33: Rayssa Karapeticov | D33: Panamby | E33: Melhoria | F33: Melhoria | G33: 3 | H33: 176 | I33: =G33*H33 -> 528 | J33: 0.01 | K33: =J33*0.25 -> 0.0025 | L33: Sim | M33: =J33*I33 -> 5.28 | N33: =I33*K33 -> 1.32 | O33: Não têm | P33: Não têm | R33: 1 | S33: Não têm | T33: Rayssa Karapeticov
A34: 45666 | B34: 117045 | C34: Rayssa Karapeticov | D34: Scotti | E34: Melhoria | F34: Melhoria | G34: 4 | H34: 149.6 | I34: =G34*H34 -> 598.4 | J34: 0.0069 | K34: =J34*0.25 -> 0.001725 | L34: Sim | M34: =J34*I34 -> 4.12896 | N34: =I34*K34 -> 1.03224 | O34: Não têm | P34: Não têm | R34: 1 | S34: Não têm | T34: Rayssa Karapeticov
A35: 45667 | B35: 108233 | C35: Rayssa Karapeticov | D35: Dvidros | E35: Treinamento | F35: Treinamentos | G35: 3 | H35: 210 | I35: =G35*H35 -> 630 | J35: 0.07 | K35: =J35*0.25 -> 0.0175 | L35: Sim | M35: =J35*I35 -> 44.1 | N35: =I35*K35 -> 11.025 | O35: Não têm | P35: Não têm | R35: 3 | S35: Não têm | T35: Rayssa Karapeticov
A36: 45667 | B36: 117556 | C36: Rayssa Karapeticov | D36: Terra Boa | E36: Treinamento | F36: Treinamentos | G36: 8 | H36: 210 | I36: =G36*H36 -> 1680 | J36: 0.07 | K36: =J36*0.25 -> 0.0175 | L36: Sim | M36: =J36*I36 -> 117.6 | N36: =I36*K36 -> 29.4 | O36: Não têm | P36: Não têm | R36: 6 | S36: Não têm | T36: Rayssa Karapeticov
A37: 45667 | B37: 113593 | C37: Rayssa Karapeticov | D37: Rischioto | E37: Melhoria | F37: Melhoria | G37: 144 | H37: 176 | I37: =G37*H37 -> 25344 | J37: 0.01 | K37: =J37*0.25 -> 0.0025 | L37: Sim | M37: =J37*I37 -> 253.44 | N37: =I37*K37 -> 63.36 | O37: Não têm | P37: Não têm | R37: 5 | S37: Não têm | T37: Rayssa Karapeticov
A38: 45670 | B38: 117550/117553 | C38: Junior Lopes | D38: Star Distribuidora | E38: ERP | F38: Treinamentos | G38: 228 | H38: 171.19 | I38: =G38*H38 -> 39031.32 | J38: 0.05 | K38: =J38*0.25 -> 0.0125 | L38: Não | M38: =J38*I38 -> 1951.566 | N38: =I38*K38 -> 487.8915 | O38: Feito | P38: Feito | R38: 10 | S38: Assinado | T38: Junior Lopes
A39: 45670 | B39: 117550/117553 | C39: Junior Lopes | D39: Star Distribuidora | E39: AFV | F39: Treinamentos | G39: 40 | H39: 171.19 | I39: =G39*H39 -> 6847.6 | J39: 0.05 | K39: =J39*0.25 -> 0.0125 | L39: Não | M39: =J39*I39 -> 342.38 | N39: =I39*K39 -> 85.595 | O39: Feito | P39: Feito | R39: 10 | S39: Assinado | T39: Junior Lopes
A40: 45670 | B40: 117550/117553 | C40: Junior Lopes | D40: Star Distribuidora | E40: Cloud | F40: CDU | G40: 1 | H40: 1600 | I40: =G40*H40 -> 1600 | J40: 0.07 | K40: =J40*0.25 -> 0.0175 | L40: Não | M40: =J40*I40 -> 112 | N40: =I40*K40 -> 28 | O40: Feito | P40: Feito | R40: 10 | S40: Assinado | T40: Junior Lopes
A41: 45670 | B41: 117550/117553 | C41: Junior Lopes | D41: Star Distribuidora | E41: ERP | F41: Mensalidade | G41: 8 | H41: 248.08 | I41: =G41*H41 -> 1984.64 | J41: 1 | K41: =J41*0.25 -> 0.25 | L41: Não | M41: =J41*I41 -> 1984.64 | N41: =I41*K41 -> 496.16 | O41: Feito | P41: Feito | R41: 1 | S41: Assinado | T41: Junior Lopes
A42: 45670 | B42: 117550/117553 | C42: Junior Lopes | D42: Star Distribuidora | E42: MDE | F42: Mensalidade | G42: 1 | H42: 240 | I42: =G42*H42 -> 240 | J42: 1 | K42: =J42*0.25 -> 0.25 | L42: Não | M42: =J42*I42 -> 240 | N42: =I42*K42 -> 60 | O42: Feito | P42: Feito | R42: 1 | S42: Assinado | T42: Junior Lopes
A43: 45670 | B43: 117550/117553 | C43: Junior Lopes | D43: Star Distribuidora | E43: AFV | F43: Mensalidade | G43: 50 | H43: 81.14 | I43: =G43*H43 -> 4057 | J43: 1 | K43: =J43*0.25 -> 0.25 | L43: Não | M43: =J43*I43 -> 4057 | N43: =I43*K43 -> 1014.25 | O43: Feito | P43: Feito | R43: 1 | S43: Assinado | T43: Junior Lopes
A44: 45670 | B44: 117550/117553 | C44: Junior Lopes | D44: Star Distribuidora | E44: Cloud | F44: Mensalidade | G44: 1 | H44: 1628.22 | I44: =G44*H44 -> 1628.22 | J44: 1 | K44: =J44*0.25 -> 0.25 | L44: Não | M44: =J44*I44 -> 1628.22 | N44: =I44*K44 -> 407.055 | O44: Feito | P44: Feito | R44: 1 | S44: Assinado | T44: Junior Lopes
A45: 45670 | B45: 117550/117553 | C45: Junior Lopes | D45: Star Distribuidora | E45: Cloud | F45: Mensalidade | G45: 10 | H45: 80.9 | I45: =G45*H45 -> 809 | J45: 1 | K45: =J45*0.25 -> 0.25 | L45: Não | M45: =J45*I45 -> 809 | N45: =I45*K45 -> 202.25 | O45: Feito | P45: Feito | R45: 1 | S45: Assinado | T45: Junior Lopes
A46: 45671 | B46: 113212 | C46: Rayssa Karapeticov | D46: Full Fit | E46: Melhoria | F46: Melhoria | G46: 12 | H46: 176 | I46: =G46*H46 -> 2112 | J46: 0.01 | K46: =J46*0.25 -> 0.0025 | L46: Sim | M46: =J46*I46 -> 21.12 | N46: =I46*K46 -> 5.28 | O46: Não têm | P46: Não têm | R46: 3 | S46: Não têm | T46: Rayssa Karapeticov
A47: 45672 | B47: 117788 | C47: Rayssa Karapeticov | D47: Bella Vista | E47: Treinamento | F47: Treinamentos | G47: 16 | H47: 210 | I47: =G47*H47 -> 3360 | J47: 0.07 | K47: =J47*0.25 -> 0.0175 | L47: Sim | M47: =J47*I47 -> 235.2 | N47: =I47*K47 -> 58.8 | O47: Não têm | P47: Não têm | R47: 6 | S47: Não têm | T47: Rayssa Karapeticov
A48: 45672 | B48: 117775 | C48: Rayssa Karapeticov | D48: Quality | E48: Treinamento | F48: Treinamentos | G48: 4 | H48: 210 | I48: =G48*H48 -> 840 | J48: 0.07 | K48: =J48*0.25 -> 0.0175 | L48: Sim | M48: =J48*I48 -> 58.8 | N48: =I48*K48 -> 14.7 | O48: Não têm | P48: Não têm | R48: 6 | S48: Não têm | T48: Rayssa Karapeticov
A49: 45672 | B49: 117316 | C49: Rayssa Karapeticov | D49: Mundi | E49: WMS | F49: Mensalidade | G49: 2 | H49: 142.56 | I49: =G49*H49 -> 285.12 | J49: 1 | K49: =J49*0.25 -> 0.25 | L49: Sim | M49: =J49*I49 -> 285.12 | N49: =I49*K49 -> 71.28 | O49: Não têm | P49: Não têm | R49: 1 | S49: Não têm | T49: Rayssa Karapeticov
A50: 45673 | B50: 116965 | C50: Paulo Souza | D50: Newell Brands | E50: Melhoria | F50: Melhoria | G50: 11 | H50: 176 | I50: =G50*H50 -> 1936 | J50: 0.01 | K50: 0 | L50: Sim | M50: =J50*I50 -> 19.36 | N50: =I50*K50 -> 0 | O50: Não têm | P50: Não têm | R50: 3 | S50: Não têm | T50: Paulo Souza
A51: 45674 | B51: 117899 | C51: Rayssa Karapeticov | D51: Lira Distribuidora | E51: Tray | F51: CDU | G51: 1 | H51: 12960 | I51: =G51*H51 -> 12960 | J51: 0.0204 | K51: =J51*0.25 -> 0.0051 | L51: Sim | M51: =J51*I51 -> 264.384 | N51: =I51*K51 -> 66.096 | O51: Feito | P51: Feito | R51: 10 | S51: Assinado | T51: Rayssa Karapeticov
A52: 45674 | B52: 117899 | C52: Rayssa Karapeticov | D52: Mundi | E52: Tray | F52: Mensalidade | G52: 1 | H52: 641.52 | I52: =G52*H52 -> 641.52 | J52: 1 | K52: =J52*0.25 -> 0.25 | L52: Sim | M52: =J52*I52 -> 641.52 | N52: =I52*K52 -> 160.38 | O52: Feito | P52: Feito | R52: 1 | S52: Assinado | T52: Rayssa Karapeticov
A53: 45681 | B53: 118061 | C53: Junior Lopes | D53: Baag | E53: ERP | F53: Treinamentos | G53: 427 | H53: 180.045 | I53: =G53*H53 -> 76879.215 | J53: 0.07 | K53: =J53*0.25 -> 0.0175 | L53: Não | M53: =J53*I53 -> 5381.5451 | N53: =I53*K53 -> 1345.3863 | O53: Feito | P53: Feito | R53: 6 | S53: Assinado | T53: Junior Lopes
A54: 45681 | B54: 118061 | C54: Junior Lopes | D54: Baag | E54: ERP | F54: Mensalidade | G54: 12 | H54: 275.62 | I54: =G54*H54 -> 3307.44 | J54: 1 | K54: =J54*0.25 -> 0.25 | L54: Não | M54: =J54*I54 -> 3307.44 | N54: =I54*K54 -> 826.86 | O54: Feito | P54: Feito | R54: 1 | S54: Assinado | T54: Junior Lopes
A55: 45681 | B55: 118061 | C55: Junior Lopes | D55: Baag | E55: MDe | F55: Mensalidade | G55: 1 | H55: 356.4 | I55: =G55*H55 -> 356.4 | J55: 1 | K55: =J55*0.25 -> 0.25 | L55: Não | M55: =J55*I55 -> 356.4 | N55: =I55*K55 -> 89.1 | O55: Feito | P55: Feito | R55: 1 | S55: Assinado | T55: Junior Lopes
A56: 45681 | B56: 118061 | C56: Junior Lopes | D56: Baag | E56: AFV | F56: Treinamentos | G56: 44 | H56: 180.04 | I56: =G56*H56 -> 7921.76 | J56: 0.07 | K56: =J56*0.25 -> 0.0175 | L56: Não | M56: =J56*I56 -> 554.5232 | N56: =I56*K56 -> 138.6308 | O56: Feito | P56: Feito | R56: 6 | S56: Assinado | T56: Junior Lopes
A57: 45681 | B57: 118061 | C57: Junior Lopes | D57: Baag | E57: AFV | F57: Mensalidade | G57: 30 | H57: 88.2 | I57: =G57*H57 -> 2646 | J57: 1 | K57: =J57*0.25 -> 0.25 | L57: Não | M57: =J57*I57 -> 2646 | N57: =I57*K57 -> 661.5 | O57: Feito | P57: Feito | R57: 1 | S57: Assinado | T57: Junior Lopes
A58: 45681 | B58: 117780 | C58: Rayssa Karapeticov | D58: JP Representação | E58: Melhoria | F58: Melhoria | G58: 7 | H58: 176 | I58: =G58*H58 -> 1232 | J58: 0.01 | K58: =J58*0.25 -> 0.0025 | L58: Sim | M58: =J58*I58 -> 12.32 | N58: =I58*K58 -> 3.08 | O58: Não têm | P58: Não têm | R58: 3 | S58: Não têm | T58: Rayssa Karapeticov
A59: 45681 | B59: 117808 | C59: Rayssa Karapeticov | D59: NDI | E59: Treinamento | F59: Treinamentos | G59: 4 | H59: 178.5 | I59: =G59*H59 -> 714 | J59: 0.0667 | K59: =J59*0.25 -> 0.016675 | L59: Sim | M59: =J59*I59 -> 47.6238 | N59: =I59*K59 -> 11.90595 | O59: Não têm | P59: Não têm | R59: 1 | S59: Não têm | T59: Rayssa Karapeticov
A60: 45685 | B60: 116514 | C60: Rayssa Karapeticov | D60: FWB | E60: Melhoria | F60: Melhoria | G60: 4 | H60: 158.4 | I60: =G60*H60 -> 633.6 | J60: 0.01 | K60: =J60*0.25 -> 0.0025 | L60: Sim | M60: =J60*I60 -> 6.336 | N60: =I60*K60 -> 1.584 | O60: Não têm | P60: Não têm | R60: 3 | S60: Não têm | T60: Rayssa Karapeticov
A61: 45686 | B61: 118426 | C61: Junior Lopes | D61: Polimax | E61: Cloud | F61: CDU | G61: 1 | H61: 1600 | I61: =G61*H61 -> 1600 | J61: 0.07 | K61: =J61*0.25 -> 0.0175 | L61: Não | M61: =J61*I61 -> 112 | N61: =I61*K61 -> 28 | O61: Feito | P61: Feito | R61: 8 | S61: Assinado | T61: Junior Lopes
A62: 45686 | B62: 118426 | C62: Junior Lopes | D62: Polimax | E62: Cloud | F62: Mensalidade | G62: 1 | H62: 1643.4 | I62: =G62*H62 -> 1643.4 | J62: 1 | K62: =J62*0.25 -> 0.25 | L62: Não | M62: =J62*I62 -> 1643.4 | N62: =I62*K62 -> 410.85 | O62: Feito | P62: Feito | R62: 1 | S62: Assinado | T62: Junior Lopes
... A68: 45691 | B68: 118419 | C68: Rayssa Karapeticov | D68: Sultex | E68: MDe | F68: Mensalidade | G68: 1 | H68: 356.4 | I68: =G68*H68 -> 356.4 | J68: 1 | K68: =J68*0.25 -> 0.25 | L68: Sim | M68: =J68*I68 -> 356.4 | N68: =I68*K68 -> 89.1 | O68: Feito | P68: Feito | R68: 1 | S68: Assinado | T68: Rayssa Karapeticov
A69: 45697 | B69: 116965 | C69: Paulo Souza | D69: Newell Brands | E69: Melhoria | F69: Melhoria | G69: 9 | H69: 176 | I69: =G69*H69 -> 1584 | J69: 0.01 | K69: 0 | L69: Sim | M69: =J69*I69 -> 15.84 | N69: =I69*K69 -> 0 | O69: Não têm | P69: Não têm | R69: 3 | S69: Não têm | T69: Paulo Souza
A70: 45697 | B70: 118707 | C70: Rayssa Karapeticov | D70: Newell Brands | E70: Melhoria | F70: Melhoria | G70: 45 | H70: 176 | I70: =G70*H70 -> 7920 | J70: 0.01 | K70: =J70*0.25 -> 0.0025 | L70: Sim | M70: =J70*I70 -> 79.2 | N70: =I70*K70 -> 19.8 | O70: Não têm | P70: Não têm | R70: 3 | S70: Não têm | T70: Rayssa Karapeticov
A71: 45697 | B71: 106541 | C71: Paulo Souza | D71: Paramount | E71: Treinamento | F71: Treinamentos | G71: 34.5 | H71: 140 | I71: =G71*H71 -> 4830 | J71: 0.035 | K71: 0 | L71: Sim | M71: =J71*I71 -> 169.05 | N71: =I71*K71 -> 0 | O71: Não têm | P71: Não têm | R71: 1 | S71: Não têm | T71: Paulo Souza
A72: 45697 | B72: 118955 | C72: Rayssa Karapeticov | D72: Aluminio Nacional | E72: CNPJ | F72: CDU | G72: 1 | H72: 8311.97 | I72: =G72*H72 -> 8311.97 | J72: 0.07 | K72: =J72*0.25 -> 0.0175 | L72: Sim | M72: =J72*I72 -> 581.8379 | N72: =I72*K72 -> 145.45947 | O72: Feito | P72: Feito | R72: 6 | S72: Assinado | T72: Rayssa Karapeticov
A73: 45697 | B73: 118955 | C73: Rayssa Karapeticov | D73: Aluminio Nacional | E73: ERP | F73: Mensalidade | G73: 1 | H73: 361.39 | I73: =G73*H73 -> 361.39 | J73: 1 | K73: =J73*0.25 -> 0.25 | L73: Sim | M73: =J73*I73 -> 361.39 | N73: =I73*K73 -> 90.3475 | O73: Não têm | P73: Não têm | R73: 1 | S73: Não têm | T73: Rayssa Karapeticov
